[{"_id": "629aab94f707900007a9c54f", "category_tag_id": "54967e14ff43b99e284d0bf7", "title": "\u3010\u55b5\u840c\u5976\u8336\u5c4b\u3011\u260504\u6708\u65b0\u756a\u2605[Estab Life: Great Escape][01-12END][1080p][\u7e41\u9ad4][\u62db\u52df\u7ffb\u8b6f\u6821\u5c0d]", "introduction": "<p><img src=\"https://p.sda1.dev/5/401465fb62a0b9926e834d1c814b3192/wstablife_tv_1000.jpg\"></p>", "tag_ids": ["624774a270e8f89b23a18556", "58a9c1e6f5dc363606ab42ed", "549ef207fe682f7549f1ea90", "548ee1204ab7379536f56357", "548ee2ce4ab7379536f56358", "54967e14ff43b99e284d0bf7"], "comments": 0, "downloads": 100, "finished": 637, "leechers": 4, "seeders": 25, "uploader_id": "59842d4fde238a777bf95202", "team_id": "58a9c1c9f5dc363606ab42ec", "publish_time": "2022-06-04T00:47:16.510Z", "magnet": "magnet:?xt=urn:btih:d0723114d7eb8688feed3cddfc9b2fd21ab6aec8", "infoHash": "d0723114d7eb8688feed3cddfc9b2fd21ab6aec8", "file_id": "629aab7ef707900007a9c50c", "teamsync": true, "content": [["[Nekomoe kissaten][Estab Life - Great Escape][01-12][1080p][CHT]/[Nekomoe kissaten][Estab Life - Great Escape][01][1080p][CHT].mp4", "574.8 MB"], ["[Nekomoe kissaten][Estab Life - Great Escape][01-12][1080p][CHT]/[Nekomoe kissaten][Estab Life - Great Escape][02][1080p][CHT].mp4", "527.41 MB"], ["[Nekomoe kissaten][Estab Life - Great Escape][01-12][1080p][CHT]/[Nekomoe kissaten][Estab Life - Great Escape][03][1080p][CHT].mp4", "615.39 MB"], ["[Nekomoe kissaten][Estab Life - Great Escape][01-12][1080p][CHT]/[Nekomoe kissaten][Estab Life - Great Escape][04][1080p][CHT].mp4", "647.29 MB"], ["[Nekomoe kissaten][Estab Life - Great Escape][01-12][1080p][CHT]/[Nekomoe kissaten][Estab Life - Great Escape][05][1080p][CHT].mp4", "616.76 MB"], ["[Nekomoe kissaten][Estab Life - Great Escape][01-12][1080p][CHT]/[Nekomoe kissaten][Estab Life - Great Escape][06][1080p][CHT].mp4", "517.84 MB"], ["[Nekomoe kissaten][Estab Life - Great Escape][01-12][1080p][CHT]/[Nekomoe kissaten][Estab Life - Great Escape][07][1080p][CHT].mp4", "514.61 MB"], ["[Nekomoe kissaten][Estab Life - Great Escape][01-12][1080p][CHT]/[Nekomoe kissaten][Estab Life - Great Escape][08][1080p][CHT].mp4", "428.68 MB"], ["[Nekomoe kissaten][Estab Life - Great Escape][01-12][1080p][CHT]/[Nekomoe kissaten][Estab Life - Great Escape][09][1080p][CHT].mp4", "675.5 MB"], ["[Nekomoe kissaten][Estab Life - Great Escape][01-12][1080p][CHT]/[Nekomoe kissaten][Estab Life - Great Escape][10][1080p][CHT].mp4", "626.26 MB"], ["[Nekomoe kissaten][Estab Life - Great Escape][01-12][1080p][CHT]/[Nekomoe kissaten][Estab Life - Great Escape][11][1080p][CHT].mp4", "726.85 MB"], ["[Nekomoe kissaten][Estab Life - Great Escape][01-12][1080p][CHT]/[Nekomoe kissaten][Estab Life - Great Escape][12][1080p][CHT].mp4", "755.16 MB"]], "size": "7.06 GB", "btskey": "", "sync": {"dmhy": "http://share.dmhy.org/topics/view/602042_04_Estab_Life_Great_Escape_01-12END_1080p.html", "acgrip": "https://acg.rip/t/256614", "nyaa": "https://nyaa.si/view/1537157", "acgnx": "https://share.acgnx.se/show-d0723114d7eb8688feed3cddfc9b2fd21ab6aec8.html", "acgnx_int": "https://www.acgnx.se/show-d0723114d7eb8688feed3cddfc9b2fd21ab6aec8.html"}}, {"_id": "629aab75f707900007a9c4f6", "category_tag_id": "54967e14ff43b99e284d0bf7", "title": "\u3010\u55b5\u840c\u5976\u8336\u5c4b\u3011\u260504\u6708\u65b0\u756a\u2605[Estab Life: Great Escape][01-12END][1080p][\u7b80\u4f53][\u62db\u52df\u7ffb\u8bd1\u6821\u5bf9]", "introduction": "<p><img src=\"https://p.sda1.dev/5/401465fb62a0b9926e834d1c814b3192/wstablife_tv_1000.jpg\"></p>", "tag_ids": ["58a9c1e6f5dc363606ab42ed", "548ee0ea4ab7379536f56354", "549ef207fe682f7549f1ea90", "624774a270e8f89b23a18556", "54967e14ff43b99e284d0bf7", "548ee2ce4ab7379536f56358"], "comments": 0, "downloads": 99, "finished": 383, "leechers": 0, "seeders": 47, "uploader_id": "59842d4fde238a777bf95202", "team_id": "58a9c1c9f5dc363606ab42ec", "publish_time": "2022-06-04T00:46:45.240Z", "magnet": "magnet:?xt=urn:btih:7c9d8b45894fd8cc95dca1c4433c4c004a1eba0e", "infoHash": "7c9d8b45894fd8cc95dca1c4433c4c004a1eba0e", "file_id": "629aab67f707900007a9c4ce", "teamsync": true, "content": [["[Nekomoe kissaten][Estab Life - Great Escape][01-12][1080p][CHS]/[Nekomoe kissaten][Estab Life - Great Escape][01][1080p][CHS].mp4", "574.74 MB"], ["[Nekomoe kissaten][Estab Life - Great Escape][01-12][1080p][CHS]/[Nekomoe kissaten][Estab Life - Great Escape][02][1080p][CHS].mp4", "527.07 MB"], ["[Nekomoe kissaten][Estab Life - Great Escape][01-12][1080p][CHS]/[Nekomoe kissaten][Estab Life - Great Escape][03][1080p][CHS].mp4", "615.33 MB"], ["[Nekomoe kissaten][Estab Life - Great Escape][01-12][1080p][CHS]/[Nekomoe kissaten][Estab Life - Great Escape][04][1080p][CHS].mp4", "647.37 MB"], ["[Nekomoe kissaten][Estab Life - Great Escape][01-12][1080p][CHS]/[Nekomoe kissaten][Estab Life - Great Escape][05][1080p][CHS].mp4", "616.74 MB"], ["[Nekomoe kissaten][Estab Life - Great Escape][01-12][1080p][CHS]/[Nekomoe kissaten][Estab Life - Great Escape][06][1080p][CHS].mp4", "517.8 MB"], ["[Nekomoe kissaten][Estab Life - Great Escape][01-12][1080p][CHS]/[Nekomoe kissaten][Estab Life - Great Escape][07][1080p][CHS].mp4", "514.54 MB"], ["[Nekomoe kissaten][Estab Life - Great Escape][01-12][1080p][CHS]/[Nekomoe kissaten][Estab Life - Great Escape][08][1080p][CHS].mp4", "428.91 MB"], ["[Nekomoe kissaten][Estab Life - Great Escape][01-12][1080p][CHS]/[Nekomoe kissaten][Estab Life - Great Escape][09][1080p][CHS].mp4", "675.46 MB"], ["[Nekomoe kissaten][Estab Life - Great Escape][01-12][1080p][CHS]/[Nekomoe kissaten][Estab Life - Great Escape][10][1080p][CHS].mp4", "626.21 MB"], ["[Nekomoe kissaten][Estab Life - Great Escape][01-12][1080p][CHS]/[Nekomoe kissaten][Estab Life - Great Escape][11][1080p][CHS].mp4", "726.94 MB"], ["[Nekomoe kissaten][Estab Life - Great Escape][01-12][1080p][CHS]/[Nekomoe kissaten][Estab Life - Great Escape][12][1080p][CHS].mp4", "755.23 MB"]], "size": "7.06 GB", "btskey": "", "sync": {"dmhy": "http://share.dmhy.org/topics/view/602041_04_Estab_Life_Great_Escape_01-12END_1080p.html", "acgrip": "https://acg.rip/t/256613", "nyaa": "https://nyaa.si/view/1537156", "acgnx": "https://share.acgnx.se/show-7c9d8b45894fd8cc95dca1c4433c4c004a1eba0e.html", "acgnx_int": "https://www.acgnx.se/show-7c9d8b45894fd8cc95dca1c4433c4c004a1eba0e.html"}}, {"_id": "629aab62f707900007a9c4bb", "category_tag_id": "54967e14ff43b99e284d0bf7", "title": "\u3010\u55b5\u840c\u5976\u8336\u5c4b\u3011\u260504\u6708\u65b0\u756a\u2605[Estab Life: Great Escape][01-12END][720p][\u7e41\u9ad4][\u62db\u52df\u7ffb\u8b6f\u6821\u5c0d]", "introduction": "<p><img src=\"https://p.sda1.dev/5/401465fb62a0b9926e834d1c814b3192/wstablife_tv_1000.jpg\"></p>", "tag_ids": ["624774a270e8f89b23a18556", "58a9c1e6f5dc363606ab42ed", "548edfb54ab7379536f56351", "549ef207fe682f7549f1ea90", "548ee1204ab7379536f56357", "54967e14ff43b99e284d0bf7"], "comments": 0, "downloads": 78, "finished": 366, "leechers": 4, "seeders": 10, "uploader_id": "59842d4fde238a777bf95202", "team_id": "58a9c1c9f5dc363606ab42ec", "publish_time": "2022-06-04T00:46:26.333Z", "magnet": "magnet:?xt=urn:btih:2ff8c04263443a97cc80b082fe526eb1b587f92f", "infoHash": "2ff8c04263443a97cc80b082fe526eb1b587f92f", "file_id": "629aab52f707900007a9c498", "teamsync": true, "content": [["[Nekomoe kissaten][Estab Life - Great Escape][01-12][720p][CHT]/[Nekomoe kissaten][Estab Life - Great Escape][01][720p][CHT].mp4", "277.42 MB"], ["[Nekomoe kissaten][Estab Life - Great Escape][01-12][720p][CHT]/[Nekomoe kissaten][Estab Life - Great Escape][02][720p][CHT].mp4", "253.36 MB"], ["[Nekomoe kissaten][Estab Life - Great Escape][01-12][720p][CHT]/[Nekomoe kissaten][Estab Life - Great Escape][03][720p][CHT].mp4", "290.27 MB"], ["[Nekomoe kissaten][Estab Life - Great Escape][01-12][720p][CHT]/[Nekomoe kissaten][Estab Life - Great Escape][04][720p][CHT].mp4", "308.61 MB"], ["[Nekomoe kissaten][Estab Life - Great Escape][01-12][720p][CHT]/[Nekomoe kissaten][Estab Life - Great Escape][05][720p][CHT].mp4", "299.41 MB"], ["[Nekomoe kissaten][Estab Life - Great Escape][01-12][720p][CHT]/[Nekomoe kissaten][Estab Life - Great Escape][06][720p][CHT].mp4", "251.58 MB"], ["[Nekomoe kissaten][Estab Life - Great Escape][01-12][720p][CHT]/[Nekomoe kissaten][Estab Life - Great Escape][07][720p][CHT].mp4", "244.46 MB"], ["[Nekomoe kissaten][Estab Life - Great Escape][01-12][720p][CHT]/[Nekomoe kissaten][Estab Life - Great Escape][08][720p][CHT].mp4", "203.6 MB"], ["[Nekomoe kissaten][Estab Life - Great Escape][01-12][720p][CHT]/[Nekomoe kissaten][Estab Life - Great Escape][09][720p][CHT].mp4", "321.54 MB"], ["[Nekomoe kissaten][Estab Life - Great Escape][01-12][720p][CHT]/[Nekomoe kissaten][Estab Life - Great Escape][10][720p][CHT].mp4", "295.18 MB"], ["[Nekomoe kissaten][Estab Life - Great Escape][01-12][720p][CHT]/[Nekomoe kissaten][Estab Life - Great Escape][11][720p][CHT].mp4", "346.77 MB"], ["[Nekomoe kissaten][Estab Life - Great Escape][01-12][720p][CHT]/[Nekomoe kissaten][Estab Life - Great Escape][12][720p][CHT].mp4", "363.29 MB"]], "size": "3.37 GB", "btskey": "", "sync": {"dmhy": "http://share.dmhy.org/topics/view/602040_04_Estab_Life_Great_Escape_01-12END_720p.html", "acgrip": "https://acg.rip/t/256612", "nyaa": "https://nyaa.si/view/1537155", "acgnx": "https://share.acgnx.se/show-2ff8c04263443a97cc80b082fe526eb1b587f92f.html", "acgnx_int": "https://www.acgnx.se/show-2ff8c04263443a97cc80b082fe526eb1b587f92f.html"}}, {"_id": "629aab4df707900007a9c48e", "category_tag_id": "54967e14ff43b99e284d0bf7", "title": "\u3010\u55b5\u840c\u5976\u8336\u5c4b\u3011\u260504\u6708\u65b0\u756a\u2605[Estab Life: Great Escape][01-12END][720p][\u7b80\u4f53][\u62db\u52df\u7ffb\u8bd1\u6821\u5bf9]", "introduction": "<p><img src=\"https://p.sda1.dev/5/401465fb62a0b9926e834d1c814b3192/wstablife_tv_1000.jpg\"></p>", "tag_ids": ["58a9c1e6f5dc363606ab42ed", "548edfb54ab7379536f56351", "548ee0ea4ab7379536f56354", "549ef207fe682f7549f1ea90", "624774a270e8f89b23a18556", "54967e14ff43b99e284d0bf7"], "comments": 0, "downloads": 71, "finished": 137, "leechers": 0, "seeders": 5, "uploader_id": "59842d4fde238a777bf95202", "team_id": "58a9c1c9f5dc363606ab42ec", "publish_time": "2022-06-04T00:46:05.944Z", "magnet": "magnet:?xt=urn:btih:1a7029e6c85772d5c2a11a1582c158abc062adaa", "infoHash": "1a7029e6c85772d5c2a11a1582c158abc062adaa", "file_id": "629aab27f707900007a9c424", "teamsync": true, "content": [["[Nekomoe kissaten][Estab Life - Great Escape][01-12][720p][CHS]/[Nekomoe kissaten][Estab Life - Great Escape][01][720p][CHS].mp4", "277.54 MB"], ["[Nekomoe kissaten][Estab Life - Great Escape][01-12][720p][CHS]/[Nekomoe kissaten][Estab Life - Great Escape][02][720p][CHS].mp4", "253.37 MB"], ["[Nekomoe kissaten][Estab Life - Great Escape][01-12][720p][CHS]/[Nekomoe kissaten][Estab Life - Great Escape][03][720p][CHS].mp4", "290.21 MB"], ["[Nekomoe kissaten][Estab Life - Great Escape][01-12][720p][CHS]/[Nekomoe kissaten][Estab Life - Great Escape][04][720p][CHS].mp4", "308.51 MB"], ["[Nekomoe kissaten][Estab Life - Great Escape][01-12][720p][CHS]/[Nekomoe kissaten][Estab Life - Great Escape][05][720p][CHS].mp4", "299.49 MB"], ["[Nekomoe kissaten][Estab Life - Great Escape][01-12][720p][CHS]/[Nekomoe kissaten][Estab Life - Great Escape][06][720p][CHS].mp4", "251.55 MB"], ["[Nekomoe kissaten][Estab Life - Great Escape][01-12][720p][CHS]/[Nekomoe kissaten][Estab Life - Great Escape][07][720p][CHS].mp4", "244.43 MB"], ["[Nekomoe kissaten][Estab Life - Great Escape][01-12][720p][CHS]/[Nekomoe kissaten][Estab Life - Great Escape][08][720p][CHS].mp4", "203.57 MB"], ["[Nekomoe kissaten][Estab Life - Great Escape][01-12][720p][CHS]/[Nekomoe kissaten][Estab Life - Great Escape][09][720p][CHS].mp4", "321.61 MB"], ["[Nekomoe kissaten][Estab Life - Great Escape][01-12][720p][CHS]/[Nekomoe kissaten][Estab Life - Great Escape][10][720p][CHS].mp4", "295.12 MB"], ["[Nekomoe kissaten][Estab Life - Great Escape][01-12][720p][CHS]/[Nekomoe kissaten][Estab Life - Great Escape][11][720p][CHS].mp4", "346.74 MB"], ["[Nekomoe kissaten][Estab Life - Great Escape][01-12][720p][CHS]/[Nekomoe kissaten][Estab Life - Great Escape][12][720p][CHS].mp4", "363.23 MB"]], "size": "3.37 GB", "btskey": "", "sync": {"dmhy": "http://share.dmhy.org/topics/view/602039_04_Estab_Life_Great_Escape_01-12END_720p.html", "acgrip": "https://acg.rip/t/256611", "nyaa": "https://nyaa.si/view/1537154", "acgnx": "https://share.acgnx.se/show-1a7029e6c85772d5c2a11a1582c158abc062adaa.html", "acgnx_int": "https://www.acgnx.se/show-1a7029e6c85772d5c2a11a1582c158abc062adaa.html"}}, {"_id": "6298cb7d3d2af000077bd5ef", "category_tag_id": "549ef207fe682f7549f1ea90", "title": "\u3010\u55b5\u840c\u5976\u8336\u5c4b\u3011\u260504\u6708\u65b0\u756a\u2605[Estab Life: Great Escape][12END][1080p][\u7e41\u9ad4][\u62db\u52df\u7ffb\u8b6f\u6821\u5c0d]", "introduction": "<p><img src=\"https://p.sda1.dev/5/401465fb62a0b9926e834d1c814b3192/wstablife_tv_1000.jpg\"></p>", "tag_ids": ["624774a270e8f89b23a18556", "58a9c1e6f5dc363606ab42ed", "549ef207fe682f7549f1ea90", "548ee1204ab7379536f56357", "548ee2ce4ab7379536f56358"], "comments": 0, "downloads": 104, "finished": 634, "leechers": 0, "seeders": 16, "uploader_id": "59842d4fde238a777bf95202", "team_id": "58a9c1c9f5dc363606ab42ec", "publish_time": "2022-06-02T14:38:53.887Z", "magnet": "magnet:?xt=urn:btih:8e8172b06e0510e914356858a4636fa0e80f5384", "infoHash": "8e8172b06e0510e914356858a4636fa0e80f5384", "file_id": "6298cb793d2af000077bd5e5", "teamsync": true, "content": [["[Nekomoe kissaten][Estab Life - Great Escape][12][1080p][CHT].mp4", "755.16 MB"]], "size": "755.16 MB", "btskey": "", "sync": {"dmhy": "http://share.dmhy.org/topics/view/601888_04_Estab_Life_Great_Escape_12END_1080p.html", "acgrip": "https://acg.rip/t/256515", "nyaa": "https://nyaa.si/view/1536470", "acgnx": "https://share.acgnx.se/show-8e8172b06e0510e914356858a4636fa0e80f5384.html", "acgnx_int": "https://www.acgnx.se/show-8e8172b06e0510e914356858a4636fa0e80f5384.html"}}, {"_id": "6298cb763d2af000077bd5d4", "category_tag_id": "549ef207fe682f7549f1ea90", "title": "\u3010\u55b5\u840c\u5976\u8336\u5c4b\u3011\u260504\u6708\u65b0\u756a\u2605[Estab Life: Great Escape][12END][1080p][\u7b80\u4f53][\u62db\u52df\u7ffb\u8bd1\u6821\u5bf9]", "introduction": "<p><img src=\"https://p.sda1.dev/5/401465fb62a0b9926e834d1c814b3192/wstablife_tv_1000.jpg\"></p>", "tag_ids": ["624774a270e8f89b23a18556", "58a9c1e6f5dc363606ab42ed", "549ef207fe682f7549f1ea90", "548ee0ea4ab7379536f56354", "548ee2ce4ab7379536f56358"], "comments": 0, "downloads": 107, "finished": 624, "leechers": 0, "seeders": 37, "uploader_id": "59842d4fde238a777bf95202", "team_id": "58a9c1c9f5dc363606ab42ec", "publish_time": "2022-06-02T14:38:46.373Z", "magnet": "magnet:?xt=urn:btih:52f2f619adf29e5b3d64ecfa8b8cfcdd96b647ef", "infoHash": "52f2f619adf29e5b3d64ecfa8b8cfcdd96b647ef", "file_id": "6298cb723d2af000077bd5c7", "teamsync": true, "content": [["[Nekomoe kissaten][Estab Life - Great Escape][12][1080p][CHS].mp4", "755.23 MB"]], "size": "755.23 MB", "btskey": "", "sync": {"dmhy": "http://share.dmhy.org/topics/view/601887_04_Estab_Life_Great_Escape_12END_1080p.html", "acgrip": "https://acg.rip/t/256515", "nyaa": "https://nyaa.si/view/1536469", "acgnx": "https://share.acgnx.se/show-52f2f619adf29e5b3d64ecfa8b8cfcdd96b647ef.html", "acgnx_int": "https://www.acgnx.se/show-52f2f619adf29e5b3d64ecfa8b8cfcdd96b647ef.html"}}, {"_id": "6298cb6e3d2af000077bd5ba", "category_tag_id": "549ef207fe682f7549f1ea90", "title": "\u3010\u55b5\u840c\u5976\u8336\u5c4b\u3011\u260504\u6708\u65b0\u756a\u2605[Estab Life: Great Escape][12END][720p][\u7e41\u9ad4][\u62db\u52df\u7ffb\u8b6f\u6821\u5c0d]", "introduction": "<p><img src=\"https://p.sda1.dev/5/401465fb62a0b9926e834d1c814b3192/wstablife_tv_1000.jpg\"></p>", "tag_ids": ["624774a270e8f89b23a18556", "58a9c1e6f5dc363606ab42ed", "548edfb54ab7379536f56351", "549ef207fe682f7549f1ea90", "548ee1204ab7379536f56357"], "comments": 0, "downloads": 85, "finished": 442, "leechers": 0, "seeders": 3, "uploader_id": "59842d4fde238a777bf95202", "team_id": "58a9c1c9f5dc363606ab42ec", "publish_time": "2022-06-02T14:38:38.213Z", "magnet": "magnet:?xt=urn:btih:8bec2647fc148f57a68f61152e722d5e686326ad", "infoHash": "8bec2647fc148f57a68f61152e722d5e686326ad", "file_id": "6298cb5f3d2af000077bd598", "teamsync": true, "content": [["[Nekomoe kissaten][Estab Life - Great Escape][12][720p][CHT].mp4", "363.29 MB"]], "size": "363.29 MB", "btskey": "", "sync": {"dmhy": "http://share.dmhy.org/topics/view/601886_04_Estab_Life_Great_Escape_12END_720p.html", "acgrip": "https://acg.rip/t/256514", "nyaa": "https://nyaa.si/view/1536468", "acgnx": "https://share.acgnx.se/show-8bec2647fc148f57a68f61152e722d5e686326ad.html", "acgnx_int": "https://www.acgnx.se/show-8bec2647fc148f57a68f61152e722d5e686326ad.html"}}, {"_id": "6298cb583d2af000077bd588", "category_tag_id": "549ef207fe682f7549f1ea90", "title": "\u3010\u55b5\u840c\u5976\u8336\u5c4b\u3011\u260504\u6708\u65b0\u756a\u2605[Estab Life: Great Escape][12END][720p][\u7b80\u4f53][\u62db\u52df\u7ffb\u8bd1\u6821\u5bf9]", "introduction": "<p><img src=\"https://p.sda1.dev/5/401465fb62a0b9926e834d1c814b3192/wstablife_tv_1000.jpg\"></p>", "tag_ids": ["548edfb54ab7379536f56351", "624774a270e8f89b23a18556", "58a9c1e6f5dc363606ab42ed", "548ee0ea4ab7379536f56354", "549ef207fe682f7549f1ea90"], "comments": 0, "downloads": 76, "finished": 191, "leechers": 0, "seeders": 2, "uploader_id": "59842d4fde238a777bf95202", "team_id": "58a9c1c9f5dc363606ab42ec", "publish_time": "2022-06-02T14:38:16.259Z", "magnet": "magnet:?xt=urn:btih:1faaefd3be47c62334e3b8535e04af36b605b108", "infoHash": "1faaefd3be47c62334e3b8535e04af36b605b108", "file_id": "6298cb363d2af000077bd539", "teamsync": true, "content": [["[Nekomoe kissaten][Estab Life - Great Escape][12][720p][CHS].mp4", "363.23 MB"]], "size": "363.23 MB", "btskey": "", "sync": {"dmhy": "http://share.dmhy.org/topics/view/601885_04_Estab_Life_Great_Escape_12END_720p.html", "acgrip": "https://acg.rip/t/256512", "nyaa": "https://nyaa.si/view/1536467", "acgnx": "https://share.acgnx.se/show-1faaefd3be47c62334e3b8535e04af36b605b108.html", "acgnx_int": "https://www.acgnx.se/show-1faaefd3be47c62334e3b8535e04af36b605b108.html"}}, {"_id": "628fa9293d5c310007813b03", "category_tag_id": "549ef207fe682f7549f1ea90", "title": "\u3010\u55b5\u840c\u5976\u8336\u5c4b\u3011\u260504\u6708\u65b0\u756a\u2605[Estab Life: Great Escape][11][1080p][\u7e41\u9ad4][\u62db\u52df\u7ffb\u8b6f\u6821\u5c0d]", "introduction": "<p><img src=\"https://p.sda1.dev/5/401465fb62a0b9926e834d1c814b3192/wstablife_tv_1000.jpg\"></p>", "tag_ids": ["624774a270e8f89b23a18556", "58a9c1e6f5dc363606ab42ed", "548ee1204ab7379536f56357", "549ef207fe682f7549f1ea90", "548ee2ce4ab7379536f56358"], "comments": 0, "downloads": 126, "finished": 688, "leechers": 0, "seeders": 6, "uploader_id": "59842d4fde238a777bf95202", "team_id": "58a9c1c9f5dc363606ab42ec", "publish_time": "2022-05-26T16:22:01.727Z", "magnet": "magnet:?xt=urn:btih:077c59a8c3e94c900a132db0910f44171117f5c9", "infoHash": "077c59a8c3e94c900a132db0910f44171117f5c9", "file_id": "628fa91f3d5c310007813ae7", "teamsync": true, "content": [["[Nekomoe kissaten][Estab Life - Great Escape][11][1080p][CHT].mp4", "727.01 MB"]], "size": "727.01 MB", "btskey": "", "sync": {"dmhy": "http://share.dmhy.org/topics/view/601286_04_Estab_Life_Great_Escape_11_1080p.html", "acgrip": "https://acg.rip/t/256176", "nyaa": "https://nyaa.si/view/1533391", "acgnx": "https://share.acgnx.se/show-077c59a8c3e94c900a132db0910f44171117f5c9.html", "acgnx_int": "https://www.acgnx.se/show-077c59a8c3e94c900a132db0910f44171117f5c9.html"}}, {"_id": "628fa91a3d5c310007813ada", "category_tag_id": "549ef207fe682f7549f1ea90", "title": "\u3010\u55b5\u840c\u5976\u8336\u5c4b\u3011\u260504\u6708\u65b0\u756a\u2605[Estab Life: Great Escape][11][1080p][\u7b80\u4f53][\u62db\u52df\u7ffb\u8bd1\u6821\u5bf9]", "introduction": "<p><img src=\"https://p.sda1.dev/5/401465fb62a0b9926e834d1c814b3192/wstablife_tv_1000.jpg\"></p>", "tag_ids": ["624774a270e8f89b23a18556", "58a9c1e6f5dc363606ab42ed", "549ef207fe682f7549f1ea90", "548ee0ea4ab7379536f56354", "548ee2ce4ab7379536f56358"], "comments": 0, "downloads": 127, "finished": 664, "leechers": 0, "seeders": 34, "uploader_id": "59842d4fde238a777bf95202", "team_id": "58a9c1c9f5dc363606ab42ec", "publish_time": "2022-05-26T16:21:46.213Z", "magnet": "magnet:?xt=urn:btih:e0b253c5e205604c39716bf54941dbb2bb1c4e62", "infoHash": "e0b253c5e205604c39716bf54941dbb2bb1c4e62", "file_id": "628fa9153d5c310007813ad2", "teamsync": true, "content": [["[Nekomoe kissaten][Estab Life - Great Escape][11][1080p][CHS].mp4", "727.09 MB"]], "size": "727.09 MB", "btskey": "", "sync": {"dmhy": "http://share.dmhy.org/topics/view/601285_04_Estab_Life_Great_Escape_11_1080p.html", "acgrip": "https://acg.rip/t/256175", "nyaa": "https://nyaa.si/view/1533390", "acgnx": "https://share.acgnx.se/show-e0b253c5e205604c39716bf54941dbb2bb1c4e62.html", "acgnx_int": "https://www.acgnx.se/show-e0b253c5e205604c39716bf54941dbb2bb1c4e62.html"}}, {"_id": "628fa90e3d5c310007813ac3", "category_tag_id": "549ef207fe682f7549f1ea90", "title": "\u3010\u55b5\u840c\u5976\u8336\u5c4b\u3011\u260504\u6708\u65b0\u756a\u2605[Estab Life: Great Escape][11][720p][\u7e41\u9ad4][\u62db\u52df\u7ffb\u8b6f\u6821\u5c0d]", "introduction": "<p><img src=\"https://p.sda1.dev/5/401465fb62a0b9926e834d1c814b3192/wstablife_tv_1000.jpg\"></p>", "tag_ids": ["624774a270e8f89b23a18556", "58a9c1e6f5dc363606ab42ed", "548ee1204ab7379536f56357", "549ef207fe682f7549f1ea90", "548edfb54ab7379536f56351"], "comments": 0, "downloads": 81, "finished": 460, "leechers": 1, "seeders": 4, "uploader_id": "59842d4fde238a777bf95202", "team_id": "58a9c1c9f5dc363606ab42ec", "publish_time": "2022-05-26T16:21:34.727Z", "magnet": "magnet:?xt=urn:btih:115f2b1525ce2dc683e9d4065ca0a8e206fefaa6", "infoHash": "115f2b1525ce2dc683e9d4065ca0a8e206fefaa6", "file_id": "628fa8f93d5c310007813aa4", "teamsync": true, "content": [["[Nekomoe kissaten][Estab Life - Great Escape][11][720p][CHT].mp4", "346.89 MB"]], "size": "346.89 MB", "btskey": "", "sync": {"dmhy": "http://share.dmhy.org/topics/view/601284_04_Estab_Life_Great_Escape_11_720p.html", "acgrip": "https://acg.rip/t/256174", "nyaa": "https://nyaa.si/view/1533389", "acgnx": "https://share.acgnx.se/show-115f2b1525ce2dc683e9d4065ca0a8e206fefaa6.html", "acgnx_int": "https://www.acgnx.se/show-115f2b1525ce2dc683e9d4065ca0a8e206fefaa6.html"}}, {"_id": "628fa8c43d5c310007813a3c", "category_tag_id": "549ef207fe682f7549f1ea90", "title": "\u3010\u55b5\u840c\u5976\u8336\u5c4b\u3011\u260504\u6708\u65b0\u756a\u2605[Estab Life: Great Escape][11][720p][\u7b80\u4f53][\u62db\u52df\u7ffb\u8bd1\u6821\u5bf9]", "introduction": "<p><img src=\"https://p.sda1.dev/5/401465fb62a0b9926e834d1c814b3192/wstablife_tv_1000.jpg\"></p>", "tag_ids": ["624774a270e8f89b23a18556", "58a9c1e6f5dc363606ab42ed", "549ef207fe682f7549f1ea90", "548ee0ea4ab7379536f56354", "548edfb54ab7379536f56351"], "comments": 0, "downloads": 75, "finished": 199, "leechers": 0, "seeders": 2, "uploader_id": "59842d4fde238a777bf95202", "team_id": "58a9c1c9f5dc363606ab42ec", "publish_time": "2022-05-26T16:20:20.746Z", "magnet": "magnet:?xt=urn:btih:e1297385057ce10c32ceeecc043300fce774a8ee", "infoHash": "e1297385057ce10c32ceeecc043300fce774a8ee", "file_id": "628fa8b13d5c310007813a20", "teamsync": true, "content": [["[Nekomoe kissaten][Estab Life - Great Escape][11][720p][CHS].mp4", "346.85 MB"]], "size": "346.85 MB", "btskey": "", "sync": {"dmhy": "http://share.dmhy.org/topics/view/601283_04_Estab_Life_Great_Escape_11_720p.html", "acgrip": "https://acg.rip/t/256173", "nyaa": "https://nyaa.si/view/1533388", "acgnx": "https://share.acgnx.se/show-e1297385057ce10c32ceeecc043300fce774a8ee.html", "acgnx_int": "https://www.acgnx.se/show-e1297385057ce10c32ceeecc043300fce774a8ee.html"}}, {"_id": "6288f93b3d5c31000774b0b1", "category_tag_id": "549ef207fe682f7549f1ea90", "title": "\u3010\u55b5\u840c\u5976\u8336\u5c4b\u3011\u260504\u6708\u65b0\u756a\u2605[Estab Life: Great Escape][10][1080p][\u7e41\u9ad4][\u62db\u52df\u7ffb\u8b6f\u6821\u5c0d]", "introduction": "<p><img src=\"https://p.sda1.dev/5/401465fb62a0b9926e834d1c814b3192/wstablife_tv_1000.jpg\"></p>", "tag_ids": ["624774a270e8f89b23a18556", "58a9c1e6f5dc363606ab42ed", "549ef207fe682f7549f1ea90", "548ee1204ab7379536f56357", "548ee2ce4ab7379536f56358"], "comments": 0, "downloads": 105, "finished": 764, "leechers": 1, "seeders": 10, "uploader_id": "59842d4fde238a777bf95202", "team_id": "58a9c1c9f5dc363606ab42ec", "publish_time": "2022-05-21T14:37:47.905Z", "magnet": "magnet:?xt=urn:btih:f7f46d9e8048358a0e9c9752e3909aaf2d85e81c", "infoHash": "f7f46d9e8048358a0e9c9752e3909aaf2d85e81c", "file_id": "6288f9373d5c31000774b0a5", "teamsync": true, "content": [["[Nekomoe kissaten][Estab Life - Great Escape][10][1080p][CHT].mp4", "626.26 MB"]], "size": "626.26 MB", "btskey": "", "sync": {"dmhy": "http://share.dmhy.org/topics/view/600861_04_Estab_Life_Great_Escape_10_1080p.html", "acgrip": "https://acg.rip/t/255859", "nyaa": "https://nyaa.si/view/1531306", "acgnx": "https://share.acgnx.se/show-f7f46d9e8048358a0e9c9752e3909aaf2d85e81c.html", "acgnx_int": "https://www.acgnx.se/show-f7f46d9e8048358a0e9c9752e3909aaf2d85e81c.html"}}, {"_id": "6288f9323d5c31000774b091", "category_tag_id": "549ef207fe682f7549f1ea90", "title": "\u3010\u55b5\u840c\u5976\u8336\u5c4b\u3011\u260504\u6708\u65b0\u756a\u2605[Estab Life: Great Escape][10][1080p][\u7b80\u4f53][\u62db\u52df\u7ffb\u8bd1\u6821\u5bf9]", "introduction": "<p><img src=\"https://p.sda1.dev/5/401465fb62a0b9926e834d1c814b3192/wstablife_tv_1000.jpg\"></p>", "tag_ids": ["624774a270e8f89b23a18556", "58a9c1e6f5dc363606ab42ed", "548ee0ea4ab7379536f56354", "549ef207fe682f7549f1ea90", "548ee2ce4ab7379536f56358"], "comments": 0, "downloads": 105, "finished": 622, "leechers": 0, "seeders": 29, "uploader_id": "59842d4fde238a777bf95202", "team_id": "58a9c1c9f5dc363606ab42ec", "publish_time": "2022-05-21T14:37:38.382Z", "magnet": "magnet:?xt=urn:btih:6783ab123a1e22debdb21b7099bbd095f46c4fc0", "infoHash": "6783ab123a1e22debdb21b7099bbd095f46c4fc0", "file_id": "6288f92d3d5c31000774b083", "teamsync": true, "content": [["[Nekomoe kissaten][Estab Life - Great Escape][10][1080p][CHS].mp4", "626.22 MB"]], "size": "626.22 MB", "btskey": "", "sync": {"dmhy": "http://share.dmhy.org/topics/view/600860_04_Estab_Life_Great_Escape_10_1080p.html", "acgrip": "https://acg.rip/t/255858", "nyaa": "https://nyaa.si/view/1531305", "acgnx": "https://share.acgnx.se/show-6783ab123a1e22debdb21b7099bbd095f46c4fc0.html", "acgnx_int": "https://www.acgnx.se/show-6783ab123a1e22debdb21b7099bbd095f46c4fc0.html"}}, {"_id": "6288f9273d5c31000774b078", "category_tag_id": "549ef207fe682f7549f1ea90", "title": "\u3010\u55b5\u840c\u5976\u8336\u5c4b\u3011\u260504\u6708\u65b0\u756a\u2605[Estab Life: Great Escape][10][720p][\u7e41\u9ad4][\u62db\u52df\u7ffb\u8b6f\u6821\u5c0d]", "introduction": "<p><img src=\"https://p.sda1.dev/5/401465fb62a0b9926e834d1c814b3192/wstablife_tv_1000.jpg\"></p>", "tag_ids": ["548edfb54ab7379536f56351", "624774a270e8f89b23a18556", "58a9c1e6f5dc363606ab42ed", "549ef207fe682f7549f1ea90", "548ee1204ab7379536f56357"], "comments": 0, "downloads": 72, "finished": 532, "leechers": 0, "seeders": 3, "uploader_id": "59842d4fde238a777bf95202", "team_id": "58a9c1c9f5dc363606ab42ec", "publish_time": "2022-05-21T14:37:27.664Z", "magnet": "magnet:?xt=urn:btih:a68753612c0dbd41097e2e3adcae1fe7e94f8bf8", "infoHash": "a68753612c0dbd41097e2e3adcae1fe7e94f8bf8", "file_id": "6288f9143d5c31000774b050", "teamsync": true, "content": [["[Nekomoe kissaten][Estab Life - Great Escape][10][720p][CHT].mp4", "295.18 MB"]], "size": "295.18 MB", "btskey": "", "sync": {"dmhy": "http://share.dmhy.org/topics/view/600859_04_Estab_Life_Great_Escape_10_720p.html", "acgrip": "https://acg.rip/t/255857", "nyaa": "https://nyaa.si/view/1531304", "acgnx": "https://share.acgnx.se/show-a68753612c0dbd41097e2e3adcae1fe7e94f8bf8.html", "acgnx_int": "https://www.acgnx.se/show-a68753612c0dbd41097e2e3adcae1fe7e94f8bf8.html"}}, {"_id": "6288f8733d5c31000774af02", "category_tag_id": "549ef207fe682f7549f1ea90", "title": "\u3010\u55b5\u840c\u5976\u8336\u5c4b\u3011\u260504\u6708\u65b0\u756a\u2605[Estab Life: Great Escape][10][720p][\u7b80\u4f53][\u62db\u52df\u7ffb\u8bd1\u6821\u5bf9]", "introduction": "<p><img src=\"https://p.sda1.dev/5/401465fb62a0b9926e834d1c814b3192/wstablife_tv_1000.jpg\"></p>", "tag_ids": ["548edfb54ab7379536f56351", "624774a270e8f89b23a18556", "58a9c1e6f5dc363606ab42ed", "548ee0ea4ab7379536f56354", "549ef207fe682f7549f1ea90"], "comments": 0, "downloads": 57, "finished": 183, "leechers": 0, "seeders": 2, "uploader_id": "59842d4fde238a777bf95202", "team_id": "58a9c1c9f5dc363606ab42ec", "publish_time": "2022-05-21T14:34:27.580Z", "magnet": "magnet:?xt=urn:btih:1ec581e439824db19f58517cbcf1fc2d0eb06030", "infoHash": "1ec581e439824db19f58517cbcf1fc2d0eb06030", "file_id": "6288f8343d5c31000774aeab", "teamsync": true, "content": [["[Nekomoe kissaten][Estab Life - Great Escape][10][720p][CHS].mp4", "295.12 MB"]], "size": "295.12 MB", "btskey": "", "sync": {"dmhy": "http://share.dmhy.org/topics/view/600858_04_Estab_Life_Great_Escape_10_720p.html", "acgrip": "https://acg.rip/t/255856", "nyaa": "https://nyaa.si/view/1531301", "acgnx": "https://share.acgnx.se/show-1ec581e439824db19f58517cbcf1fc2d0eb06030.html", "acgnx_int": "https://www.acgnx.se/show-1ec581e439824db19f58517cbcf1fc2d0eb06030.html"}}, {"_id": "627e37823d5c31000760f12e", "category_tag_id": "549ef207fe682f7549f1ea90", "title": "\u3010\u55b5\u840c\u5976\u8336\u5c4b\u3011\u260504\u6708\u65b0\u756a\u2605[Estab Life: Great Escape][09][1080p][\u7e41\u9ad4][\u62db\u52df\u7ffb\u8b6f\u6821\u5c0d]", "introduction": "<p><img src=\"https://p.sda1.dev/5/401465fb62a0b9926e834d1c814b3192/wstablife_tv_1000.jpg\"></p>", "tag_ids": ["624774a270e8f89b23a18556", "58a9c1e6f5dc363606ab42ed", "549ef207fe682f7549f1ea90", "548ee1204ab7379536f56357", "548ee2ce4ab7379536f56358"], "comments": 0, "downloads": 126, "finished": 762, "leechers": 0, "seeders": 4, "uploader_id": "59842d4fde238a777bf95202", "team_id": "58a9c1c9f5dc363606ab42ec", "publish_time": "2022-05-13T10:48:34.047Z", "magnet": "magnet:?xt=urn:btih:42a7f44dac8d9d97cd882e383478acab5456bc43", "infoHash": "42a7f44dac8d9d97cd882e383478acab5456bc43", "file_id": "627e377e3d5c31000760f126", "teamsync": true, "content": [["[Nekomoe kissaten][Estab Life - Great Escape][09][1080p][CHT].mp4", "748.63 MB"]], "size": "748.63 MB", "btskey": "", "sync": {"dmhy": "http://share.dmhy.org/topics/view/600173_04_Estab_Life_Great_Escape_09_1080p.html", "acgrip": "https://acg.rip/t/255433", "nyaa": "https://nyaa.si/view/1527588", "acgnx": "https://share.acgnx.se/show-42a7f44dac8d9d97cd882e383478acab5456bc43.html", "acgnx_int": "https://www.acgnx.se/show-42a7f44dac8d9d97cd882e383478acab5456bc43.html"}}, {"_id": "627e377a3d5c31000760f11a", "category_tag_id": "549ef207fe682f7549f1ea90", "title": "\u3010\u55b5\u840c\u5976\u8336\u5c4b\u3011\u260504\u6708\u65b0\u756a\u2605[Estab Life: Great Escape][09][1080p][\u7b80\u4f53][\u62db\u52df\u7ffb\u8bd1\u6821\u5bf9]", "introduction": "<p><img src=\"https://p.sda1.dev/5/401465fb62a0b9926e834d1c814b3192/wstablife_tv_1000.jpg\"></p>", "tag_ids": ["624774a270e8f89b23a18556", "58a9c1e6f5dc363606ab42ed", "548ee0ea4ab7379536f56354", "549ef207fe682f7549f1ea90", "548ee2ce4ab7379536f56358"], "comments": 0, "downloads": 116, "finished": 676, "leechers": 0, "seeders": 27, "uploader_id": "59842d4fde238a777bf95202", "team_id": "58a9c1c9f5dc363606ab42ec", "publish_time": "2022-05-13T10:48:26.205Z", "magnet": "magnet:?xt=urn:btih:c79e136da8ec0ed161dfba90d6045358f680866e", "infoHash": "c79e136da8ec0ed161dfba90d6045358f680866e", "file_id": "627e37763d5c31000760f10f", "teamsync": true, "content": [["[Nekomoe kissaten][Estab Life - Great Escape][09][1080p][CHS].mp4", "748.68 MB"]], "size": "748.68 MB", "btskey": "", "sync": {"dmhy": "http://share.dmhy.org/topics/view/600172_04_Estab_Life_Great_Escape_09_1080p.html", "acgrip": "https://acg.rip/t/255432", "nyaa": "https://nyaa.si/view/1527587", "acgnx": "https://share.acgnx.se/show-c79e136da8ec0ed161dfba90d6045358f680866e.html", "acgnx_int": "https://www.acgnx.se/show-c79e136da8ec0ed161dfba90d6045358f680866e.html"}}, {"_id": "627e37083d5c31000760f067", "category_tag_id": "549ef207fe682f7549f1ea90", "title": "\u3010\u55b5\u840c\u5976\u8336\u5c4b\u3011\u260504\u6708\u65b0\u756a\u2605[Estab Life: Great Escape][09][720p][\u7e41\u9ad4][\u62db\u52df\u7ffb\u8b6f\u6821\u5c0d]", "introduction": "<p><img src=\"https://p.sda1.dev/5/401465fb62a0b9926e834d1c814b3192/wstablife_tv_1000.jpg\"></p>", "tag_ids": ["624774a270e8f89b23a18556", "58a9c1e6f5dc363606ab42ed", "548edfb54ab7379536f56351", "549ef207fe682f7549f1ea90", "548ee1204ab7379536f56357"], "comments": 0, "downloads": 87, "finished": 479, "leechers": 0, "seeders": 3, "uploader_id": "59842d4fde238a777bf95202", "team_id": "58a9c1c9f5dc363606ab42ec", "publish_time": "2022-05-13T10:46:32.391Z", "magnet": "magnet:?xt=urn:btih:b197ba881642852e7c29f325cd0653278da4a43e", "infoHash": "b197ba881642852e7c29f325cd0653278da4a43e", "file_id": "627e36d83d5c31000760f00d", "teamsync": true, "content": [["[Nekomoe kissaten][Estab Life - Great Escape][09][720p][CHT].mp4", "346.69 MB"]], "size": "346.69 MB", "btskey": "", "sync": {"dmhy": "http://share.dmhy.org/topics/view/600171_04_Estab_Life_Great_Escape_09_720p.html", "acgrip": "https://acg.rip/t/255431", "nyaa": "https://nyaa.si/view/1527586", "acgnx": "https://share.acgnx.se/show-b197ba881642852e7c29f325cd0653278da4a43e.html", "acgnx_int": "https://www.acgnx.se/show-b197ba881642852e7c29f325cd0653278da4a43e.html"}}, {"_id": "627e36d33d5c31000760f003", "category_tag_id": "549ef207fe682f7549f1ea90", "title": "\u3010\u55b5\u840c\u5976\u8336\u5c4b\u3011\u260504\u6708\u65b0\u756a\u2605[Estab Life: Great Escape][09][720p][\u7b80\u4f53][\u62db\u52df\u7ffb\u8bd1\u6821\u5bf9]", "introduction": "<p><img src=\"https://p.sda1.dev/5/401465fb62a0b9926e834d1c814b3192/wstablife_tv_1000.jpg\"></p>", "tag_ids": ["548edfb54ab7379536f56351", "624774a270e8f89b23a18556", "58a9c1e6f5dc363606ab42ed", "548ee0ea4ab7379536f56354", "549ef207fe682f7549f1ea90"], "comments": 0, "downloads": 75, "finished": 161, "leechers": 0, "seeders": 1, "uploader_id": "59842d4fde238a777bf95202", "team_id": "58a9c1c9f5dc363606ab42ec", "publish_time": "2022-05-13T10:45:39.708Z", "magnet": "magnet:?xt=urn:btih:b8586390665def1ebf06e7cf469dab47a83f3e07", "infoHash": "b8586390665def1ebf06e7cf469dab47a83f3e07", "file_id": "627e36c73d5c31000760efe7", "teamsync": true, "content": [["[Nekomoe kissaten][Estab Life - Great Escape][09][720p][CHS].mp4", "346.73 MB"]], "size": "346.73 MB", "btskey": "", "sync": {"dmhy": "http://share.dmhy.org/topics/view/600170_04_Estab_Life_Great_Escape_09_720p.html", "acgrip": "https://acg.rip/t/255430", "nyaa": "https://nyaa.si/view/1527585", "acgnx": "https://share.acgnx.se/show-b8586390665def1ebf06e7cf469dab47a83f3e07.html", "acgnx_int": "https://www.acgnx.se/show-b8586390665def1ebf06e7cf469dab47a83f3e07.html"}}, {"_id": "627337b53d5c3100074e3244", "category_tag_id": "549ef207fe682f7549f1ea90", "title": "\u3010\u55b5\u840c\u5976\u8336\u5c4b\u3011\u260504\u6708\u65b0\u756a\u2605[Estab Life: Great Escape][08][1080p][\u7e41\u9ad4][\u62db\u52df\u7ffb\u8b6f\u6821\u5c0d]", "introduction": "<p><img src=\"https://p.sda1.dev/5/401465fb62a0b9926e834d1c814b3192/wstablife_tv_1000.jpg\"></p>", "tag_ids": ["624774a270e8f89b23a18556", "58a9c1e6f5dc363606ab42ed", "549ef207fe682f7549f1ea90", "548ee1204ab7379536f56357", "548ee2ce4ab7379536f56358"], "comments": 0, "downloads": 144, "finished": 775, "leechers": 0, "seeders": 6, "uploader_id": "59842d4fde238a777bf95202", "team_id": "58a9c1c9f5dc363606ab42ec", "publish_time": "2022-05-05T02:34:29.683Z", "magnet": "magnet:?xt=urn:btih:57c865570faf88dd94de4add45f2001e322d63bf", "infoHash": "57c865570faf88dd94de4add45f2001e322d63bf", "file_id": "627337b03d5c3100074e323a", "teamsync": true, "content": [["[Nekomoe kissaten][Estab Life - Great Escape][08][1080p][CHT].mp4", "449.15 MB"]], "size": "449.15 MB", "btskey": "", "sync": {"dmhy": "http://share.dmhy.org/topics/view/599414_04_Estab_Life_Great_Escape_08_1080p.html", "acgrip": "https://acg.rip/t/254969", "nyaa": "https://nyaa.si/view/1524078", "acgnx": "https://share.acgnx.se/show-57c865570faf88dd94de4add45f2001e322d63bf.html", "acgnx_int": "https://www.acgnx.se/show-57c865570faf88dd94de4add45f2001e322d63bf.html"}}, {"_id": "627337ac3d5c3100074e3237", "category_tag_id": "549ef207fe682f7549f1ea90", "title": "\u3010\u55b5\u840c\u5976\u8336\u5c4b\u3011\u260504\u6708\u65b0\u756a\u2605[Estab Life: Great Escape][08][1080p][\u7b80\u4f53][\u62db\u52df\u7ffb\u8bd1\u6821\u5bf9]", "introduction": "<p><img src=\"https://p.sda1.dev/5/401465fb62a0b9926e834d1c814b3192/wstablife_tv_1000.jpg\"></p>", "tag_ids": ["624774a270e8f89b23a18556", "58a9c1e6f5dc363606ab42ed", "548ee0ea4ab7379536f56354", "549ef207fe682f7549f1ea90", "548ee2ce4ab7379536f56358"], "comments": 0, "downloads": 141, "finished": 739, "leechers": 0, "seeders": 33, "uploader_id": "59842d4fde238a777bf95202", "team_id": "58a9c1c9f5dc363606ab42ec", "publish_time": "2022-05-05T02:34:20.633Z", "magnet": "magnet:?xt=urn:btih:3bbe8b61c6e363df769fd308a401262e899522dc", "infoHash": "3bbe8b61c6e363df769fd308a401262e899522dc", "file_id": "627337a83d5c3100074e3230", "teamsync": true, "content": [["[Nekomoe kissaten][Estab Life - Great Escape][08][1080p][CHS].mp4", "449.2 MB"]], "size": "449.2 MB", "btskey": "", "sync": {"dmhy": "http://share.dmhy.org/topics/view/599413_04_Estab_Life_Great_Escape_08_1080p.html", "acgrip": "https://acg.rip/t/254968", "nyaa": "https://nyaa.si/view/1524077", "acgnx": "https://share.acgnx.se/show-3bbe8b61c6e363df769fd308a401262e899522dc.html", "acgnx_int": "https://www.acgnx.se/show-3bbe8b61c6e363df769fd308a401262e899522dc.html"}}, {"_id": "627337a43d5c3100074e3227", "category_tag_id": "549ef207fe682f7549f1ea90", "title": "\u3010\u55b5\u840c\u5976\u8336\u5c4b\u3011\u260504\u6708\u65b0\u756a\u2605[Estab Life: Great Escape][08][720p][\u7e41\u9ad4][\u62db\u52df\u7ffb\u8b6f\u6821\u5c0d]", "introduction": "<p><img src=\"https://p.sda1.dev/5/401465fb62a0b9926e834d1c814b3192/wstablife_tv_1000.jpg\"></p>", "tag_ids": ["624774a270e8f89b23a18556", "58a9c1e6f5dc363606ab42ed", "548edfb54ab7379536f56351", "549ef207fe682f7549f1ea90", "548ee1204ab7379536f56357"], "comments": 0, "downloads": 86, "finished": 556, "leechers": 0, "seeders": 3, "uploader_id": "59842d4fde238a777bf95202", "team_id": "58a9c1c9f5dc363606ab42ec", "publish_time": "2022-05-05T02:34:12.677Z", "magnet": "magnet:?xt=urn:btih:8b956e70e4c363a25697538314bc2c2765e5986e", "infoHash": "8b956e70e4c363a25697538314bc2c2765e5986e", "file_id": "627337983d5c3100074e321c", "teamsync": true, "content": [["[Nekomoe kissaten][Estab Life - Great Escape][08][720p][CHT].mp4", "225.75 MB"]], "size": "225.75 MB", "btskey": "", "sync": {"dmhy": "http://share.dmhy.org/topics/view/599412_04_Estab_Life_Great_Escape_08_720p.html", "acgrip": "https://acg.rip/t/254967", "nyaa": "https://nyaa.si/view/1524076", "acgnx": "https://share.acgnx.se/show-8b956e70e4c363a25697538314bc2c2765e5986e.html", "acgnx_int": "https://www.acgnx.se/show-8b956e70e4c363a25697538314bc2c2765e5986e.html"}}, {"_id": "627337943d5c3100074e3218", "category_tag_id": "549ef207fe682f7549f1ea90", "title": "\u3010\u55b5\u840c\u5976\u8336\u5c4b\u3011\u260504\u6708\u65b0\u756a\u2605[Estab Life: Great Escape][08][720p][\u7b80\u4f53][\u62db\u52df\u7ffb\u8bd1\u6821\u5bf9]", "introduction": "<p><img src=\"https://p.sda1.dev/5/401465fb62a0b9926e834d1c814b3192/wstablife_tv_1000.jpg\"></p>", "tag_ids": ["548edfb54ab7379536f56351", "624774a270e8f89b23a18556", "58a9c1e6f5dc363606ab42ed", "548ee0ea4ab7379536f56354", "549ef207fe682f7549f1ea90"], "comments": 0, "downloads": 79, "finished": 186, "leechers": 0, "seeders": 3, "uploader_id": "59842d4fde238a777bf95202", "team_id": "58a9c1c9f5dc363606ab42ec", "publish_time": "2022-05-05T02:33:56.043Z", "magnet": "magnet:?xt=urn:btih:67424f0606d4de967d41dd1225c6d7a7128a77d5", "infoHash": "67424f0606d4de967d41dd1225c6d7a7128a77d5", "file_id": "627337753d5c3100074e31ec", "teamsync": true, "content": [["[Nekomoe kissaten][Estab Life - Great Escape][08][720p][CHS].mp4", "225.79 MB"]], "size": "225.79 MB", "btskey": "", "sync": {"dmhy": "http://share.dmhy.org/topics/view/599411_04_Estab_Life_Great_Escape_08_720p.html", "acgrip": "https://acg.rip/t/254966", "nyaa": "https://nyaa.si/view/1524075", "acgnx": "https://share.acgnx.se/show-67424f0606d4de967d41dd1225c6d7a7128a77d5.html", "acgnx_int": "https://www.acgnx.se/show-67424f0606d4de967d41dd1225c6d7a7128a77d5.html"}}, {"_id": "626a2ccc3d5c3100073e4268", "category_tag_id": "549ef207fe682f7549f1ea90", "title": "\u3010\u55b5\u840c\u5976\u8336\u5c4b\u3011\u260504\u6708\u65b0\u756a\u2605[Estab Life: Great Escape][07][1080p][\u7e41\u9ad4][\u62db\u52df\u7ffb\u8b6f\u6821\u5c0d]", "introduction": "<p><img src=\"https://p.sda1.dev/5/401465fb62a0b9926e834d1c814b3192/wstablife_tv_1000.jpg\"></p>", "tag_ids": ["58a9c1e6f5dc363606ab42ed", "549ef207fe682f7549f1ea90", "548ee1204ab7379536f56357", "548ee2ce4ab7379536f56358", "624774a270e8f89b23a18556"], "comments": 0, "downloads": 131, "finished": 806, "leechers": 0, "seeders": 5, "uploader_id": "59842d4fde238a777bf95202", "team_id": "58a9c1c9f5dc363606ab42ec", "publish_time": "2022-04-28T05:57:32.418Z", "magnet": "magnet:?xt=urn:btih:7eee88e56383a766aa0b395a26692bf88e27de5a", "infoHash": "7eee88e56383a766aa0b395a26692bf88e27de5a", "file_id": "626a2cc83d5c3100073e4261", "teamsync": true, "content": [["[Nekomoe kissaten][Estab Life - Great Escape][07][1080p][CHT].mp4", "589.18 MB"]], "size": "589.18 MB", "btskey": "", "sync": {"dmhy": "http://share.dmhy.org/topics/view/598833_04_Estab_Life_Great_Escape_07_1080p.html", "acgrip": "https://acg.rip/t/254584", "nyaa": "https://nyaa.si/view/1521002", "acgnx": "https://share.acgnx.se/show-7eee88e56383a766aa0b395a26692bf88e27de5a.html", "acgnx_int": "https://www.acgnx.se/show-7eee88e56383a766aa0b395a26692bf88e27de5a.html"}}, {"_id": "626a2cc43d5c3100073e425c", "category_tag_id": "549ef207fe682f7549f1ea90", "title": "\u3010\u55b5\u840c\u5976\u8336\u5c4b\u3011\u260504\u6708\u65b0\u756a\u2605[Estab Life: Great Escape][07][1080p][\u7b80\u4f53][\u62db\u52df\u7ffb\u8bd1\u6821\u5bf9]", "introduction": "<p><img src=\"https://p.sda1.dev/5/401465fb62a0b9926e834d1c814b3192/wstablife_tv_1000.jpg\"></p>", "tag_ids": ["58a9c1e6f5dc363606ab42ed", "548ee0ea4ab7379536f56354", "549ef207fe682f7549f1ea90", "548ee2ce4ab7379536f56358", "624774a270e8f89b23a18556"], "comments": 0, "downloads": 136, "finished": 761, "leechers": 0, "seeders": 35, "uploader_id": "59842d4fde238a777bf95202", "team_id": "58a9c1c9f5dc363606ab42ec", "publish_time": "2022-04-28T05:57:24.359Z", "magnet": "magnet:?xt=urn:btih:3b36756c2bf768b0698ab3309e4efa949fdf872a", "infoHash": "3b36756c2bf768b0698ab3309e4efa949fdf872a", "file_id": "626a2cbc3d5c3100073e424d", "teamsync": true, "content": [["[Nekomoe kissaten][Estab Life - Great Escape][07][1080p][CHS].mp4", "589.16 MB"]], "size": "589.16 MB", "btskey": "", "sync": {"dmhy": "http://share.dmhy.org/topics/view/598832_04_Estab_Life_Great_Escape_07_1080p.html", "acgrip": "https://acg.rip/t/254583", "nyaa": "https://nyaa.si/view/1521001", "acgnx": "https://share.acgnx.se/show-3b36756c2bf768b0698ab3309e4efa949fdf872a.html", "acgnx_int": "https://www.acgnx.se/show-3b36756c2bf768b0698ab3309e4efa949fdf872a.html"}}, {"_id": "626a2ca93d5c3100073e4228", "category_tag_id": "549ef207fe682f7549f1ea90", "title": "\u3010\u55b5\u840c\u5976\u8336\u5c4b\u3011\u260504\u6708\u65b0\u756a\u2605[Estab Life: Great Escape][07][720p][\u7e41\u9ad4][\u62db\u52df\u7ffb\u8b6f\u6821\u5c0d]", "introduction": "<p><img src=\"https://p.sda1.dev/5/401465fb62a0b9926e834d1c814b3192/wstablife_tv_1000.jpg\"></p>", "tag_ids": ["58a9c1e6f5dc363606ab42ed", "548edfb54ab7379536f56351", "549ef207fe682f7549f1ea90", "548ee1204ab7379536f56357", "624774a270e8f89b23a18556"], "comments": 0, "downloads": 90, "finished": 637, "leechers": 0, "seeders": 1, "uploader_id": "59842d4fde238a777bf95202", "team_id": "58a9c1c9f5dc363606ab42ec", "publish_time": "2022-04-28T05:56:57.303Z", "magnet": "magnet:?xt=urn:btih:e159f5d8487402bc6a745aa84f4352ec649ce429", "infoHash": "e159f5d8487402bc6a745aa84f4352ec649ce429", "file_id": "626a2c9d3d5c3100073e4219", "teamsync": true, "content": [["[Nekomoe kissaten][Estab Life - Great Escape][07][720p][CHT].mp4", "260.37 MB"]], "size": "260.37 MB", "btskey": "", "sync": {"dmhy": "http://share.dmhy.org/topics/view/598831_04_Estab_Life_Great_Escape_07_720p.html", "acgrip": "https://acg.rip/t/254582", "nyaa": "https://nyaa.si/view/1521000", "acgnx": "https://share.acgnx.se/show-e159f5d8487402bc6a745aa84f4352ec649ce429.html", "acgnx_int": "https://www.acgnx.se/show-e159f5d8487402bc6a745aa84f4352ec649ce429.html"}}, {"_id": "626a2c983d5c3100073e4212", "category_tag_id": "549ef207fe682f7549f1ea90", "title": "\u3010\u55b5\u840c\u5976\u8336\u5c4b\u3011\u260504\u6708\u65b0\u756a\u2605[Estab Life: Great Escape][07][720p][\u7b80\u4f53][\u62db\u52df\u7ffb\u8bd1\u6821\u5bf9]", "introduction": "<p><img src=\"https://p.sda1.dev/5/401465fb62a0b9926e834d1c814b3192/wstablife_tv_1000.jpg\"></p>", "tag_ids": ["548edfb54ab7379536f56351", "58a9c1e6f5dc363606ab42ed", "548ee0ea4ab7379536f56354", "549ef207fe682f7549f1ea90", "624774a270e8f89b23a18556"], "comments": 0, "downloads": 77, "finished": 222, "leechers": 0, "seeders": 0, "uploader_id": "59842d4fde238a777bf95202", "team_id": "58a9c1c9f5dc363606ab42ec", "publish_time": "2022-04-28T05:56:40.631Z", "magnet": "magnet:?xt=urn:btih:cb3798a9d6354a68a79feef5d89db59bac90baa9", "infoHash": "cb3798a9d6354a68a79feef5d89db59bac90baa9", "file_id": "626a2c623d5c3100073e41b6", "teamsync": true, "content": [["[Nekomoe kissaten][Estab Life - Great Escape][07][720p][CHS].mp4", "260.35 MB"]], "size": "260.35 MB", "btskey": "", "sync": {"dmhy": "http://share.dmhy.org/topics/view/598830_04_Estab_Life_Great_Escape_07_720p.html", "acgrip": "https://acg.rip/t/254581", "nyaa": "https://nyaa.si/view/1520999", "acgnx": "https://share.acgnx.se/show-cb3798a9d6354a68a79feef5d89db59bac90baa9.html", "acgnx_int": "https://www.acgnx.se/show-cb3798a9d6354a68a79feef5d89db59bac90baa9.html"}}, {"_id": "626169713d5c3100072f1ca5", "category_tag_id": "549ef207fe682f7549f1ea90", "title": "\u3010\u55b5\u840c\u5976\u8336\u5c4b\u3011\u260504\u6708\u65b0\u756a\u2605[Estab Life: Great Escape][06][1080p][\u7e41\u9ad4][\u62db\u52df\u7ffb\u8b6f\u6821\u5c0d]", "introduction": "<p><img src=\"https://p.sda1.dev/5/401465fb62a0b9926e834d1c814b3192/wstablife_tv_1000.jpg\"></p>", "tag_ids": ["58a9c1e6f5dc363606ab42ed", "624774a270e8f89b23a18556", "549ef207fe682f7549f1ea90", "548ee1204ab7379536f56357", "548ee2ce4ab7379536f56358"], "comments": 0, "downloads": 153, "finished": 882, "leechers": 0, "seeders": 5, "uploader_id": "59842d4fde238a777bf95202", "team_id": "58a9c1c9f5dc363606ab42ec", "publish_time": "2022-04-21T14:25:53.044Z", "magnet": "magnet:?xt=urn:btih:3a62acb7f6fe4ea091ac0124e6954b4d8caedf60", "infoHash": "3a62acb7f6fe4ea091ac0124e6954b4d8caedf60", "file_id": "6261696c3d5c3100072f1c9e", "teamsync": true, "content": [["[Nekomoe kissaten][Estab Life - Great Escape][06][1080p][CHT].mp4", "581.68 MB"]], "size": "581.68 MB", "btskey": "", "sync": {"dmhy": "http://share.dmhy.org/topics/view/598178_04_Estab_Life_Great_Escape_06_1080p.html", "acgrip": "https://acg.rip/t/254158", "nyaa": "https://nyaa.si/view/1517749", "acgnx": "https://share.acgnx.se/show-3a62acb7f6fe4ea091ac0124e6954b4d8caedf60.html", "acgnx_int": "https://www.acgnx.se/show-3a62acb7f6fe4ea091ac0124e6954b4d8caedf60.html"}}, {"_id": "626169683d5c3100072f1c91", "category_tag_id": "549ef207fe682f7549f1ea90", "title": "\u3010\u55b5\u840c\u5976\u8336\u5c4b\u3011\u260504\u6708\u65b0\u756a\u2605[Estab Life: Great Escape][06][1080p][\u7b80\u4f53][\u62db\u52df\u7ffb\u8bd1\u6821\u5bf9]", "introduction": "<p><img src=\"https://p.sda1.dev/5/401465fb62a0b9926e834d1c814b3192/wstablife_tv_1000.jpg\"></p>", "tag_ids": ["58a9c1e6f5dc363606ab42ed", "548ee0ea4ab7379536f56354", "624774a270e8f89b23a18556", "549ef207fe682f7549f1ea90", "548ee2ce4ab7379536f56358"], "comments": 0, "downloads": 145, "finished": 855, "leechers": 0, "seeders": 32, "uploader_id": "59842d4fde238a777bf95202", "team_id": "58a9c1c9f5dc363606ab42ec", "publish_time": "2022-04-21T14:25:44.302Z", "magnet": "magnet:?xt=urn:btih:7acf334c33e07a2aafc49bc662d8b41970ad1218", "infoHash": "7acf334c33e07a2aafc49bc662d8b41970ad1218", "file_id": "626169613d5c3100072f1c7e", "teamsync": true, "content": [["[Nekomoe kissaten][Estab Life - Great Escape][06][1080p][CHS].mp4", "581.58 MB"]], "size": "581.58 MB", "btskey": "", "sync": {"dmhy": "http://share.dmhy.org/topics/view/598177_04_Estab_Life_Great_Escape_06_1080p.html", "acgrip": "https://acg.rip/t/254157", "nyaa": "https://nyaa.si/view/1517748", "acgnx": "https://share.acgnx.se/show-7acf334c33e07a2aafc49bc662d8b41970ad1218.html", "acgnx_int": "https://www.acgnx.se/show-7acf334c33e07a2aafc49bc662d8b41970ad1218.html"}}, {"_id": "6261693b3d5c3100072f1c4c", "category_tag_id": "549ef207fe682f7549f1ea90", "title": "\u3010\u55b5\u840c\u5976\u8336\u5c4b\u3011\u260504\u6708\u65b0\u756a\u2605[Estab Life: Great Escape][06][720p][\u7e41\u9ad4][\u62db\u52df\u7ffb\u8b6f\u6821\u5c0d]", "introduction": "<p><img src=\"https://p.sda1.dev/5/401465fb62a0b9926e834d1c814b3192/wstablife_tv_1000.jpg\"></p>", "tag_ids": ["548edfb54ab7379536f56351", "58a9c1e6f5dc363606ab42ed", "624774a270e8f89b23a18556", "549ef207fe682f7549f1ea90", "548ee1204ab7379536f56357"], "comments": 0, "downloads": 88, "finished": 571, "leechers": 0, "seeders": 0, "uploader_id": "59842d4fde238a777bf95202", "team_id": "58a9c1c9f5dc363606ab42ec", "publish_time": "2022-04-21T14:24:59.134Z", "magnet": "magnet:?xt=urn:btih:78c94634f168403bdfc81b89945e8a8e52f633e7", "infoHash": "78c94634f168403bdfc81b89945e8a8e52f633e7", "file_id": "626169093d5c3100072f1bfc", "teamsync": true, "content": [["[Nekomoe kissaten][Estab Life - Great Escape][06][720p][CHT].mp4", "261.69 MB"]], "size": "261.69 MB", "btskey": "", "sync": {"dmhy": "http://share.dmhy.org/topics/view/598176_04_Estab_Life_Great_Escape_06_720p.html", "acgrip": "https://acg.rip/t/254156", "nyaa": "https://nyaa.si/view/1517747", "acgnx": "https://share.acgnx.se/show-78c94634f168403bdfc81b89945e8a8e52f633e7.html", "acgnx_int": "https://www.acgnx.se/show-78c94634f168403bdfc81b89945e8a8e52f633e7.html"}}, {"_id": "626169043d5c3100072f1beb", "category_tag_id": "549ef207fe682f7549f1ea90", "title": "\u3010\u55b5\u840c\u5976\u8336\u5c4b\u3011\u260504\u6708\u65b0\u756a\u2605[Estab Life: Great Escape][06][720p][\u7b80\u4f53][\u62db\u52df\u7ffb\u8bd1\u6821\u5bf9]", "introduction": "<p><img src=\"https://p.sda1.dev/5/401465fb62a0b9926e834d1c814b3192/wstablife_tv_1000.jpg\"></p>", "tag_ids": ["548edfb54ab7379536f56351", "58a9c1e6f5dc363606ab42ed", "548ee0ea4ab7379536f56354", "624774a270e8f89b23a18556", "549ef207fe682f7549f1ea90"], "comments": 0, "downloads": 81, "finished": 204, "leechers": 0, "seeders": 0, "uploader_id": "59842d4fde238a777bf95202", "team_id": "58a9c1c9f5dc363606ab42ec", "publish_time": "2022-04-21T14:24:04.309Z", "magnet": "magnet:?xt=urn:btih:7f2083571d35c9f737b3bfa025237e27777f358c", "infoHash": "7f2083571d35c9f737b3bfa025237e27777f358c", "file_id": "626168dd3d5c3100072f1b9c", "teamsync": true, "content": [["[Nekomoe kissaten][Estab Life - Great Escape][06][720p][CHS].mp4", "261.76 MB"]], "size": "261.76 MB", "btskey": "", "sync": {"dmhy": "http://share.dmhy.org/topics/view/598175_04_Estab_Life_Great_Escape_06_720p.html", "acgrip": "https://acg.rip/t/254155", "nyaa": "https://nyaa.si/view/1517746", "acgnx": "https://share.acgnx.se/show-7f2083571d35c9f737b3bfa025237e27777f358c.html", "acgnx_int": "https://www.acgnx.se/show-7f2083571d35c9f737b3bfa025237e27777f358c.html"}}, {"_id": "625a77885aa8700007905ece", "category_tag_id": "549ef207fe682f7549f1ea90", "title": "\u3010\u55b5\u840c\u5976\u8336\u5c4b\u3011\u260504\u6708\u65b0\u756a\u2605[Estab Life: Great Escape][05][1080p][\u7e41\u9ad4][\u62db\u52df\u7ffb\u8b6f\u6821\u5c0d]", "introduction": "<p><img src=\"https://p.sda1.dev/5/401465fb62a0b9926e834d1c814b3192/wstablife_tv_1000.jpg\"></p>", "tag_ids": ["58a9c1e6f5dc363606ab42ed", "624774a270e8f89b23a18556", "548edfb54ab7379536f56351", "549ef207fe682f7549f1ea90", "548ee1204ab7379536f56357"], "comments": 0, "downloads": 125, "finished": 871, "leechers": 0, "seeders": 2, "uploader_id": "59842d4fde238a777bf95202", "team_id": "58a9c1c9f5dc363606ab42ec", "publish_time": "2022-04-16T08:00:08.109Z", "magnet": "magnet:?xt=urn:btih:6cfdeba2877fec30f3085f0e7bca0f0d273d3700", "infoHash": "6cfdeba2877fec30f3085f0e7bca0f0d273d3700", "file_id": "625a77815aa8700007905ec3", "teamsync": true, "content": [["[Nekomoe kissaten][Estab Life - Great Escape][05][1080p][CHT].mp4", "682.1 MB"]], "size": "682.1 MB", "btskey": "", "sync": {"dmhy": "http://share.dmhy.org/topics/view/597592_04_Estab_Life_Great_Escape_05_1080p.html", "acgrip": "https://acg.rip/t/253795", "nyaa": "https://nyaa.si/view/1515480", "acgnx": "https://share.acgnx.se/show-6cfdeba2877fec30f3085f0e7bca0f0d273d3700.html", "acgnx_int": "https://www.acgnx.se/show-6cfdeba2877fec30f3085f0e7bca0f0d273d3700.html"}}, {"_id": "625a777e5aa8700007905ebb", "category_tag_id": "549ef207fe682f7549f1ea90", "title": "\u3010\u55b5\u840c\u5976\u8336\u5c4b\u3011\u260504\u6708\u65b0\u756a\u2605[Estab Life: Great Escape][05][1080p][\u7b80\u4f53][\u62db\u52df\u7ffb\u8bd1\u6821\u5bf9]", "introduction": "<p><img src=\"https://p.sda1.dev/5/401465fb62a0b9926e834d1c814b3192/wstablife_tv_1000.jpg\"></p>", "tag_ids": ["548edfb54ab7379536f56351", "58a9c1e6f5dc363606ab42ed", "548ee0ea4ab7379536f56354", "624774a270e8f89b23a18556", "549ef207fe682f7549f1ea90"], "comments": 0, "downloads": 130, "finished": 932, "leechers": 0, "seeders": 37, "uploader_id": "59842d4fde238a777bf95202", "team_id": "58a9c1c9f5dc363606ab42ec", "publish_time": "2022-04-16T07:59:58.025Z", "magnet": "magnet:?xt=urn:btih:feb35276831ca11b54891007270031406a1c9b56", "infoHash": "feb35276831ca11b54891007270031406a1c9b56", "file_id": "625a777a5aa8700007905eb5", "teamsync": true, "content": [["[Nekomoe kissaten][Estab Life - Great Escape][05][1080p][CHS].mp4", "682.16 MB"]], "size": "682.16 MB", "btskey": "", "sync": {"dmhy": "http://share.dmhy.org/topics/view/597591_04_Estab_Life_Great_Escape_05_1080p.html", "acgrip": "https://acg.rip/t/253794", "nyaa": "https://nyaa.si/view/1515479", "acgnx": "https://share.acgnx.se/show-feb35276831ca11b54891007270031406a1c9b56.html", "acgnx_int": "https://www.acgnx.se/show-feb35276831ca11b54891007270031406a1c9b56.html"}}, {"_id": "625a77765aa8700007905eaf", "category_tag_id": "549ef207fe682f7549f1ea90", "title": "\u3010\u55b5\u840c\u5976\u8336\u5c4b\u3011\u260504\u6708\u65b0\u756a\u2605[Estab Life: Great Escape][05][720p][\u7e41\u9ad4][\u62db\u52df\u7ffb\u8b6f\u6821\u5c0d]", "introduction": "<p><img src=\"https://p.sda1.dev/5/401465fb62a0b9926e834d1c814b3192/wstablife_tv_1000.jpg\"></p>", "tag_ids": ["58a9c1e6f5dc363606ab42ed", "624774a270e8f89b23a18556", "548edfb54ab7379536f56351", "549ef207fe682f7549f1ea90", "548ee1204ab7379536f56357"], "comments": 0, "downloads": 85, "finished": 456, "leechers": 0, "seeders": 1, "uploader_id": "59842d4fde238a777bf95202", "team_id": "58a9c1c9f5dc363606ab42ec", "publish_time": "2022-04-16T07:59:50.499Z", "magnet": "magnet:?xt=urn:btih:f4cfbc1a4b86f8e92952ca4c242447a4fe51174e", "infoHash": "f4cfbc1a4b86f8e92952ca4c242447a4fe51174e", "file_id": "625a77725aa8700007905ea8", "teamsync": true, "content": [["[Nekomoe kissaten][Estab Life - Great Escape][05][720p][CHT].mp4", "318.59 MB"]], "size": "318.59 MB", "btskey": "", "sync": {"dmhy": "http://share.dmhy.org/topics/view/597590_04_Estab_Life_Great_Escape_05_720p.html", "acgrip": "https://acg.rip/t/253793", "nyaa": "https://nyaa.si/view/1515478", "acgnx": "https://share.acgnx.se/show-f4cfbc1a4b86f8e92952ca4c242447a4fe51174e.html", "acgnx_int": "https://www.acgnx.se/show-f4cfbc1a4b86f8e92952ca4c242447a4fe51174e.html"}}, {"_id": "625a776e5aa8700007905ea0", "category_tag_id": "549ef207fe682f7549f1ea90", "title": "\u3010\u55b5\u840c\u5976\u8336\u5c4b\u3011\u260504\u6708\u65b0\u756a\u2605[Estab Life: Great Escape][05][720p][\u7b80\u4f53][\u62db\u52df\u7ffb\u8bd1\u6821\u5bf9]", "introduction": "<p><img src=\"https://p.sda1.dev/5/401465fb62a0b9926e834d1c814b3192/wstablife_tv_1000.jpg\"></p>", "tag_ids": ["548edfb54ab7379536f56351", "58a9c1e6f5dc363606ab42ed", "548ee0ea4ab7379536f56354", "624774a270e8f89b23a18556", "549ef207fe682f7549f1ea90"], "comments": 0, "downloads": 74, "finished": 164, "leechers": 0, "seeders": 0, "uploader_id": "59842d4fde238a777bf95202", "team_id": "58a9c1c9f5dc363606ab42ec", "publish_time": "2022-04-16T07:59:42.238Z", "magnet": "magnet:?xt=urn:btih:e4aa754477f3afd26d2eb0388331866c9cc5a10b", "infoHash": "e4aa754477f3afd26d2eb0388331866c9cc5a10b", "file_id": "625a77695aa8700007905e97", "teamsync": true, "content": [["[Nekomoe kissaten][Estab Life - Great Escape][05][720p][CHS].mp4", "318.57 MB"]], "size": "318.57 MB", "btskey": "", "sync": {"dmhy": "http://share.dmhy.org/topics/view/597589_04_Estab_Life_Great_Escape_05_720p.html", "acgrip": "https://acg.rip/t/253792", "nyaa": "https://nyaa.si/view/1515477", "acgnx": "https://share.acgnx.se/show-e4aa754477f3afd26d2eb0388331866c9cc5a10b.html", "acgnx_int": "https://www.acgnx.se/show-e4aa754477f3afd26d2eb0388331866c9cc5a10b.html"}}, {"_id": "6256e36f5aa87000078ad9b1", "category_tag_id": "549ef207fe682f7549f1ea90", "title": "\u3010\u55b5\u840c\u5976\u8336\u5c4b\u3011\u260504\u6708\u65b0\u756a\u2605[Estab Life: Great Escape][04][1080p][\u7e41\u9ad4][\u62db\u52df\u7ffb\u8b6f\u6821\u5c0d]", "introduction": "<p><img src=\"https://p.sda1.dev/5/401465fb62a0b9926e834d1c814b3192/wstablife_tv_1000.jpg\"></p>", "tag_ids": ["58a9c1e6f5dc363606ab42ed", "624774a270e8f89b23a18556", "548edfb54ab7379536f56351", "549ef207fe682f7549f1ea90", "548ee1204ab7379536f56357"], "comments": 0, "downloads": 144, "finished": 954, "leechers": 0, "seeders": 2, "uploader_id": "59842d4fde238a777bf95202", "team_id": "58a9c1c9f5dc363606ab42ec", "publish_time": "2022-04-13T14:51:27.172Z", "magnet": "magnet:?xt=urn:btih:67f3dfd78c7d12d80526c202e328b16fcfb09b44", "infoHash": "67f3dfd78c7d12d80526c202e328b16fcfb09b44", "file_id": "6256e36b5aa87000078ad9ad", "teamsync": true, "content": [["[Nekomoe kissaten][Estab Life - Great Escape][04][1080p][CHT].mp4", "708.49 MB"]], "size": "708.49 MB", "btskey": "", "sync": {"dmhy": "http://share.dmhy.org/topics/view/597376_04_Estab_Life_Great_Escape_04_1080p.html", "acgrip": "https://acg.rip/t/253649", "nyaa": "https://nyaa.si/view/1514246", "acgnx": "https://share.acgnx.se/show-67f3dfd78c7d12d80526c202e328b16fcfb09b44.html", "acgnx_int": "https://www.acgnx.se/show-67f3dfd78c7d12d80526c202e328b16fcfb09b44.html"}}, {"_id": "6256e3685aa87000078ad9a3", "category_tag_id": "549ef207fe682f7549f1ea90", "title": "\u3010\u55b5\u840c\u5976\u8336\u5c4b\u3011\u260504\u6708\u65b0\u756a\u2605[Estab Life: Great Escape][04][1080p][\u7b80\u4f53][\u62db\u52df\u7ffb\u8bd1\u6821\u5bf9]", "introduction": "<p><img src=\"https://p.sda1.dev/5/401465fb62a0b9926e834d1c814b3192/wstablife_tv_1000.jpg\"></p>", "tag_ids": ["548edfb54ab7379536f56351", "58a9c1e6f5dc363606ab42ed", "548ee0ea4ab7379536f56354", "624774a270e8f89b23a18556", "549ef207fe682f7549f1ea90"], "comments": 0, "downloads": 152, "finished": 929, "leechers": 0, "seeders": 34, "uploader_id": "59842d4fde238a777bf95202", "team_id": "58a9c1c9f5dc363606ab42ec", "publish_time": "2022-04-13T14:51:20.133Z", "magnet": "magnet:?xt=urn:btih:954262deef69df2804a82d109b33c6c315968343", "infoHash": "954262deef69df2804a82d109b33c6c315968343", "file_id": "6256e3645aa87000078ad99e", "teamsync": true, "content": [["[Nekomoe kissaten][Estab Life - Great Escape][04][1080p][CHS].mp4", "708.53 MB"]], "size": "708.53 MB", "btskey": "", "sync": {"dmhy": "http://share.dmhy.org/topics/view/597375_04_Estab_Life_Great_Escape_04_1080p.html", "acgrip": "https://acg.rip/t/253648", "nyaa": "https://nyaa.si/view/1514245", "acgnx": "https://share.acgnx.se/show-954262deef69df2804a82d109b33c6c315968343.html", "acgnx_int": "https://www.acgnx.se/show-954262deef69df2804a82d109b33c6c315968343.html"}}, {"_id": "6256e3615aa87000078ad995", "category_tag_id": "549ef207fe682f7549f1ea90", "title": "\u3010\u55b5\u840c\u5976\u8336\u5c4b\u3011\u260504\u6708\u65b0\u756a\u2605[Estab Life: Great Escape][04][720p][\u7e41\u9ad4][\u62db\u52df\u7ffb\u8b6f\u6821\u5c0d]", "introduction": "<p><img src=\"https://p.sda1.dev/5/401465fb62a0b9926e834d1c814b3192/wstablife_tv_1000.jpg\"></p>", "tag_ids": ["58a9c1e6f5dc363606ab42ed", "624774a270e8f89b23a18556", "548edfb54ab7379536f56351", "549ef207fe682f7549f1ea90", "548ee1204ab7379536f56357"], "comments": 0, "downloads": 96, "finished": 662, "leechers": 0, "seeders": 1, "uploader_id": "59842d4fde238a777bf95202", "team_id": "58a9c1c9f5dc363606ab42ec", "publish_time": "2022-04-13T14:51:13.079Z", "magnet": "magnet:?xt=urn:btih:d24953ac6091718607047b3c3f0f05357252fbc3", "infoHash": "d24953ac6091718607047b3c3f0f05357252fbc3", "file_id": "6256e35d5aa87000078ad98f", "teamsync": true, "content": [["[Nekomoe kissaten][Estab Life - Great Escape][04][720p][CHT].mp4", "329.55 MB"]], "size": "329.55 MB", "btskey": "", "sync": {"dmhy": "http://share.dmhy.org/topics/view/597374_04_Estab_Life_Great_Escape_04_720p.html", "acgrip": "https://acg.rip/t/253647", "nyaa": "https://nyaa.si/view/1514244", "acgnx": "https://share.acgnx.se/show-d24953ac6091718607047b3c3f0f05357252fbc3.html", "acgnx_int": "https://www.acgnx.se/show-d24953ac6091718607047b3c3f0f05357252fbc3.html"}}, {"_id": "6256e3595aa87000078ad98b", "category_tag_id": "549ef207fe682f7549f1ea90", "title": "\u3010\u55b5\u840c\u5976\u8336\u5c4b\u3011\u260504\u6708\u65b0\u756a\u2605[Estab Life: Great Escape][04][720p][\u7b80\u4f53][\u62db\u52df\u7ffb\u8bd1\u6821\u5bf9]", "introduction": "<p><img src=\"https://p.sda1.dev/5/401465fb62a0b9926e834d1c814b3192/wstablife_tv_1000.jpg\"></p>", "tag_ids": ["548edfb54ab7379536f56351", "58a9c1e6f5dc363606ab42ed", "548ee0ea4ab7379536f56354", "624774a270e8f89b23a18556", "549ef207fe682f7549f1ea90"], "comments": 0, "downloads": 88, "finished": 235, "leechers": 0, "seeders": 1, "uploader_id": "59842d4fde238a777bf95202", "team_id": "58a9c1c9f5dc363606ab42ec", "publish_time": "2022-04-13T14:51:05.516Z", "magnet": "magnet:?xt=urn:btih:75160ad7c24ac2931adb2bceecf04da453b6ebce", "infoHash": "75160ad7c24ac2931adb2bceecf04da453b6ebce", "file_id": "6256e3555aa87000078ad986", "teamsync": true, "content": [["[Nekomoe kissaten][Estab Life - Great Escape][04][720p][CHS].mp4", "329.59 MB"]], "size": "329.59 MB", "btskey": "", "sync": {"dmhy": "http://share.dmhy.org/topics/view/597373_04_Estab_Life_Great_Escape_04_720p.html", "acgrip": "https://acg.rip/t/253646", "nyaa": "https://nyaa.si/view/1514243", "acgnx": "https://share.acgnx.se/show-75160ad7c24ac2931adb2bceecf04da453b6ebce.html", "acgnx_int": "https://www.acgnx.se/show-75160ad7c24ac2931adb2bceecf04da453b6ebce.html"}}, {"_id": "6252fba65aa87000078540b7", "category_tag_id": "549ef207fe682f7549f1ea90", "title": "\u3010\u55b5\u840c\u5976\u8336\u5c4b\u3011\u260504\u6708\u65b0\u756a\u2605[Estab Life: Great Escape][03][1080p][\u7e41\u9ad4][\u62db\u52df\u7ffb\u8b6f\u6821\u5c0d]", "introduction": "<p><img src=\"https://p.sda1.dev/5/401465fb62a0b9926e834d1c814b3192/wstablife_tv_1000.jpg\"></p>", "tag_ids": ["58a9c1e6f5dc363606ab42ed", "624774a270e8f89b23a18556", "548edfb54ab7379536f56351", "549ef207fe682f7549f1ea90", "548ee1204ab7379536f56357"], "comments": 0, "downloads": 144, "finished": 1054, "leechers": 0, "seeders": 3, "uploader_id": "59842d4fde238a777bf95202", "team_id": "58a9c1c9f5dc363606ab42ec", "publish_time": "2022-04-10T15:45:42.625Z", "magnet": "magnet:?xt=urn:btih:a9df5f4a46512be3fe555bbd0d48949114849794", "infoHash": "a9df5f4a46512be3fe555bbd0d48949114849794", "file_id": "6252fba15aa87000078540a5", "teamsync": true, "content": [["[Nekomoe kissaten][Estab Life - Great Escape][03][1080p][CHT].mp4", "694.24 MB"]], "size": "694.24 MB", "btskey": "", "sync": {"dmhy": "http://share.dmhy.org/topics/view/597104_04_Estab_Life_Great_Escape_03_1080p.html", "acgrip": "https://acg.rip/t/253478", "nyaa": "https://nyaa.si/view/1513157", "acgnx": "https://share.acgnx.se/show-a9df5f4a46512be3fe555bbd0d48949114849794.html", "acgnx_int": "https://www.acgnx.se/show-a9df5f4a46512be3fe555bbd0d48949114849794.html"}}, {"_id": "6252fb9c5aa870000785409a", "category_tag_id": "549ef207fe682f7549f1ea90", "title": "\u3010\u55b5\u840c\u5976\u8336\u5c4b\u3011\u260504\u6708\u65b0\u756a\u2605[Estab Life: Great Escape][03][1080p][\u7b80\u4f53][\u62db\u52df\u7ffb\u8bd1\u6821\u5bf9]", "introduction": "<p><img src=\"https://p.sda1.dev/5/401465fb62a0b9926e834d1c814b3192/wstablife_tv_1000.jpg\"></p>", "tag_ids": ["548edfb54ab7379536f56351", "58a9c1e6f5dc363606ab42ed", "548ee0ea4ab7379536f56354", "624774a270e8f89b23a18556", "549ef207fe682f7549f1ea90"], "comments": 0, "downloads": 161, "finished": 1011, "leechers": 0, "seeders": 32, "uploader_id": "59842d4fde238a777bf95202", "team_id": "58a9c1c9f5dc363606ab42ec", "publish_time": "2022-04-10T15:45:32.436Z", "magnet": "magnet:?xt=urn:btih:af1c6cc695612ac9f7cccdf5fa4224778e0363cb", "infoHash": "af1c6cc695612ac9f7cccdf5fa4224778e0363cb", "file_id": "6252fb985aa870000785408f", "teamsync": true, "content": [["[Nekomoe kissaten][Estab Life - Great Escape][03][1080p][CHS].mp4", "694.3 MB"]], "size": "694.3 MB", "btskey": "", "sync": {"dmhy": "http://share.dmhy.org/topics/view/597103_04_Estab_Life_Great_Escape_03_1080p.html", "acgrip": "https://acg.rip/t/253477", "nyaa": "https://nyaa.si/view/1513156", "acgnx": "https://share.acgnx.se/show-af1c6cc695612ac9f7cccdf5fa4224778e0363cb.html", "acgnx_int": "https://www.acgnx.se/show-af1c6cc695612ac9f7cccdf5fa4224778e0363cb.html"}}, {"_id": "6252fb935aa8700007854082", "category_tag_id": "549ef207fe682f7549f1ea90", "title": "\u3010\u55b5\u840c\u5976\u8336\u5c4b\u3011\u260504\u6708\u65b0\u756a\u2605[Estab Life: Great Escape][03][720p][\u7e41\u9ad4][\u62db\u52df\u7ffb\u8b6f\u6821\u5c0d]", "introduction": "<p><img src=\"https://p.sda1.dev/5/401465fb62a0b9926e834d1c814b3192/wstablife_tv_1000.jpg\"></p>", "tag_ids": ["58a9c1e6f5dc363606ab42ed", "624774a270e8f89b23a18556", "548edfb54ab7379536f56351", "549ef207fe682f7549f1ea90", "548ee1204ab7379536f56357"], "comments": 0, "downloads": 93, "finished": 750, "leechers": 0, "seeders": 2, "uploader_id": "59842d4fde238a777bf95202", "team_id": "58a9c1c9f5dc363606ab42ec", "publish_time": "2022-04-10T15:45:23.639Z", "magnet": "magnet:?xt=urn:btih:11d2b182dc781017b8e4092705775701648265ea", "infoHash": "11d2b182dc781017b8e4092705775701648265ea", "file_id": "6252fb8e5aa8700007854072", "teamsync": true, "content": [["[Nekomoe kissaten][Estab Life - Great Escape][03][720p][CHT].mp4", "315.85 MB"]], "size": "315.85 MB", "btskey": "", "sync": {"dmhy": "http://share.dmhy.org/topics/view/597102_04_Estab_Life_Great_Escape_03_720p.html", "acgrip": "https://acg.rip/t/253476", "nyaa": "https://nyaa.si/view/1513155", "acgnx": "https://share.acgnx.se/show-11d2b182dc781017b8e4092705775701648265ea.html", "acgnx_int": "https://www.acgnx.se/show-11d2b182dc781017b8e4092705775701648265ea.html"}}, {"_id": "6252fb885aa8700007854064", "category_tag_id": "549ef207fe682f7549f1ea90", "title": "\u3010\u55b5\u840c\u5976\u8336\u5c4b\u3011\u260504\u6708\u65b0\u756a\u2605[Estab Life: Great Escape][03][720p][\u7b80\u4f53][\u62db\u52df\u7ffb\u8bd1\u6821\u5bf9]", "introduction": "<p><img src=\"https://p.sda1.dev/5/401465fb62a0b9926e834d1c814b3192/wstablife_tv_1000.jpg\"></p>", "tag_ids": ["548edfb54ab7379536f56351", "58a9c1e6f5dc363606ab42ed", "548ee0ea4ab7379536f56354", "624774a270e8f89b23a18556", "549ef207fe682f7549f1ea90"], "comments": 0, "downloads": 87, "finished": 273, "leechers": 0, "seeders": 2, "uploader_id": "59842d4fde238a777bf95202", "team_id": "58a9c1c9f5dc363606ab42ec", "publish_time": "2022-04-10T15:45:12.575Z", "magnet": "magnet:?xt=urn:btih:48a01fd82ed4352e5bc6c2a630703e928715089b", "infoHash": "48a01fd82ed4352e5bc6c2a630703e928715089b", "file_id": "6252fb835aa8700007854054", "teamsync": true, "content": [["[Nekomoe kissaten][Estab Life - Great Escape][03][720p][CHS].mp4", "315.87 MB"]], "size": "315.87 MB", "btskey": "", "sync": {"dmhy": "http://share.dmhy.org/topics/view/597101_04_Estab_Life_Great_Escape_03_720p.html", "acgrip": "https://acg.rip/t/253476", "nyaa": "https://nyaa.si/view/1513154", "acgnx": "https://share.acgnx.se/show-48a01fd82ed4352e5bc6c2a630703e928715089b.html", "acgnx_int": "https://www.acgnx.se/show-48a01fd82ed4352e5bc6c2a630703e928715089b.html"}}, {"_id": "625110715aa8700007826654", "category_tag_id": "549ef207fe682f7549f1ea90", "title": "\u3010\u55b5\u840c\u5976\u8336\u5c4b\u3011\u260504\u6708\u65b0\u756a\u2605[Estab Life: Great Escape][02][1080p][\u7e41\u9ad4][\u62db\u52df\u7ffb\u8b6f\u6821\u5c0d]", "introduction": "<p><img src=\"https://p.sda1.dev/5/401465fb62a0b9926e834d1c814b3192/wstablife_tv_1000.jpg\"></p>", "tag_ids": ["58a9c1e6f5dc363606ab42ed", "624774a270e8f89b23a18556", "548edfb54ab7379536f56351", "549ef207fe682f7549f1ea90", "548ee1204ab7379536f56357"], "comments": 0, "downloads": 144, "finished": 1096, "leechers": 0, "seeders": 6, "uploader_id": "59842d4fde238a777bf95202", "team_id": "58a9c1c9f5dc363606ab42ec", "publish_time": "2022-04-09T04:49:53.524Z", "magnet": "magnet:?xt=urn:btih:f7c8165895db406ad3138fb0356279c661887862", "infoHash": "f7c8165895db406ad3138fb0356279c661887862", "file_id": "625110645aa8700007826637", "teamsync": true, "content": [["[Nekomoe kissaten][Estab Life - Great Escape][02][1080p][CHT].mp4", "587.91 MB"]], "size": "587.91 MB", "btskey": "", "sync": {"dmhy": "http://share.dmhy.org/topics/view/596914_04_Estab_Life_Great_Escape_02_1080p.html", "acgrip": "https://acg.rip/t/253350", "nyaa": "https://nyaa.si/view/1512280", "acgnx": "https://share.acgnx.se/show-f7c8165895db406ad3138fb0356279c661887862.html", "acgnx_int": "https://www.acgnx.se/show-f7c8165895db406ad3138fb0356279c661887862.html"}}, {"_id": "625110495aa870000782660d", "category_tag_id": "549ef207fe682f7549f1ea90", "title": "\u3010\u55b5\u840c\u5976\u8336\u5c4b\u3011\u260504\u6708\u65b0\u756a\u2605[Estab Life: Great Escape][02][1080p][\u7b80\u4f53][\u62db\u52df\u7ffb\u8bd1\u6821\u5bf9]", "introduction": "<p><img src=\"https://p.sda1.dev/5/401465fb62a0b9926e834d1c814b3192/wstablife_tv_1000.jpg\"></p>", "tag_ids": ["548edfb54ab7379536f56351", "58a9c1e6f5dc363606ab42ed", "548ee0ea4ab7379536f56354", "624774a270e8f89b23a18556", "549ef207fe682f7549f1ea90"], "comments": 0, "downloads": 164, "finished": 941, "leechers": 0, "seeders": 37, "uploader_id": "59842d4fde238a777bf95202", "team_id": "58a9c1c9f5dc363606ab42ec", "publish_time": "2022-04-09T04:49:13.577Z", "magnet": "magnet:?xt=urn:btih:1d518217f13b359461e841d75e30c10ca0f9a4ec", "infoHash": "1d518217f13b359461e841d75e30c10ca0f9a4ec", "file_id": "625110365aa87000078265f0", "teamsync": true, "content": [["[Nekomoe kissaten][Estab Life - Great Escape][02][1080p][CHS].mp4", "587.9 MB"]], "size": "587.9 MB", "btskey": "", "sync": {"dmhy": "http://share.dmhy.org/topics/view/596913_04_Estab_Life_Great_Escape_02_1080p.html", "acgrip": "https://acg.rip/t/253349", "nyaa": "https://nyaa.si/view/1512279", "acgnx": "https://share.acgnx.se/show-1d518217f13b359461e841d75e30c10ca0f9a4ec.html", "acgnx_int": "https://www.acgnx.se/show-1d518217f13b359461e841d75e30c10ca0f9a4ec.html"}}, {"_id": "625110315aa87000078265e7", "category_tag_id": "549ef207fe682f7549f1ea90", "title": "\u3010\u55b5\u840c\u5976\u8336\u5c4b\u3011\u260504\u6708\u65b0\u756a\u2605[Estab Life: Great Escape][02][720p][\u7e41\u9ad4][\u62db\u52df\u7ffb\u8b6f\u6821\u5c0d]", "introduction": "<p><img src=\"https://p.sda1.dev/5/401465fb62a0b9926e834d1c814b3192/wstablife_tv_1000.jpg\"></p>", "tag_ids": ["58a9c1e6f5dc363606ab42ed", "624774a270e8f89b23a18556", "548edfb54ab7379536f56351", "549ef207fe682f7549f1ea90", "548ee1204ab7379536f56357"], "comments": 0, "downloads": 96, "finished": 561, "leechers": 0, "seeders": 1, "uploader_id": "59842d4fde238a777bf95202", "team_id": "58a9c1c9f5dc363606ab42ec", "publish_time": "2022-04-09T04:48:49.487Z", "magnet": "magnet:?xt=urn:btih:af30f9203519ab084cf2d4641f15d6552ad7c418", "infoHash": "af30f9203519ab084cf2d4641f15d6552ad7c418", "file_id": "625110275aa87000078265cf", "teamsync": true, "content": [["[Nekomoe kissaten][Estab Life - Great Escape][02][720p][CHT].mp4", "263.94 MB"]], "size": "263.94 MB", "btskey": "", "sync": {"dmhy": "http://share.dmhy.org/topics/view/596912_04_Estab_Life_Great_Escape_02_720p.html", "acgrip": "https://acg.rip/t/253348", "nyaa": "https://nyaa.si/view/1512278", "acgnx": "https://share.acgnx.se/show-af30f9203519ab084cf2d4641f15d6552ad7c418.html", "acgnx_int": "https://www.acgnx.se/show-af30f9203519ab084cf2d4641f15d6552ad7c418.html"}}, {"_id": "625110135aa87000078265b7", "category_tag_id": "549ef207fe682f7549f1ea90", "title": "\u3010\u55b5\u840c\u5976\u8336\u5c4b\u3011\u260504\u6708\u65b0\u756a\u2605[Estab Life: Great Escape][02][720p][\u7b80\u4f53][\u62db\u52df\u7ffb\u8bd1\u6821\u5bf9]", "introduction": "<p><img src=\"https://p.sda1.dev/5/401465fb62a0b9926e834d1c814b3192/wstablife_tv_1000.jpg\"></p>", "tag_ids": ["548edfb54ab7379536f56351", "58a9c1e6f5dc363606ab42ed", "548ee0ea4ab7379536f56354", "624774a270e8f89b23a18556", "549ef207fe682f7549f1ea90"], "comments": 0, "downloads": 82, "finished": 257, "leechers": 0, "seeders": 4, "uploader_id": "59842d4fde238a777bf95202", "team_id": "58a9c1c9f5dc363606ab42ec", "publish_time": "2022-04-09T04:48:19.592Z", "magnet": "magnet:?xt=urn:btih:804e2a1966d52027ed78ad918ec188f735b0b8e1", "infoHash": "804e2a1966d52027ed78ad918ec188f735b0b8e1", "file_id": "6251100c5aa87000078265a7", "teamsync": true, "content": [["[Nekomoe kissaten][Estab Life - Great Escape][02][720p][CHS].mp4", "263.86 MB"]], "size": "263.86 MB", "btskey": "", "sync": {"dmhy": "http://share.dmhy.org/topics/view/596911_04_Estab_Life_Great_Escape_02_720p.html", "acgrip": "https://acg.rip/t/253347", "nyaa": "https://nyaa.si/view/1512277", "acgnx": "https://share.acgnx.se/show-804e2a1966d52027ed78ad918ec188f735b0b8e1.html", "acgnx_int": "https://www.acgnx.se/show-804e2a1966d52027ed78ad918ec188f735b0b8e1.html"}}, {"_id": "624e7ae65aa87000077f4ae7", "category_tag_id": "549ef207fe682f7549f1ea90", "title": "\u3010\u55b5\u840c\u5976\u8336\u5c4b\u3011\u260504\u6708\u65b0\u756a\u2605[Estab Life: Great Escape][01][1080p][\u7e41\u9ad4][\u62db\u52df\u7ffb\u8b6f\u6821\u5c0d]", "introduction": "<p><img src=\"https://p.sda1.dev/5/401465fb62a0b9926e834d1c814b3192/wstablife_tv_1000.jpg\"></p>", "tag_ids": ["58a9c1e6f5dc363606ab42ed", "624774a270e8f89b23a18556", "548edfb54ab7379536f56351", "549ef207fe682f7549f1ea90", "548ee1204ab7379536f56357"], "comments": 0, "downloads": 168, "finished": 1538, "leechers": 0, "seeders": 10, "uploader_id": "59842d4fde238a777bf95202", "team_id": "58a9c1c9f5dc363606ab42ec", "publish_time": "2022-04-07T05:47:18.608Z", "magnet": "magnet:?xt=urn:btih:433a03c940fa156a0ce590a2eb9d0e27664cba03", "infoHash": "433a03c940fa156a0ce590a2eb9d0e27664cba03", "file_id": "624e7ae05aa87000077f4adb", "teamsync": true, "content": [["[Nekomoe kissaten][Estab Life - Great Escape][01][1080p][CHT].mp4", "649.17 MB"]], "size": "649.17 MB", "btskey": "", "sync": {"dmhy": "http://share.dmhy.org/topics/view/596736_04_Estab_Life_Great_Escape_01_1080p.html", "acgrip": "https://acg.rip/t/253251", "nyaa": "https://nyaa.si/view/1511328", "acgnx": "https://share.acgnx.se/show-433a03c940fa156a0ce590a2eb9d0e27664cba03.html", "acgnx_int": "https://www.acgnx.se/show-433a03c940fa156a0ce590a2eb9d0e27664cba03.html"}}, {"_id": "624e7add5aa87000077f4ad7", "category_tag_id": "549ef207fe682f7549f1ea90", "title": "\u3010\u55b5\u840c\u5976\u8336\u5c4b\u3011\u260504\u6708\u65b0\u756a\u2605[Estab Life: Great Escape][01][1080p][\u7b80\u4f53][\u62db\u52df\u7ffb\u8bd1\u6821\u5bf9]", "introduction": "<p><img src=\"https://p.sda1.dev/5/401465fb62a0b9926e834d1c814b3192/wstablife_tv_1000.jpg\"></p>", "tag_ids": ["548edfb54ab7379536f56351", "58a9c1e6f5dc363606ab42ed", "548ee0ea4ab7379536f56354", "624774a270e8f89b23a18556", "549ef207fe682f7549f1ea90"], "comments": 0, "downloads": 173, "finished": 1203, "leechers": 0, "seeders": 38, "uploader_id": "59842d4fde238a777bf95202", "team_id": "58a9c1c9f5dc363606ab42ec", "publish_time": "2022-04-07T05:47:09.206Z", "magnet": "magnet:?xt=urn:btih:d4acb4a5e3a6a10c5cfae21d49ce24a1df2dc6ba", "infoHash": "d4acb4a5e3a6a10c5cfae21d49ce24a1df2dc6ba", "file_id": "624e7ad85aa87000077f4ad0", "teamsync": true, "content": [["[Nekomoe kissaten][Estab Life - Great Escape][01][1080p][CHS].mp4", "649.15 MB"]], "size": "649.15 MB", "btskey": "", "sync": {"dmhy": "http://share.dmhy.org/topics/view/596735_04_Estab_Life_Great_Escape_01_1080p.html", "acgrip": "https://acg.rip/t/253250", "nyaa": "https://nyaa.si/view/1511327", "acgnx": "https://share.acgnx.se/show-d4acb4a5e3a6a10c5cfae21d49ce24a1df2dc6ba.html", "acgnx_int": "https://www.acgnx.se/show-d4acb4a5e3a6a10c5cfae21d49ce24a1df2dc6ba.html"}}, {"_id": "624e7ad35aa87000077f4ac9", "category_tag_id": "549ef207fe682f7549f1ea90", "title": "\u3010\u55b5\u840c\u5976\u8336\u5c4b\u3011\u260504\u6708\u65b0\u756a\u2605[Estab Life: Great Escape][01][720p][\u7e41\u9ad4][\u62db\u52df\u7ffb\u8b6f\u6821\u5c0d]", "introduction": "<p><img src=\"https://p.sda1.dev/5/401465fb62a0b9926e834d1c814b3192/wstablife_tv_1000.jpg\"></p>", "tag_ids": ["58a9c1e6f5dc363606ab42ed", "624774a270e8f89b23a18556", "548edfb54ab7379536f56351", "549ef207fe682f7549f1ea90", "548ee1204ab7379536f56357"], "comments": 0, "downloads": 63, "finished": 903, "leechers": 0, "seeders": 1, "uploader_id": "59842d4fde238a777bf95202", "team_id": "58a9c1c9f5dc363606ab42ec", "publish_time": "2022-04-07T05:46:59.090Z", "magnet": "magnet:?xt=urn:btih:ab1e5e34e87bf2db0debe5b9848610bb5498bb3c", "infoHash": "ab1e5e34e87bf2db0debe5b9848610bb5498bb3c", "file_id": "624e7ab85aa87000077f4aa9", "teamsync": true, "content": [["[Nekomoe kissaten][Estab Life - Great Escape][01][720p][CHT].mp4", "295.76 MB"]], "size": "295.76 MB", "btskey": "", "sync": {"dmhy": "http://share.dmhy.org/topics/view/596734_04_Estab_Life_Great_Escape_01_720p.html", "acgrip": "https://acg.rip/t/253249", "nyaa": "https://nyaa.si/view/1511326", "acgnx": "https://share.acgnx.se/show-ab1e5e34e87bf2db0debe5b9848610bb5498bb3c.html", "acgnx_int": "https://www.acgnx.se/show-ab1e5e34e87bf2db0debe5b9848610bb5498bb3c.html"}}, {"_id": "624e7ab05aa87000077f4a9c", "category_tag_id": "549ef207fe682f7549f1ea90", "title": "\u3010\u55b5\u840c\u5976\u8336\u5c4b\u3011\u260504\u6708\u65b0\u756a\u2605[Estab Life: Great Escape][01][720p][\u7b80\u4f53][\u62db\u52df\u7ffb\u8bd1\u6821\u5bf9]", "introduction": "<p><img src=\"https://p.sda1.dev/5/401465fb62a0b9926e834d1c814b3192/wstablife_tv_1000.jpg\"></p>", "tag_ids": ["548edfb54ab7379536f56351", "58a9c1e6f5dc363606ab42ed", "548ee0ea4ab7379536f56354", "624774a270e8f89b23a18556", "549ef207fe682f7549f1ea90"], "comments": 0, "downloads": 58, "finished": 373, "leechers": 0, "seeders": 2, "uploader_id": "59842d4fde238a777bf95202", "team_id": "58a9c1c9f5dc363606ab42ec", "publish_time": "2022-04-07T05:46:24.519Z", "magnet": "magnet:?xt=urn:btih:d1ed838f3e7a82f7b315e34a5f5b8d1f8d65b5f0", "infoHash": "d1ed838f3e7a82f7b315e34a5f5b8d1f8d65b5f0", "file_id": "624e79b95aa87000077f4929", "teamsync": true, "content": [["[Nekomoe kissaten][Estab Life - Great Escape][01][720p][CHS].mp4", "295.73 MB"]], "size": "295.73 MB", "btskey": "", "sync": {"dmhy": "http://share.dmhy.org/topics/view/596733_04_Estab_Life_Great_Escape_01_720p.html", "acgrip": "https://acg.rip/t/253248", "nyaa": "https://nyaa.si/view/1511325", "acgnx": "https://share.acgnx.se/show-d1ed838f3e7a82f7b315e34a5f5b8d1f8d65b5f0.html", "acgnx_int": "https://www.acgnx.se/show-d1ed838f3e7a82f7b315e34a5f5b8d1f8d65b5f0.html"}}]