[{"_id": "62a4c3def248710007aa8d05", "category_tag_id": "549ef207fe682f7549f1ea90", "title": "[Lilith-Raws] \u5973\u5fcd\u8005\u693f\u7684\u5fc3\u4e8b / Kunoichi Tsubaki no Mune no Uchi - 10 [Baha][WEB-DL][1080p][AVC AAC][CHT][MP4]", "introduction": "<p>Telegram Update Notification Channel : <a href=\"https://t.me/lilithraws\">https://t.me/lilithraws</a><br>Open Data Platform : <a href=\"https://open.lilithraws.cf\">https://open.lilithraws.cf</a> (Support Streaming and Direct Download)<br>Twitter : <a href=\"https://twitter.com/lilithraws\">https://twitter.com/lilithraws</a></p><p>We're recommending <a href=\"https://github.com/c0re100/qBittorrent-Enhanced-Edition/releases\">qBittorrent Enhanced Edition</a> for downloading our seeds.<br><a href=\"https://bit.ly/lilithcrypto\"><img src=\"https://p.sda1.dev/6/0180852211c0976ae980b760e0a86221\" alt=\"Lilith Crypto Banner\"></a></p><p>Paypal Donation -&gt; <a href=\"https://donorbox.org/lilithraws\">https://donorbox.org/lilithraws</a><br>Support Us on Patreon -&gt; <a href=\"https://www.patreon.com/lilithraws\">https://www.patreon.com/lilithraws</a></p>", "tag_ids": ["548ee2ce4ab7379536f56358", "55c3036c7030f8c855f992ee", "548ee1204ab7379536f56357", "5d8b3245306f1a0007bd7aca", "548edffb4ab7379536f56352", "624774ab70e8f89b23a18584", "549ef207fe682f7549f1ea90"], "comments": 0, "downloads": 161, "finished": 1815, "leechers": 2, "seeders": 75, "uploader_id": "5d333d66306f1a0007b6c0bf", "team_id": "5d8b24be306f1a0007bd7998", "publish_time": "2022-06-11T16:33:34.352Z", "magnet": "magnet:?xt=urn:btih:16dca88a211cf5590aa3491db37530436f719e6b", "infoHash": "16dca88a211cf5590aa3491db37530436f719e6b", "file_id": "62a4c3dcf248710007aa8d02", "teamsync": true, "content": [["[Lilith-Raws] Kunoichi Tsubaki no Mune no Uchi - 10 [Baha][WEB-DL][1080p][AVC AAC][CHT][MP4].mp4", "458.17 MB"]], "size": "458.17 MB", "btskey": "", "sync": {"dmhy": "http://share.dmhy.org/topics/view/602740_Lilith-Raws_Kunoichi_Tsubaki_no_Mune_no_Uchi_-_10_Baha_WEB-DL_1080p_AVC_AAC_CHT_MP4.html", "acgrip": "https://acg.rip/t/257083", "acgnx": "https://share.acgnx.se/show-16dca88a211cf5590aa3491db37530436f719e6b.html"}}, {"_id": "62a4c381f248710007aa8ca6", "category_tag_id": "549ef207fe682f7549f1ea90", "title": "[ANi] In the Heart of Kunoichi Tsubaki -  \u5973\u5fcd\u8005\u693f\u7684\u5fc3\u4e8b - 10 [1080P][Baha][WEB-DL][AAC AVC][CHT][MP4]", "introduction": "<p>Torrent Info By: ANi API (Auto Generated)</p> <p>Subtitle:</p> <p>&emsp;HardSub</p> <p>Mediainfo:</p> <p>&emsp;Resolution: 1080P</p> <p>&emsp;Video Format: AVC</p> <p>&emsp;Audio Format: AAC</p> <br><p>Note:</p> <p>&emsp;Magnet link is lack of http source info. If you want to download the file asap, please use the torrent file rather than the magnet link.</p> <p>&emsp;Xunlei, torrent media player and offline downloader has been banned by our seeding server.</p> <p>&emsp;This torrent using the HTTP Sources for the first content distributor and the source file stored on IPFS</p> <p>&emsp;This automatic torrent publisher currently in beta test. If have any thought about this publisher. Feel free to contact me.</p> <p>&emsp;Telegram Chat: <a title=\"https://t.me/+SH8EUievFGLKQew_\" href=\"https://t.me/+SH8EUievFGLKQew_\" target=\"_blank\">https://t.me/+SH8EUievFGLKQew_</a></p> <p>2022/6/11 16:32:00 UTC+0000 (Coordinated Universal Time)</p>", "tag_ids": ["548ee2ce4ab7379536f56358", "6039092432f14c00074809b9", "55c3036c7030f8c855f992ee", "548ee1204ab7379536f56357", "548edffb4ab7379536f56352", "624774ab70e8f89b23a18584", "549ef207fe682f7549f1ea90"], "comments": 0, "downloads": 67, "finished": 350, "leechers": 1, "seeders": 25, "uploader_id": "5e43f999306f1a0007cd093f", "team_id": "60313a6e32f14c000745a5e2", "publish_time": "2022-06-11T16:32:01.763Z", "magnet": "magnet:?xt=urn:btih:130d7da438262be68be3ce1540c0934d3f9128e7", "infoHash": "130d7da438262be68be3ce1540c0934d3f9128e7", "file_id": "62a4c381f248710007aa8ca5", "teamsync": true, "content": [["[ANi] \u5973\u5fcd\u8005\u693f\u7684\u5fc3\u4e8b - 10 [1080P][Baha][WEB-DL][AAC AVC][CHT].mp4", "458.48 MB"]], "size": "458.48 MB", "btskey": "", "sync": {"dmhy": "http://share.dmhy.org/topics/view/602738_ANi_In_the_Heart_of_Kunoichi_Tsubaki_-_-_10_1080P_Baha_WEB-DL_AAC_AVC_CHT_MP4.html", "acgrip": "https://acg.rip/t/257081", "nyaa": "https://nyaa.si/view/1540441", "acgnx": "https://share.acgnx.se/show-130d7da438262be68be3ce1540c0934d3f9128e7.html"}}, {"_id": "62a4c374f248710007aa8c9c", "category_tag_id": "549ef207fe682f7549f1ea90", "title": "[NC-Raws] \u5973\u5fcd\u8005\u693f\u7684\u5fc3\u4e8b / Kunoichi Tsubaki no Mune no Uchi - 10 (Baha 1920x1080 AVC AAC MP4)", "introduction": "\n<p><img src=\"https://rr1---bh.raws.dev/B/2KU/36/416daef79e9c9dddb242c4c7af1gpmw5.JPG\" alt /></p> <hr /> <p><strong><i>Kunoichi Tsubaki no Mune no Uchi - EP 10</i></strong><br><strong>[<a href=\"https://www.themoviedb.org/tv/138180\" target=\"_blank\">tmdb</a>] | [<a href=\"https://bgm.tv/subject/351973\" target=\"_blank\">bangumi.tv</a>]</strong></p> <hr /> <p><strong>Information:</strong></p> <ul>\n<li><strong>Overall Bit Rate:</strong> 2 707 kb/s</li> <li><strong>Subtitle:</strong> HardSub - \u4e2d\u6587\uff08\u7e41\u9ad4\uff09</li> <li><strong>Duration:</strong> 00:23:40.110</li> <li><strong>CRC32:</strong> 0C3DA775</li> <li><strong><a href=\"https://rentry.co/f4wf6/raw\" target=\"_blank\">MediaInfo</a></strong></li>\n</ul> <hr /> <p>In case of any issues with the file, please let us know via the contact details below.<br><strong>Xunlei has been banned by default.</strong><br><strong>Seeding after downloading is appreciated.</strong></p> <hr /> <p>Join us on Telegram at <a href=\"https://t.me/NC_Raws_Channel\" target=\"_blank\">NC-Raws</a> | <a href=\"https://nc-raws.org\" target=\"_blank\">Website</a></p>\n", "tag_ids": ["548ee2ce4ab7379536f56358", "55c3036c7030f8c855f992ee", "548edffb4ab7379536f56352", "600c009432f14c00073a9f49", "624774ab70e8f89b23a18584", "549ef207fe682f7549f1ea90"], "comments": 0, "downloads": 80, "finished": 642, "leechers": 1, "seeders": 24, "uploader_id": "60098e9132f14c000739f8f4", "team_id": "60098fb532f14c000739f911", "publish_time": "2022-06-11T16:31:48.419Z", "magnet": "magnet:?xt=urn:btih:3b97d602113bd01585d8800aa4a10b0876398f73", "infoHash": "3b97d602113bd01585d8800aa4a10b0876398f73", "file_id": "62a4c374f248710007aa8c9b", "teamsync": true, "content": [["[NC-Raws] \u5973\u5fcd\u8005\u693f\u7684\u5fc3\u4e8b - 10 (Baha 1920x1080 AVC AAC MP4) [0C3DA775].mp4", "458.33 MB"]], "size": "458.33 MB", "btskey": "", "sync": {"dmhy": "http://share.dmhy.org/topics/view/602737_NC-Raws_Kunoichi_Tsubaki_no_Mune_no_Uchi_-_10_Baha_1920x1080_AVC_AAC_MP4.html", "acgrip": "https://acg.rip/t/257080", "acgnx": "https://share.acgnx.se/show-3b97d602113bd01585d8800aa4a10b0876398f73.html"}}, {"_id": "62a4c368f248710007aa8c8f", "category_tag_id": "549ef207fe682f7549f1ea90", "title": "[NC-Raws] \u5973\u5fcd\u8005\u693f\u7684\u5fc3\u4e8b / Kunoichi Tsubaki no Mune no Uchi - 10 (B-Global 1920x1080 HEVC AAC MKV)", "introduction": "\n<p><img src=\"https://rr1---bg.raws.dev/bfs/intl/management/9cfd482c7c13b990fbfa72b9e0cf6f677eefc016.png@960w_540h_100Q_1c.jpg\" alt /></p> <hr /> <p><strong><i>Kunoichi Tsubaki no Mune no Uchi - EP 10</i></strong><br><strong>[<a href=\"https://www.themoviedb.org/tv/138180\" target=\"_blank\">tmdb</a>] | [<a href=\"https://bgm.tv/subject/351973\" target=\"_blank\">bangumi.tv</a>]</strong></p>\n<hr /> <p><strong>Information:</strong></p> <ul>\n<li><strong>Overall Bit Rate:</strong> 3 804 kb/s</li> <li><strong>Subtitle:</strong> English, \u0e20\u0e32\u0e29\u0e32\u0e44\u0e17\u0e22, Ti\u1ebfng Vi\u1ec7t, Bahasa Indonesia, \u4e2d\u6587\uff08\u7e41\u4f53\uff09, \u4e2d\u6587\uff08\u7b80\u4f53\uff09| \u7e41\u5316\u59ec</li> <li><strong>Duration:</strong> 00:23:41.369</li> <li><strong>CRC32:</strong> 549D0812</li> <li><strong><a href=\"https://rentry.co/pvpd2/raw\" target=\"_blank\">MediaInfo</a></strong></li>\n</ul> <hr /> <p>In case of any issues with the file, please let us know via the contact details below.<br><strong>Xunlei has been banned by default, Chinese subtitles may not match the source, please solve it by yourself.</strong><br><strong>Seeding after downloading is appreciated.</strong></p> <hr /> <p>Join us on Telegram at <a href=\"https://t.me/NC_Raws_Channel\" target=\"_blank\">NC-Raws</a> | <a href=\"https://nc-raws.org\" target=\"_blank\">Website</a></p>\n", "tag_ids": ["548ee2ce4ab7379536f56358", "55c3024a7030f8c855f992ed", "548ee00b4ab7379536f56353", "600c009432f14c00073a9f49", "624774ab70e8f89b23a18584", "549ef207fe682f7549f1ea90"], "comments": 0, "downloads": 53, "finished": 175, "leechers": 0, "seeders": 16, "uploader_id": "60098e9132f14c000739f8f4", "team_id": "60098fb532f14c000739f911", "publish_time": "2022-06-11T16:31:36.533Z", "magnet": "magnet:?xt=urn:btih:b4d2f6f68ee8a83a065d6069783f06009c8041b3", "infoHash": "b4d2f6f68ee8a83a065d6069783f06009c8041b3", "file_id": "62a4c368f248710007aa8c8e", "teamsync": true, "content": [["[NC-Raws] \u5973\u5fcd\u8005\u693f\u7684\u5fc3\u4e8b - 10 (B-Global 1920x1080 HEVC AAC MKV) [549D0812].mkv", "644.47 MB"]], "size": "644.47 MB", "btskey": "", "sync": {"dmhy": "http://share.dmhy.org/topics/view/602735_NC-Raws_Kunoichi_Tsubaki_no_Mune_no_Uchi_-_10_B-Global_1920x1080_HEVC_AAC_MKV.html", "acgrip": "https://acg.rip/t/257078", "acgnx": "https://share.acgnx.se/show-b4d2f6f68ee8a83a065d6069783f06009c8041b3.html"}}, {"_id": "629b8cd9f707900007ab6699", "category_tag_id": "549ef207fe682f7549f1ea90", "title": "[Lilith-Raws] \u5973\u5fcd\u8005\u693f\u7684\u5fc3\u4e8b / Kunoichi Tsubaki no Mune no Uchi - 09 [Baha][WEB-DL][1080p][AVC AAC][CHT][MP4]", "introduction": "<p>Telegram Update Notification Channel : <a href=\"https://t.me/lilithraws\">https://t.me/lilithraws</a><br>Open Data Platform : <a href=\"https://open.lilithraws.cf\">https://open.lilithraws.cf</a> (Support Streaming and Direct Download)<br>Twitter : <a href=\"https://twitter.com/lilithraws\">https://twitter.com/lilithraws</a></p><p>We're recommending <a href=\"https://github.com/c0re100/qBittorrent-Enhanced-Edition/releases\">qBittorrent Enhanced Edition</a> for downloading our seeds.<br><a href=\"https://bit.ly/lilithcrypto\"><img src=\"https://p.sda1.dev/6/0180852211c0976ae980b760e0a86221\" alt=\"Lilith Crypto Banner\"></a></p><p>Paypal Donation -&gt; <a href=\"https://donorbox.org/lilithraws\">https://donorbox.org/lilithraws</a><br>Support Us on Patreon -&gt; <a href=\"https://www.patreon.com/lilithraws\">https://www.patreon.com/lilithraws</a></p>", "tag_ids": ["548ee2ce4ab7379536f56358", "55c3036c7030f8c855f992ee", "548ee1204ab7379536f56357", "5d8b3245306f1a0007bd7aca", "548edffb4ab7379536f56352", "624774ab70e8f89b23a18584", "549ef207fe682f7549f1ea90"], "comments": 0, "downloads": 222, "finished": 2164, "leechers": 3, "seeders": 53, "uploader_id": "5d333d66306f1a0007b6c0bf", "team_id": "5d8b24be306f1a0007bd7998", "publish_time": "2022-06-04T16:48:25.324Z", "magnet": "magnet:?xt=urn:btih:294a3df8b8d5a47980cc95ea2ad86e10e22a2e9f", "infoHash": "294a3df8b8d5a47980cc95ea2ad86e10e22a2e9f", "file_id": "629b8cd7f707900007ab6697", "teamsync": true, "content": [["[Lilith-Raws] Kunoichi Tsubaki no Mune no Uchi - 09 [Baha][WEB-DL][1080p][AVC AAC][CHT][MP4].mp4", "448.92 MB"]], "size": "448.92 MB", "btskey": "", "sync": {"dmhy": "http://share.dmhy.org/topics/view/602138_Lilith-Raws_Kunoichi_Tsubaki_no_Mune_no_Uchi_-_09_Baha_WEB-DL_1080p_AVC_AAC_CHT_MP4.html", "acgrip": "https://acg.rip/t/256698", "acgnx": "https://share.acgnx.se/show-294a3df8b8d5a47980cc95ea2ad86e10e22a2e9f.html"}}, {"_id": "629b88f4f707900007ab5f66", "category_tag_id": "549ef207fe682f7549f1ea90", "title": "[ANi] In the Heart of Kunoichi Tsubaki -  \u5973\u5fcd\u8005\u693f\u7684\u5fc3\u4e8b - 09 [1080P][Baha][WEB-DL][AAC AVC][CHT][MP4]", "introduction": "<p>Torrent Info By: ANi API (Auto Generated)</p> <p>Subtitle:</p> <p>&emsp;HardSub</p> <p>Mediainfo:</p> <p>&emsp;Resolution: 1080P</p> <p>&emsp;Video Format: AVC</p> <p>&emsp;Audio Format: AAC</p> <br><p>Note:</p> <p>&emsp;Magnet link is lack of http source info. If you want to download the file asap, please use the torrent file rather than the magnet link.</p> <p>&emsp;Xunlei, torrent media player and offline downloader has been banned by our seeding server.</p> <p>&emsp;This torrent using the HTTP Sources for the first content distributor and the source file stored on IPFS</p> <p>&emsp;This automatic torrent publisher currently in beta test. If have any thought about this publisher. Feel free to contact me.</p> <p>&emsp;Telegram Chat: <a title=\"https://t.me/+SH8EUievFGLKQew_\" href=\"https://t.me/+SH8EUievFGLKQew_\" target=\"_blank\">https://t.me/+SH8EUievFGLKQew_</a></p> <p>2022/6/4 16:31:48 UTC+0000 (Coordinated Universal Time)</p>", "tag_ids": ["548ee2ce4ab7379536f56358", "6039092432f14c00074809b9", "55c3036c7030f8c855f992ee", "548ee1204ab7379536f56357", "548edffb4ab7379536f56352", "624774ab70e8f89b23a18584", "549ef207fe682f7549f1ea90"], "comments": 0, "downloads": 101, "finished": 400, "leechers": 0, "seeders": 18, "uploader_id": "5e43f999306f1a0007cd093f", "team_id": "60313a6e32f14c000745a5e2", "publish_time": "2022-06-04T16:31:48.820Z", "magnet": "magnet:?xt=urn:btih:57ef067fe3b39ef55b953ef7e614c7b88832301b", "infoHash": "57ef067fe3b39ef55b953ef7e614c7b88832301b", "file_id": "629b88f4f707900007ab5f65", "teamsync": true, "content": [["[ANi] \u5973\u5fcd\u8005\u693f\u7684\u5fc3\u4e8b - 09 [1080P][Baha][WEB-DL][AAC AVC][CHT].mp4", "449.23 MB"]], "size": "449.23 MB", "btskey": "", "sync": {"dmhy": "http://share.dmhy.org/topics/view/602132_ANi_In_the_Heart_of_Kunoichi_Tsubaki_-_-_09_1080P_Baha_WEB-DL_AAC_AVC_CHT_MP4.html", "acgrip": "https://acg.rip/t/256692", "nyaa": "https://nyaa.si/view/1537535", "acgnx": "https://share.acgnx.se/show-57ef067fe3b39ef55b953ef7e614c7b88832301b.html"}}, {"_id": "629b88e6f707900007ab5f45", "category_tag_id": "549ef207fe682f7549f1ea90", "title": "[NC-Raws] \u5973\u5fcd\u8005\u693f\u7684\u5fc3\u4e8b / Kunoichi Tsubaki no Mune no Uchi - 09 (Baha 1920x1080 AVC AAC MP4)", "introduction": "<p style=\"text-align:center\"><img src=\"https://rr1---bh.raws.dev/B/2KU/58/f2b292987d21497ad2b47713351gm0y5.JPG\" alt=\"https://rr1---bh.raws.dev/B/2KU/58/f2b292987d21497ad2b47713351gm0y5.JPG\"></p><p style=\"text-align:center\">Watch on Telegram Channel: <a href=\"https://t.me/NC_Raws_Channel\" target=\"view_window\">https://t.me/NC_Raws_Channel</a></p><p style=\"text-align:center\">Auto-generated by NC-Raws.</p><p style=\"text-align:center\">Alternate Title: <b><i>Kunoichi Tsubaki no Mune no Uchi</i></b></p><p style=\"text-align:center\">Subtitle Language: \u4e2d\u6587\uff08\u7e41\u9ad4\uff09</p><p style=\"text-align:center\">Note: Xunlei has been banned by default.</p><p style=\"text-align:center\">Feel free to donate<br>BTC =&gt; 18aMQdjsAni1gbGk1Qvi12oFZTbdwT6E3p<br>ETH =&gt; 0xE766aC6e44d5Ab05534611583B38C7F1c897501a<br>USDT-TRC20 =&gt; TC7P5msV5PyAsnMeCcCEgkCZ7Mpgf4vspW<br><br>PayPal Donation =&gt; <a href=\"https://ko-fi.com/NC_Raws_Channel\" target=\"view_window\">NC-Raws@Ko-fi</a></p>", "tag_ids": ["548ee2ce4ab7379536f56358", "55c3036c7030f8c855f992ee", "548edffb4ab7379536f56352", "600c009432f14c00073a9f49", "624774ab70e8f89b23a18584", "549ef207fe682f7549f1ea90"], "comments": 0, "downloads": 110, "finished": 704, "leechers": 0, "seeders": 20, "uploader_id": "60098e9132f14c000739f8f4", "team_id": "60098fb532f14c000739f911", "publish_time": "2022-06-04T16:31:34.239Z", "magnet": "magnet:?xt=urn:btih:2c21f1ddab86840492513c1fa1e7d5c6cde96fea", "infoHash": "2c21f1ddab86840492513c1fa1e7d5c6cde96fea", "file_id": "629b88e6f707900007ab5f44", "teamsync": true, "content": [["[NC-Raws] \u5973\u5fcd\u8005\u693f\u7684\u5fc3\u4e8b - 09 (Baha 1920x1080 AVC AAC MP4).mp4", "449.08 MB"]], "size": "449.08 MB", "btskey": "", "sync": {"dmhy": "http://share.dmhy.org/topics/view/602130_NC-Raws_Kunoichi_Tsubaki_no_Mune_no_Uchi_-_09_Baha_1920x1080_AVC_AAC_MP4.html", "acgrip": "https://acg.rip/t/256690", "acgnx": "https://share.acgnx.se/show-2c21f1ddab86840492513c1fa1e7d5c6cde96fea.html"}}, {"_id": "629b88d4f707900007ab5f23", "category_tag_id": "549ef207fe682f7549f1ea90", "title": "[NC-Raws] \u5973\u5fcd\u8005\u693f\u7684\u5fc3\u4e8b / Kunoichi Tsubaki no Mune no Uchi - 09 (B-Global 1920x1080 HEVC AAC MKV)", "introduction": "<p style=\"text-align:center\"><img src=\"https://rr1---bg.raws.dev/bfs/intl/management/eb36540fe0a89a0fe4a9299220e5ea14de9f0da6.png@960w_540h_100Q_1c.jpg\" alt=\"https://rr1---bg.raws.dev/bfs/intl/management/eb36540fe0a89a0fe4a9299220e5ea14de9f0da6.png@960w_540h_100Q_1c.jpg\"></p><p style=\"text-align:center\">Watch on Telegram Channel: <a href=\"https://t.me/NC_Raws_Channel\" target=\"view_window\">https://t.me/NC_Raws_Channel</a></p><p style=\"text-align:center\">Auto-generated by NC-Raws.</p><p style=\"text-align:center\">Alternate Title: <b><i>Kunoichi Tsubaki no Mune no Uchi</i></b></p><p style=\"text-align:center\">Subtitle Language: ['English', '\u0e20\u0e32\u0e29\u0e32\u0e44\u0e17\u0e22', 'Ti\u1ebfng Vi\u1ec7t', 'Bahasa Indonesia', '\u4e2d\u6587\uff08\u7e41\u4f53\uff09', '\u4e2d\u6587\uff08\u7b80\u4f53\uff09| \u7e41\u5316\u59ec']</p><p style=\"text-align:center\">Note: Xunlei has been banned by default. Chinese subtitles may not match the source, please solve it by yourself.</p><p style=\"text-align:center\">Feel free to donate<br>BTC =&gt; 18aMQdjsAni1gbGk1Qvi12oFZTbdwT6E3p<br>ETH =&gt; 0xE766aC6e44d5Ab05534611583B38C7F1c897501a<br>USDT-TRC20 =&gt; TC7P5msV5PyAsnMeCcCEgkCZ7Mpgf4vspW<br><br>PayPal Donation =&gt; <a href=\"https://ko-fi.com/NC_Raws_Channel\" target=\"view_window\">NC-Raws@Ko-fi</a></p>", "tag_ids": ["548ee2ce4ab7379536f56358", "55c3024a7030f8c855f992ed", "548ee00b4ab7379536f56353", "600c009432f14c00073a9f49", "624774ab70e8f89b23a18584", "549ef207fe682f7549f1ea90"], "comments": 0, "downloads": 77, "finished": 214, "leechers": 0, "seeders": 9, "uploader_id": "60098e9132f14c000739f8f4", "team_id": "60098fb532f14c000739f911", "publish_time": "2022-06-04T16:31:16.319Z", "magnet": "magnet:?xt=urn:btih:4401dd477a276739792188e8f091d231837cc759", "infoHash": "4401dd477a276739792188e8f091d231837cc759", "file_id": "629b88d4f707900007ab5f22", "teamsync": true, "content": [["[NC-Raws] \u5973\u5fcd\u8005\u693f\u7684\u5fc3\u4e8b - 09 (B-Global 1920x1080 HEVC AAC MKV).mkv", "645.7 MB"]], "size": "645.7 MB", "btskey": "", "sync": {"dmhy": "http://share.dmhy.org/topics/view/602129_NC-Raws_Kunoichi_Tsubaki_no_Mune_no_Uchi_-_09_B-Global_1920x1080_HEVC_AAC_MKV.html", "acgrip": "https://acg.rip/t/256689", "acgnx": "https://share.acgnx.se/show-4401dd477a276739792188e8f091d231837cc759.html"}}, {"_id": "629250ff3d5c310007860a66", "category_tag_id": "549ef207fe682f7549f1ea90", "title": "[Lilith-Raws] \u5973\u5fcd\u8005\u693f\u7684\u5fc3\u4e8b / Kunoichi Tsubaki no Mune no Uchi - 08 [Baha][WEB-DL][1080p][AVC AAC][CHT][MP4]", "introduction": "<p>Telegram Update Notification Channel : <a href=\"https://t.me/lilithraws\">https://t.me/lilithraws</a><br>Open Data Platform : <a href=\"https://open.lilithraws.cf\">https://open.lilithraws.cf</a> (Support Streaming and Direct Download)<br>Twitter : <a href=\"https://twitter.com/lilithraws\">https://twitter.com/lilithraws</a></p><p>We're recommending <a href=\"https://github.com/c0re100/qBittorrent-Enhanced-Edition/releases\">qBittorrent Enhanced Edition</a> for downloading our seeds.<br><a href=\"https://bit.ly/lilithcrypto\"><img src=\"https://p.sda1.dev/6/0180852211c0976ae980b760e0a86221\" alt=\"Lilith Crypto Banner\"></a></p><p>Paypal Donation -&gt; <a href=\"https://donorbox.org/lilithraws\">https://donorbox.org/lilithraws</a><br>Support Us on Patreon -&gt; <a href=\"https://www.patreon.com/lilithraws\">https://www.patreon.com/lilithraws</a></p>", "tag_ids": ["548ee2ce4ab7379536f56358", "55c3036c7030f8c855f992ee", "548ee1204ab7379536f56357", "5d8b3245306f1a0007bd7aca", "548edffb4ab7379536f56352", "624774ab70e8f89b23a18584", "549ef207fe682f7549f1ea90"], "comments": 0, "downloads": 211, "finished": 2204, "leechers": 1, "seeders": 51, "uploader_id": "5d333d66306f1a0007b6c0bf", "team_id": "5d8b24be306f1a0007bd7998", "publish_time": "2022-05-28T16:42:39.774Z", "magnet": "magnet:?xt=urn:btih:759b13f91dde566481cca13699f22a2dc6b59f2d", "infoHash": "759b13f91dde566481cca13699f22a2dc6b59f2d", "file_id": "629250f53d5c310007860a5a", "teamsync": true, "content": [["[Lilith-Raws] Kunoichi Tsubaki no Mune no Uchi - 08 [Baha][WEB-DL][1080p][AVC AAC][CHT][MP4].mp4", "479.46 MB"]], "size": "479.46 MB", "btskey": "", "sync": {"dmhy": "http://share.dmhy.org/topics/view/601516_Lilith-Raws_Kunoichi_Tsubaki_no_Mune_no_Uchi_-_08_Baha_WEB-DL_1080p_AVC_AAC_CHT_MP4.html", "acgrip": "https://acg.rip/t/256309", "acgnx": "https://share.acgnx.se/show-759b13f91dde566481cca13699f22a2dc6b59f2d.html"}}, {"_id": "62924ef63d5c310007860646", "category_tag_id": "549ef207fe682f7549f1ea90", "title": "[NC-Raws] \u5973\u5fcd\u8005\u693f\u7684\u5fc3\u4e8b / Kunoichi Tsubaki no Mune no Uchi - 08 (Baha 1920x1080 AVC AAC MP4)", "introduction": "<p style=\"text-align:center\"><img src=\"https://rr1---bh.raws.dev/B/2KU/31/62259771ef5262fa867a2f45c01gidn5.JPG\" alt=\"https://rr1---bh.raws.dev/B/2KU/31/62259771ef5262fa867a2f45c01gidn5.JPG\"></p><p style=\"text-align:center\">Watch on Telegram Channel: <a href=\"https://t.me/NC_Raws_Channel\" target=\"view_window\">https://t.me/NC_Raws_Channel</a></p><p style=\"text-align:center\">Auto-generated by NC-Raws.</p><p style=\"text-align:center\">Alternate Title: <b><i>Kunoichi Tsubaki no Mune no Uchi</i></b></p><p style=\"text-align:center\">Subtitle Language: \u4e2d\u6587\uff08\u7e41\u9ad4\uff09</p><p style=\"text-align:center\">Note: Xunlei has been banned by default.</p><p style=\"text-align:center\">Feel free to donate<br>BTC =&gt; 18aMQdjsAni1gbGk1Qvi12oFZTbdwT6E3p<br>ETH =&gt; 0xE766aC6e44d5Ab05534611583B38C7F1c897501a<br>USDT-TRC20 =&gt; TC7P5msV5PyAsnMeCcCEgkCZ7Mpgf4vspW<br><br>PayPal Donation =&gt; <a href=\"https://ko-fi.com/NC_Raws_Channel\" target=\"view_window\">NC-Raws@Ko-fi</a></p>", "tag_ids": ["548ee2ce4ab7379536f56358", "55c3036c7030f8c855f992ee", "548edffb4ab7379536f56352", "600c009432f14c00073a9f49", "624774ab70e8f89b23a18584", "549ef207fe682f7549f1ea90"], "comments": 0, "downloads": 109, "finished": 747, "leechers": 0, "seeders": 18, "uploader_id": "60098e9132f14c000739f8f4", "team_id": "60098fb532f14c000739f911", "publish_time": "2022-05-28T16:33:58.791Z", "magnet": "magnet:?xt=urn:btih:b2d101430abfcefcf534b9021465a74909e72c17", "infoHash": "b2d101430abfcefcf534b9021465a74909e72c17", "file_id": "62924ef63d5c310007860645", "teamsync": true, "content": [["[NC-Raws] \u5973\u5fcd\u8005\u693f\u7684\u5fc3\u4e8b - 08 (Baha 1920x1080 AVC AAC MP4).mp4", "479.63 MB"]], "size": "479.63 MB", "btskey": "", "sync": {"dmhy": "http://share.dmhy.org/topics/view/601514_NC-Raws_Kunoichi_Tsubaki_no_Mune_no_Uchi_-_08_Baha_1920x1080_AVC_AAC_MP4.html", "acgrip": "https://acg.rip/t/256307", "acgnx": "https://share.acgnx.se/show-b2d101430abfcefcf534b9021465a74909e72c17.html"}}, {"_id": "62924e543d5c3100078604ef", "category_tag_id": "549ef207fe682f7549f1ea90", "title": "[ANi] In the Heart of Kunoichi Tsubaki -  \u5973\u5fcd\u8005\u693f\u7684\u5fc3\u4e8b - 08 [1080P][Baha][WEB-DL][AAC AVC][CHT][MP4]", "introduction": "<p>Torrent Info By: ANi API (Auto Generated)</p> <p>Subtitle:</p> <p>&emsp;HardSub</p> <p>Mediainfo:</p> <p>&emsp;Resolution: 1080P</p> <p>&emsp;Video Format: AVC</p> <p>&emsp;Audio Format: AAC</p> <br><p>Note:</p> <p>&emsp;Magnet link is lack of http source info. If you want to download the file asap, please use the torrent file rather than the magnet link.</p> <p>&emsp;Xunlei, torrent media player and offline downloader has been banned by our seeding server.</p> <p>&emsp;This torrent using the HTTP Sources for the first content distributor and the source file stored on IPFS</p> <p>&emsp;This automatic torrent publisher currently in beta test. If have any thought about this publisher. Feel free to contact me.</p> <p>&emsp;Telegram Chat: <a title=\"https://t.me/+SH8EUievFGLKQew_\" href=\"https://t.me/+SH8EUievFGLKQew_\" target=\"_blank\">https://t.me/+SH8EUievFGLKQew_</a></p> <p>2022/5/28 16:31:15 UTC+0000 (Coordinated Universal Time)</p>", "tag_ids": ["548ee2ce4ab7379536f56358", "6039092432f14c00074809b9", "55c3036c7030f8c855f992ee", "548ee1204ab7379536f56357", "548edffb4ab7379536f56352", "624774ab70e8f89b23a18584", "549ef207fe682f7549f1ea90"], "comments": 0, "downloads": 97, "finished": 364, "leechers": 0, "seeders": 15, "uploader_id": "5e43f999306f1a0007cd093f", "team_id": "60313a6e32f14c000745a5e2", "publish_time": "2022-05-28T16:31:16.105Z", "magnet": "magnet:?xt=urn:btih:09683180b8c8123c35a513a4d66eff2d6b673cef", "infoHash": "09683180b8c8123c35a513a4d66eff2d6b673cef", "file_id": "62924e543d5c3100078604ee", "teamsync": true, "content": [["[ANi] \u5973\u5fcd\u8005\u693f\u7684\u5fc3\u4e8b - 08 [1080P][Baha][WEB-DL][AAC AVC][CHT].mp4", "479.78 MB"]], "size": "479.78 MB", "btskey": "", "sync": {"dmhy": "http://share.dmhy.org/topics/view/601508_ANi_In_the_Heart_of_Kunoichi_Tsubaki_-_-_08_1080P_Baha_WEB-DL_AAC_AVC_CHT_MP4.html", "acgrip": "https://acg.rip/t/256303", "nyaa": "https://nyaa.si/view/1534424", "acgnx": "https://share.acgnx.se/show-09683180b8c8123c35a513a4d66eff2d6b673cef.html"}}, {"_id": "62924e403d5c3100078604b5", "category_tag_id": "549ef207fe682f7549f1ea90", "title": "[NC-Raws] \u5973\u5fcd\u8005\u693f\u7684\u5fc3\u4e8b / Kunoichi Tsubaki no Mune no Uchi - 08 (B-Global 1920x1080 HEVC AAC MKV)", "introduction": "<p style=\"text-align:center\"><img src=\"https://rr1---bg.raws.dev/bfs/intl/management/bdb4750a579deb35dbefed805ce69f929b70103e.png@960w_540h_100Q_1c.jpg\" alt=\"https://rr1---bg.raws.dev/bfs/intl/management/bdb4750a579deb35dbefed805ce69f929b70103e.png@960w_540h_100Q_1c.jpg\"></p><p style=\"text-align:center\">Watch on Telegram Channel: <a href=\"https://t.me/NC_Raws_Channel\" target=\"view_window\">https://t.me/NC_Raws_Channel</a></p><p style=\"text-align:center\">Auto-generated by NC-Raws.</p><p style=\"text-align:center\">Alternate Title: <b><i>Kunoichi Tsubaki no Mune no Uchi</i></b></p><p style=\"text-align:center\">Subtitle Language: ['English', '\u0e20\u0e32\u0e29\u0e32\u0e44\u0e17\u0e22', 'Ti\u1ebfng Vi\u1ec7t', 'Bahasa Indonesia', '\u4e2d\u6587\uff08\u7e41\u4f53\uff09', '\u4e2d\u6587\uff08\u7b80\u4f53\uff09| \u7e41\u5316\u59ec']</p><p style=\"text-align:center\">Note: Xunlei has been banned by default. Chinese subtitles may not match the source, please solve it by yourself.</p><p style=\"text-align:center\">Feel free to donate<br>BTC =&gt; 18aMQdjsAni1gbGk1Qvi12oFZTbdwT6E3p<br>ETH =&gt; 0xE766aC6e44d5Ab05534611583B38C7F1c897501a<br>USDT-TRC20 =&gt; TC7P5msV5PyAsnMeCcCEgkCZ7Mpgf4vspW<br><br>PayPal Donation =&gt; <a href=\"https://ko-fi.com/NC_Raws_Channel\" target=\"view_window\">NC-Raws@Ko-fi</a></p>", "tag_ids": ["548ee2ce4ab7379536f56358", "55c3024a7030f8c855f992ed", "548ee00b4ab7379536f56353", "600c009432f14c00073a9f49", "624774ab70e8f89b23a18584", "549ef207fe682f7549f1ea90"], "comments": 0, "downloads": 90, "finished": 176, "leechers": 0, "seeders": 6, "uploader_id": "60098e9132f14c000739f8f4", "team_id": "60098fb532f14c000739f911", "publish_time": "2022-05-28T16:30:56.625Z", "magnet": "magnet:?xt=urn:btih:ac172b40564d24d9f3c5cec5b7f62f7e7149f650", "infoHash": "ac172b40564d24d9f3c5cec5b7f62f7e7149f650", "file_id": "62924e403d5c3100078604b4", "teamsync": true, "content": [["[NC-Raws] \u5973\u5fcd\u8005\u693f\u7684\u5fc3\u4e8b - 08 (B-Global 1920x1080 HEVC AAC MKV).mkv", "643.89 MB"]], "size": "643.89 MB", "btskey": "", "sync": {"dmhy": "http://share.dmhy.org/topics/view/601506_NC-Raws_Kunoichi_Tsubaki_no_Mune_no_Uchi_-_08_B-Global_1920x1080_HEVC_AAC_MKV.html", "acgrip": "https://acg.rip/t/256301", "acgnx": "https://share.acgnx.se/show-ac172b40564d24d9f3c5cec5b7f62f7e7149f650.html"}}, {"_id": "628914293d5c31000774e55e", "category_tag_id": "549ef207fe682f7549f1ea90", "title": "[ANi] In the Heart of Kunoichi Tsubaki -  \u5973\u5fcd\u8005\u693f\u7684\u5fc3\u4e8b - 07 [1080P][Baha][WEB-DL][AAC AVC][CHT][MP4]", "introduction": "<p>Torrent Info By: ANi API (Auto Generated)</p> <p>Subtitle:</p> <p>&emsp;HardSub</p> <p>Mediainfo:</p> <p>&emsp;Resolution: 1080P</p> <p>&emsp;Video Format: AVC</p> <p>&emsp;Audio Format: AAC</p> <br><p>Note:</p> <p>&emsp;Magnet link is lack of http source info. If you want to download the file asap, please use the torrent file rather than the magnet link.</p> <p>&emsp;Xunlei, torrent media player and offline downloader has been banned by our seeding server.</p> <p>&emsp;This torrent using the HTTP Sources for the first content distributor and the source file stored on IPFS</p> <p>&emsp;This automatic torrent publisher currently in beta test. If have any thought about this publisher. Feel free to contact me.</p> <p>&emsp;Telegram Chat: <a title=\"https://t.me/+SH8EUievFGLKQew_\" href=\"https://t.me/+SH8EUievFGLKQew_\" target=\"_blank\">https://t.me/+SH8EUievFGLKQew_</a></p> <p>2022/5/21 16:32:40 UTC+0000 (Coordinated Universal Time)</p>", "tag_ids": ["548ee2ce4ab7379536f56358", "6039092432f14c00074809b9", "55c3036c7030f8c855f992ee", "548ee1204ab7379536f56357", "548edffb4ab7379536f56352", "624774ab70e8f89b23a18584", "549ef207fe682f7549f1ea90"], "comments": 0, "downloads": 104, "finished": 435, "leechers": 0, "seeders": 13, "uploader_id": "5e43f999306f1a0007cd093f", "team_id": "60313a6e32f14c000745a5e2", "publish_time": "2022-05-21T16:32:41.958Z", "magnet": "magnet:?xt=urn:btih:08c40031f5987b4f3e00d544e8bbd678089cf045", "infoHash": "08c40031f5987b4f3e00d544e8bbd678089cf045", "file_id": "628914293d5c31000774e55d", "teamsync": true, "content": [["[ANi] \u5973\u5fcd\u8005\u693f\u7684\u5fc3\u4e8b - 07 [1080P][Baha][WEB-DL][AAC AVC][CHT].mp4", "457.46 MB"]], "size": "457.46 MB", "btskey": "", "sync": {"dmhy": "http://share.dmhy.org/topics/view/600885_ANi_In_the_Heart_of_Kunoichi_Tsubaki_-_-_07_1080P_Baha_WEB-DL_AAC_AVC_CHT_MP4.html", "acgrip": "https://acg.rip/t/255879", "nyaa": "https://nyaa.si/view/1531427", "acgnx": "https://share.acgnx.se/show-08c40031f5987b4f3e00d544e8bbd678089cf045.html"}}, {"_id": "628913f33d5c31000774e516", "category_tag_id": "549ef207fe682f7549f1ea90", "title": "[Lilith-Raws x WitEx.io] \u5973\u5fcd\u8005\u693f\u7684\u5fc3\u4e8b / Kunoichi Tsubaki no Mune no Uchi - 07 [Baha][WEB-DL][1080p][AVC AAC][CHT][MP4]", "introduction": "<p>Telegram Update Notification Channel : <a href=\"https://t.me/lilithraws\">https://t.me/lilithraws</a><br>Open Data Platform : <a href=\"https://open.lilithraws.cf\">https://open.lilithraws.cf</a> (Support Streaming and Direct Download)<br>Twitter : <a href=\"https://twitter.com/lilithraws\">https://twitter.com/lilithraws</a></p><p>We're recommending <a href=\"https://github.com/c0re100/qBittorrent-Enhanced-Edition/releases\">qBittorrent Enhanced Edition</a> for downloading our seeds.<br><a href=\"https://bit.ly/lilithcrypto\"><img src=\"https://p.sda1.dev/5/be21c667794f31f409f5367a9d12e6bc\" alt=\"Lilith Crypto Banner\"></a><br>You can buy cryptos on WitEx -&gt; <a href=\"https://bit.ly/lilithwitex\">https://witex.io</a></p><p>Paypal Donation -&gt; <a href=\"https://donorbox.org/lilithraws\">https://donorbox.org/lilithraws</a><br>Support Us on Patreon -&gt; <a href=\"https://www.patreon.com/lilithraws\">https://www.patreon.com/lilithraws</a></p>", "tag_ids": ["548ee2ce4ab7379536f56358", "55c3036c7030f8c855f992ee", "548ee1204ab7379536f56357", "5d8b3245306f1a0007bd7aca", "548edffb4ab7379536f56352", "624774ab70e8f89b23a18584", "549ef207fe682f7549f1ea90"], "comments": 0, "downloads": 205, "finished": 2241, "leechers": 1, "seeders": 32, "uploader_id": "5d333d66306f1a0007b6c0bf", "team_id": "5d8b24be306f1a0007bd7998", "publish_time": "2022-05-21T16:31:47.097Z", "magnet": "magnet:?xt=urn:btih:a753d4b9a3e11fce0fbce63124e969b66b19e4d6", "infoHash": "a753d4b9a3e11fce0fbce63124e969b66b19e4d6", "file_id": "628913f13d5c31000774e513", "teamsync": true, "content": [["[Lilith-Raws] Kunoichi Tsubaki no Mune no Uchi - 07 [Baha][WEB-DL][1080p][AVC AAC][CHT][MP4].mp4", "457.14 MB"]], "size": "457.14 MB", "btskey": "", "sync": {"dmhy": "http://share.dmhy.org/topics/view/600883_Lilith-Raws_x_WitEx_io_Kunoichi_Tsubaki_no_Mune_no_Uchi_-_07_Baha_WEB-DL_1080p_AVC_AAC_CHT_MP4.html", "acgrip": "https://acg.rip/t/255877", "acgnx": "https://share.acgnx.se/show-a753d4b9a3e11fce0fbce63124e969b66b19e4d6.html"}}, {"_id": "627fe9323d5c31000763f9fc", "category_tag_id": "549ef207fe682f7549f1ea90", "title": "[Lilith-Raws x WitEx.io] \u5973\u5fcd\u8005\u693f\u7684\u5fc3\u4e8b / Kunoichi Tsubaki no Mune no Uchi - 06 [Baha][WEB-DL][1080p][AVC AAC][CHT][MP4]", "introduction": "<p>Telegram Update Notification Channel : <a href=\"https://t.me/lilithraws\">https://t.me/lilithraws</a><br>Open Data Platform : <a href=\"https://open.lilithraws.cf\">https://open.lilithraws.cf</a> (Support Streaming and Direct Download)<br>Twitter : <a href=\"https://twitter.com/lilithraws\">https://twitter.com/lilithraws</a></p><p>We're recommending <a href=\"https://github.com/c0re100/qBittorrent-Enhanced-Edition/releases\">qBittorrent Enhanced Edition</a> for downloading our seeds.<br><a href=\"https://bit.ly/lilithcrypto\"><img src=\"https://p.sda1.dev/5/be21c667794f31f409f5367a9d12e6bc\" alt=\"Lilith Crypto Banner\"></a><br>You can buy cryptos on WitEx -&gt; <a href=\"https://bit.ly/lilithwitex\">https://witex.io</a></p><p>Paypal Donation -&gt; <a href=\"https://donorbox.org/lilithraws\">https://donorbox.org/lilithraws</a><br>Support Us on Patreon -&gt; <a href=\"https://www.patreon.com/lilithraws\">https://www.patreon.com/lilithraws</a></p>", "tag_ids": ["548ee2ce4ab7379536f56358", "55c3036c7030f8c855f992ee", "548ee1204ab7379536f56357", "5d8b3245306f1a0007bd7aca", "548edffb4ab7379536f56352", "624774ab70e8f89b23a18584", "549ef207fe682f7549f1ea90"], "comments": 0, "downloads": 234, "finished": 2540, "leechers": 2, "seeders": 38, "uploader_id": "5d333d66306f1a0007b6c0bf", "team_id": "5d8b24be306f1a0007bd7998", "publish_time": "2022-05-14T17:38:58.709Z", "magnet": "magnet:?xt=urn:btih:58c9b83d4e7872f02f0f12e6fb2ad51bc6bed6e0", "infoHash": "58c9b83d4e7872f02f0f12e6fb2ad51bc6bed6e0", "file_id": "627fe92e3d5c31000763f9f4", "teamsync": true, "content": [["[Lilith-Raws] Kunoichi Tsubaki no Mune no Uchi - 06 [Baha][WEB-DL][1080p][AVC AAC][CHT][MP4].mp4", "513.2 MB"]], "size": "513.2 MB", "btskey": "", "sync": {"dmhy": "http://share.dmhy.org/topics/view/600315_Lilith-Raws_x_WitEx_io_Kunoichi_Tsubaki_no_Mune_no_Uchi_-_06_Baha_WEB-DL_1080p_AVC_AAC_CHT_MP4.html", "acgrip": "https://acg.rip/t/255535", "acgnx": "https://share.acgnx.se/show-58c9b83d4e7872f02f0f12e6fb2ad51bc6bed6e0.html"}}, {"_id": "627fd9553d5c31000763dda5", "category_tag_id": "549ef207fe682f7549f1ea90", "title": "[ANi] In the Heart of Kunoichi Tsubaki -  \u5973\u5fcd\u8005\u693f\u7684\u5fc3\u4e8b - 06 [1080P][Baha][WEB-DL][AAC AVC][CHT][MP4]", "introduction": "<p>Torrent Info By: ANi API (Auto Generated)</p> <p>Subtitle:</p> <p>&emsp;HardSub</p> <p>Mediainfo:</p> <p>&emsp;Resolution: 1080P</p> <p>&emsp;Video Format: AVC</p> <p>&emsp;Audio Format: AAC</p> <br><p>Note:</p> <p>&emsp;Magnet link is lack of http source info. If you want to download the file asap, please use the torrent file rather than the magnet link.</p> <p>&emsp;Xunlei, torrent media player and offline downloader has been banned by our seeding server.</p> <p>&emsp;This torrent using the HTTP Sources for the first content distributor and the source file stored on IPFS</p> <p>&emsp;This automatic torrent publisher currently in beta test. If have any thought about this publisher. Feel free to contact me.</p> <p>&emsp;Telegram Chat: <a title=\"https://t.me/+SH8EUievFGLKQew_\" href=\"https://t.me/+SH8EUievFGLKQew_\" target=\"_blank\">https://t.me/+SH8EUievFGLKQew_</a></p> <p>2022/5/14 16:31:15 UTC+0000 (Coordinated Universal Time)</p>", "tag_ids": ["548ee2ce4ab7379536f56358", "6039092432f14c00074809b9", "55c3036c7030f8c855f992ee", "548ee1204ab7379536f56357", "548edffb4ab7379536f56352", "624774ab70e8f89b23a18584", "549ef207fe682f7549f1ea90"], "comments": 0, "downloads": 98, "finished": 461, "leechers": 0, "seeders": 17, "uploader_id": "5e43f999306f1a0007cd093f", "team_id": "60313a6e32f14c000745a5e2", "publish_time": "2022-05-14T16:31:17.841Z", "magnet": "magnet:?xt=urn:btih:bdc0bcb440edad3262b4b52a6c96fe35f6be8559", "infoHash": "bdc0bcb440edad3262b4b52a6c96fe35f6be8559", "file_id": "627fd9553d5c31000763dda4", "teamsync": true, "content": [["[ANi] \u5973\u5fcd\u8005\u693f\u7684\u5fc3\u4e8b - 06 [1080P][Baha][WEB-DL][AAC AVC][CHT].mp4", "513.52 MB"]], "size": "513.52 MB", "btskey": "", "sync": {"dmhy": "http://share.dmhy.org/topics/view/600298_ANi_In_the_Heart_of_Kunoichi_Tsubaki_-_-_06_1080P_Baha_WEB-DL_AAC_AVC_CHT_MP4.html", "acgrip": "https://acg.rip/t/255518", "nyaa": "https://nyaa.si/view/1528383", "acgnx": "https://share.acgnx.se/show-bdc0bcb440edad3262b4b52a6c96fe35f6be8559.html"}}, {"_id": "6276a2133d5c31000753ee1d", "category_tag_id": "549ef207fe682f7549f1ea90", "title": "[ANi] In the Heart of Kunoichi Tsubaki -  \u5973\u5fcd\u8005\u693f\u7684\u5fc3\u4e8b - 05 [1080P][Baha][WEB-DL][AAC AVC][CHT][MP4]", "introduction": "<p>Torrent Info By: ANi API (Auto Generated)</p> <p>Subtitle:</p> <p>&emsp;HardSub</p> <p>Mediainfo:</p> <p>&emsp;Resolution: 1080P</p> <p>&emsp;Video Format: AVC</p> <p>&emsp;Audio Format: AAC</p> <br><p>Note:</p> <p>&emsp;Magnet link not contain any http source info. If you want to download the file asap, please use the torrent file rather than the magnet link.</p> <p>&emsp;Xunlei, torrent media player and offline downloader has been banned by default.</p> <p>&emsp;This torrent using the HTTP Sources for the first content distributor and the source file stored on IPFS</p> <p>&emsp;This automatic torrent publisher currently in beta test. If have any thought about this publisher. Feel free to contact me.</p> <p>&emsp;Telegram Chat: <a title=\"https://t.me/+SH8EUievFGLKQew_\" href=\"https://t.me/+SH8EUievFGLKQew_\" target=\"_blank\">https://t.me/+SH8EUievFGLKQew_</a></p> <p>2022/5/7 16:45:05 UTC+0000 (Coordinated Universal Time)</p>", "tag_ids": ["548ee2ce4ab7379536f56358", "6039092432f14c00074809b9", "55c3036c7030f8c855f992ee", "548ee1204ab7379536f56357", "548edffb4ab7379536f56352", "624774ab70e8f89b23a18584", "549ef207fe682f7549f1ea90"], "comments": 0, "downloads": 128, "finished": 613, "leechers": 0, "seeders": 14, "uploader_id": "5e43f999306f1a0007cd093f", "team_id": "60313a6e32f14c000745a5e2", "publish_time": "2022-05-07T16:45:07.346Z", "magnet": "magnet:?xt=urn:btih:ffae9b4417e187a280e3e53252475bf87bf54e6d", "infoHash": "ffae9b4417e187a280e3e53252475bf87bf54e6d", "file_id": "6276a2133d5c31000753ee1c", "teamsync": true, "content": [["[ANi] \u5973\u5fcd\u8005\u693f\u7684\u5fc3\u4e8b - 05 [1080P][Baha][WEB-DL][AAC AVC][CHT].mp4", "514.86 MB"]], "size": "514.86 MB", "btskey": "", "sync": {"dmhy": "http://share.dmhy.org/topics/view/599672_ANi_In_the_Heart_of_Kunoichi_Tsubaki_-_-_05_1080P_Baha_WEB-DL_AAC_AVC_CHT_MP4.html", "acgrip": "https://acg.rip/t/255150", "nyaa": "https://nyaa.si/view/1525371", "acgnx": "https://share.acgnx.se/show-ffae9b4417e187a280e3e53252475bf87bf54e6d.html"}}, {"_id": "62769f7f3d5c31000753e949", "category_tag_id": "549ef207fe682f7549f1ea90", "title": "[Lilith-Raws x WitEx.io] \u5973\u5fcd\u8005\u693f\u7684\u5fc3\u4e8b / Kunoichi Tsubaki no Mune no Uchi - 05 [Baha][WEB-DL][1080p][AVC AAC][CHT][MP4]", "introduction": "<p>Telegram Update Notification Channel : <a href=\"https://t.me/lilithraws\">https://t.me/lilithraws</a><br>Open Data Platform : <a href=\"https://open.lilithraws.cf\">https://open.lilithraws.cf</a> (Support Streaming and Direct Download)<br>Twitter : <a href=\"https://twitter.com/lilithraws\">https://twitter.com/lilithraws</a></p><p>We're recommending <a href=\"https://github.com/c0re100/qBittorrent-Enhanced-Edition/releases\">qBittorrent Enhanced Edition</a> for downloading our seeds.<br><a href=\"https://bit.ly/lilithcrypto\"><img src=\"https://p.sda1.dev/5/be21c667794f31f409f5367a9d12e6bc\" alt=\"Lilith Crypto Banner\"></a><br>You can buy cryptos on WitEx -&gt; <a href=\"https://bit.ly/lilithwitex\">https://witex.io</a></p><p>Paypal Donation -&gt; <a href=\"https://donorbox.org/lilithraws\">https://donorbox.org/lilithraws</a><br>Support Us on Patreon -&gt; <a href=\"https://www.patreon.com/lilithraws\">https://www.patreon.com/lilithraws</a></p>", "tag_ids": ["548ee2ce4ab7379536f56358", "55c3036c7030f8c855f992ee", "548ee1204ab7379536f56357", "5d8b3245306f1a0007bd7aca", "548edffb4ab7379536f56352", "624774ab70e8f89b23a18584", "549ef207fe682f7549f1ea90"], "comments": 0, "downloads": 256, "finished": 2484, "leechers": 0, "seeders": 38, "uploader_id": "5d333d66306f1a0007b6c0bf", "team_id": "5d8b24be306f1a0007bd7998", "publish_time": "2022-05-07T16:34:07.609Z", "magnet": "magnet:?xt=urn:btih:be06bade3b0432d0476f672f88ebba9dd144e6ff", "infoHash": "be06bade3b0432d0476f672f88ebba9dd144e6ff", "file_id": "62769f7c3d5c31000753e940", "teamsync": true, "content": [["[Lilith-Raws] Kunoichi Tsubaki no Mune no Uchi - 05 [Baha][WEB-DL][1080p][AVC AAC][CHT][MP4].mp4", "514.54 MB"]], "size": "514.54 MB", "btskey": "", "sync": {"dmhy": "http://share.dmhy.org/topics/view/599670_Lilith-Raws_x_WitEx_io_Kunoichi_Tsubaki_no_Mune_no_Uchi_-_05_Baha_WEB-DL_1080p_AVC_AAC_CHT_MP4.html", "acgrip": "https://acg.rip/t/255148", "acgnx": "https://share.acgnx.se/show-be06bade3b0432d0476f672f88ebba9dd144e6ff.html"}}, {"_id": "626d66503d5c31000743b7cb", "category_tag_id": "549ef207fe682f7549f1ea90", "title": "[Lilith-Raws x WitEx.io] \u5973\u5fcd\u8005\u693f\u7684\u5fc3\u4e8b / Kunoichi Tsubaki no Mune no Uchi - 04 [Baha][WEB-DL][1080p][AVC AAC][CHT][MP4]", "introduction": "<p>Telegram Update Notification Channel : <a href=\"https://t.me/lilithraws\">https://t.me/lilithraws</a><br>Open Data Platform : <a href=\"https://open.lilithraws.cf\">https://open.lilithraws.cf</a> (Support Streaming and Direct Download)<br>Twitter : <a href=\"https://twitter.com/lilithraws\">https://twitter.com/lilithraws</a></p><p>We're recommending <a href=\"https://github.com/c0re100/qBittorrent-Enhanced-Edition/releases\">qBittorrent Enhanced Edition</a> for downloading our seeds.<br><a href=\"https://bit.ly/lilithcrypto\"><img src=\"https://p.sda1.dev/5/be21c667794f31f409f5367a9d12e6bc\" alt=\"Lilith Crypto Banner\"></a><br>You can buy cryptos on WitEx -&gt; <a href=\"https://bit.ly/lilithwitex\">https://witex.io</a></p><p>Paypal Donation -&gt; <a href=\"https://donorbox.org/lilithraws\">https://donorbox.org/lilithraws</a><br>Support Us on Patreon -&gt; <a href=\"https://www.patreon.com/lilithraws\">https://www.patreon.com/lilithraws</a></p>", "tag_ids": ["548ee2ce4ab7379536f56358", "55c3036c7030f8c855f992ee", "548ee1204ab7379536f56357", "5d8b3245306f1a0007bd7aca", "548edffb4ab7379536f56352", "624774ab70e8f89b23a18584", "549ef207fe682f7549f1ea90"], "comments": 0, "downloads": 273, "finished": 2664, "leechers": 0, "seeders": 28, "uploader_id": "5d333d66306f1a0007b6c0bf", "team_id": "5d8b24be306f1a0007bd7998", "publish_time": "2022-04-30T16:39:44.191Z", "magnet": "magnet:?xt=urn:btih:0687da8c752717f3897890b9bc8852f552524da6", "infoHash": "0687da8c752717f3897890b9bc8852f552524da6", "file_id": "626d664e3d5c31000743b7c9", "teamsync": true, "content": [["[Lilith-Raws] Kunoichi Tsubaki no Mune no Uchi - 04 [Baha][WEB-DL][1080p][AVC AAC][CHT][MP4].mp4", "528.02 MB"]], "size": "528.02 MB", "btskey": "", "sync": {"dmhy": "http://share.dmhy.org/topics/view/599084_Lilith-Raws_x_WitEx_io_Kunoichi_Tsubaki_no_Mune_no_Uchi_-_04_Baha_WEB-DL_1080p_AVC_AAC_CHT_MP4.html", "acgrip": "https://acg.rip/t/254751", "acgnx": "https://share.acgnx.se/show-0687da8c752717f3897890b9bc8852f552524da6.html"}}, {"_id": "626d65a73d5c31000743b6e0", "category_tag_id": "549ef207fe682f7549f1ea90", "title": "[ANi] In the Heart of Kunoichi Tsubaki -  \u5973\u5fcd\u8005\u693f\u7684\u5fc3\u4e8b - 04 [1080P][Baha][WEB-DL][AAC AVC][CHT][MP4]", "introduction": "<p>Torrent Info By: ANi API (Auto Generated)</p> <p>Subtitle:</p> <p>&emsp;HardSub</p> <p>Mediainfo:</p> <p>&emsp;Resolution: 1080P</p> <p>&emsp;Video Format: AVC</p> <p>&emsp;Audio Format: AAC</p> <br><p>Note:</p> <p>&emsp;Magnet link not contain any http source info. If you want to download the file asap, please use the torrent file rather than the magnet link.</p> <p>&emsp;Xunlei, torrent media player and offline downloader has been banned by default.</p> <p>&emsp;This torrent using the HTTP Sources for the first content distributor and the source file stored on IPFS</p> <p>&emsp;This automatic torrent publisher currently in beta test. If have any thought about this publisher. Feel free to contact me.</p> <p>&emsp;Telegram Chat: <a title=\"https://t.me/+SH8EUievFGLKQew_\" href=\"https://t.me/+SH8EUievFGLKQew_\" target=\"_blank\">https://t.me/+SH8EUievFGLKQew_</a></p> <p>2022/4/30 16:36:53 UTC+0000 (Coordinated Universal Time)</p>", "tag_ids": ["548ee2ce4ab7379536f56358", "6039092432f14c00074809b9", "55c3036c7030f8c855f992ee", "548ee1204ab7379536f56357", "548edffb4ab7379536f56352", "624774ab70e8f89b23a18584", "549ef207fe682f7549f1ea90"], "comments": 0, "downloads": 104, "finished": 522, "leechers": 0, "seeders": 13, "uploader_id": "5e43f999306f1a0007cd093f", "team_id": "60313a6e32f14c000745a5e2", "publish_time": "2022-04-30T16:36:55.172Z", "magnet": "magnet:?xt=urn:btih:dd1c9ffe87925a8d5100bc3808a1c813c32e7a42", "infoHash": "dd1c9ffe87925a8d5100bc3808a1c813c32e7a42", "file_id": "626d65a73d5c31000743b6df", "teamsync": true, "content": [["[ANi] \u5973\u5fcd\u8005\u693f\u7684\u5fc3\u4e8b - 04 [1080P][Baha][WEB-DL][AAC AVC][CHT].mp4", "528.34 MB"]], "size": "528.34 MB", "btskey": "", "sync": {"dmhy": "http://share.dmhy.org/topics/view/599082_ANi_In_the_Heart_of_Kunoichi_Tsubaki_-_-_04_1080P_Baha_WEB-DL_AAC_AVC_CHT_MP4.html", "acgrip": "https://acg.rip/t/254749", "nyaa": "https://nyaa.si/view/1522344", "acgnx": "https://share.acgnx.se/show-dd1c9ffe87925a8d5100bc3808a1c813c32e7a42.html"}}, {"_id": "626435143d5c310007340266", "category_tag_id": "549ef207fe682f7549f1ea90", "title": "[Lilith-Raws x WitEx.io] \u5973\u5fcd\u8005\u693f\u7684\u5fc3\u4e8b / Kunoichi Tsubaki no Mune no Uchi - 03 [Baha][WEB-DL][1080p][AVC AAC][CHT][MP4]", "introduction": "<p>Telegram Update Notification Channel : <a href=\"https://t.me/lilithraws\">https://t.me/lilithraws</a><br>Open Data Platform : <a href=\"https://open.lilithraws.cf\">https://open.lilithraws.cf</a> (Support Streaming and Direct Download)<br>Twitter : <a href=\"https://twitter.com/lilithraws\">https://twitter.com/lilithraws</a></p><p>We're recommending <a href=\"https://github.com/c0re100/qBittorrent-Enhanced-Edition/releases\">qBittorrent Enhanced Edition</a> for downloading our seeds.<br><a href=\"https://bit.ly/lilithcrypto\"><img src=\"https://p.sda1.dev/5/be21c667794f31f409f5367a9d12e6bc\" alt=\"Lilith Crypto Banner\"></a><br>You can buy cryptos on WitEx -&gt; <a href=\"https://bit.ly/lilithwitex\">https://witex.io</a></p><p>Paypal Donation -&gt; <a href=\"https://donorbox.org/lilithraws\">https://donorbox.org/lilithraws</a><br>Support Us on Patreon -&gt; <a href=\"https://www.patreon.com/lilithraws\">https://www.patreon.com/lilithraws</a></p>", "tag_ids": ["548ee2ce4ab7379536f56358", "55c3036c7030f8c855f992ee", "548ee1204ab7379536f56357", "5d8b3245306f1a0007bd7aca", "548edffb4ab7379536f56352", "624774ab70e8f89b23a18584", "549ef207fe682f7549f1ea90"], "comments": 0, "downloads": 284, "finished": 2815, "leechers": 1, "seeders": 37, "uploader_id": "5d333d66306f1a0007b6c0bf", "team_id": "5d8b24be306f1a0007bd7998", "publish_time": "2022-04-23T17:19:16.689Z", "magnet": "magnet:?xt=urn:btih:74137997704ee369b1e6ca3a23279308d04a6db2", "infoHash": "74137997704ee369b1e6ca3a23279308d04a6db2", "file_id": "626435123d5c310007340263", "teamsync": true, "content": [["[Lilith-Raws] Kunoichi Tsubaki no Mune no Uchi - 03 [Baha][WEB-DL][1080p][AVC AAC][CHT][MP4].mp4", "498.04 MB"]], "size": "498.04 MB", "btskey": "", "sync": {"dmhy": "http://share.dmhy.org/topics/view/598425_Lilith-Raws_x_WitEx_io_Kunoichi_Tsubaki_no_Mune_no_Uchi_-_03_Baha_WEB-DL_1080p_AVC_AAC_CHT_MP4.html", "acgrip": "https://acg.rip/t/254331", "acgnx": "https://share.acgnx.se/show-74137997704ee369b1e6ca3a23279308d04a6db2.html"}}, {"_id": "62642a0a3d5c31000733ef74", "category_tag_id": "549ef207fe682f7549f1ea90", "title": "[ANi] In the Heart of Kunoichi Tsubaki -  \u5973\u5fcd\u8005\u693f\u7684\u5fc3\u4e8b - 03 [1080P][Baha][WEB-DL][AAC AVC][CHT][MP4]", "introduction": "<p>Torrent Info By: ANi API (Auto Generated)</p> <p>Subtitle:</p> <p>&emsp;HardSub</p> <p>Mediainfo:</p> <p>&emsp;Resolution: 1080P</p> <p>&emsp;Video Format: AVC</p> <p>&emsp;Audio Format: AAC</p> <br><p>Note:</p> <p>&emsp;Magnet link not contain any http source info. If you want to download the file asap, please use the torrent file rather than the magnet link.</p> <p>&emsp;Xunlei, torrent media player and offline downloader has been banned by default.</p> <p>&emsp;This torrent using the HTTP Sources for the first content distributor and the source file stored on IPFS</p> <p>&emsp;This automatic torrent publisher currently in beta test. If have any thought about this publisher. Feel free to contact me.</p> <p>&emsp;Telegram Chat: <a title=\"https://t.me/+SH8EUievFGLKQew_\" href=\"https://t.me/+SH8EUievFGLKQew_\" target=\"_blank\">https://t.me/+SH8EUievFGLKQew_</a></p> <p>2022/4/23 16:32:08 UTC+0000 (Coordinated Universal Time)</p>", "tag_ids": ["548ee2ce4ab7379536f56358", "6039092432f14c00074809b9", "55c3036c7030f8c855f992ee", "548ee1204ab7379536f56357", "548edffb4ab7379536f56352", "624774ab70e8f89b23a18584", "549ef207fe682f7549f1ea90"], "comments": 0, "downloads": 111, "finished": 475, "leechers": 0, "seeders": 13, "uploader_id": "5e43f999306f1a0007cd093f", "team_id": "60313a6e32f14c000745a5e2", "publish_time": "2022-04-23T16:32:10.858Z", "magnet": "magnet:?xt=urn:btih:e4d15be9b02d0bd4229f7928a91a9ffc1c73dfec", "infoHash": "e4d15be9b02d0bd4229f7928a91a9ffc1c73dfec", "file_id": "62642a0a3d5c31000733ef73", "teamsync": true, "content": [["[ANi] \u5973\u5fcd\u8005\u693f\u7684\u5fc3\u4e8b - 03 [1080P][Baha][WEB-DL][AAC AVC][CHT].mp4", "498.36 MB"]], "size": "498.36 MB", "btskey": "", "sync": {"dmhy": "http://share.dmhy.org/topics/view/598406_ANi_In_the_Heart_of_Kunoichi_Tsubaki_-_-_03_1080P_Baha_WEB-DL_AAC_AVC_CHT_MP4.html", "acgrip": "https://acg.rip/t/254318", "nyaa": "https://nyaa.si/view/1518876", "acgnx": "https://share.acgnx.se/show-e4d15be9b02d0bd4229f7928a91a9ffc1c73dfec.html"}}, {"_id": "6262866c3d5c31000730fc2d", "category_tag_id": "549ef207fe682f7549f1ea90", "title": "[\u5343\u590f\u5b57\u5e55\u7ec4&LoliHouse] \u5973\u5fcd\u8005\u5c0f\u693f\u7684\u5fc3\u4e8b / Kunoichi Tsubaki no Mune no Uchi - 02 [WebRip 1080p HEVC-10bit AAC][\u7b80\u7e41\u5185\u5c01\u5b57\u5e55]", "introduction": "<p><img src=\"https://s2.loli.net/2022/04/15/i8SPpZfYR7VeTQN.jpg\" style=\"width:1000px;height:1411px\"></p><p><strong>\u5973\u5fcd\u8005\u5c0f\u693f\u7684\u5fc3\u4e8b / Kunoichi Tsubaki no Mune no Uchi</strong></p><p><strong>\u5b57\u5e55\uff1a\u5343\u590f\u5b57\u5e55\u7ec4</strong></p><p><strong>\u811a\u672c\uff1a\u2588\u2588\u2588\u2588\u2588\u2588@LoliHouse</strong></p><p><strong>\u538b\u5236\uff1a\u2588\u2588\u2588\u2588\u2588\u2588@LoliHouse</strong></p><p><strong>\u672c\u7247\u4e0e<strong>\u5343\u590f\u5b57\u5e55\u7ec4</strong>\u5408\u4f5c\uff0c\u611f\u8c22\u5b57\u5e55\u7ec4\u7684\u8f9b\u52e4\u52b3\u52a8\u3002<br></strong></p><hr> <p><strong>\u4e3a\u4e86\u987a\u5229\u5730\u89c2\u770b\u6211\u4eec\u7684\u4f5c\u54c1\uff0c\u63a8\u8350\u5927\u5bb6\u4f7f\u7528\u4ee5\u4e0b\u64ad\u653e\u5668\uff1a</strong></p><p><strong>Windows\uff1a<a href=\"https://sourceforge.net/projects/mpcbe/\" target=\"_blank\">MPC-BE</a></strong></p><p><strong>macOS\uff1a<a href=\"https://lhc70000.github.io/iina/\" target=\"_blank\">IINA</a></strong></p><p><strong>iOS\uff1a<a href=\"https://itunes.apple.com/us/app/nplayer-lite/id1078835991?mt=8\" target=\"_blank\">nPlayer</a></strong></p><p><strong>Android\uff1a<a href=\"https://play.google.com/store/apps/details?id=com.mxtech.videoplayer.ad\" target=\"_blank\">MX Player<br></a></strong></p><hr><p></p><p><b><strong><b><strong><b><a href=\"https://share.dmhy.org/topics/view/533345_LoliHouse_LoliHouse_3rd_Anniversary_Gift_Part_1_Picture_Package_Wallpaper_112GB.html\" target=\"_blank\">\u70b9\u51fb\u67e5\u770bLoliHouse\u4e09\u5468\u5e74\u793c\u5305 (\u5176\u4e00)</a></b></strong></b></strong></b><br></p><p><b><strong><b><strong><b><strong><b><strong><b><a href=\"https://share.dmhy.org/topics/view/534469_LoliHouse_LoliHouse_3rd_Anniversary_Announcement.html\" target=\"_blank\">\u70b9\u51fb\u67e5\u770bLoliHouse\u4e09\u5468\u5e74\u7eaa\u5ff5\u516c\u544a</a></b></strong></b></strong></b><br></strong></b></strong></b></p><hr><p><b><strong></strong></b></p><p><strong><strong><b>\u4eba\u4eba\u4e3a\u6211\uff0c\u6211\u4e3a\u4eba\u4eba\uff0c\u4e3a\u4e86\u5404\u4f4d\u89c2\u4f17\u80fd\u5feb\u901f\u4e0b\u8f7d\uff0c\u8bf7\u4f7f\u7528<b> uTorrent / qBittorrent </b>\u7b49\u6b63\u89c4 BT \u8f6f\u4ef6\u4e0b\u8f7d\uff0c\u5e76\u4fdd\u6301\u5f00\u673a\u4e0a\u4f20\uff0c\u8c22\u8c22~</b></strong></strong></p>", "tag_ids": ["581be821ee98e9ca20730eae", "54bbe80a76870aad3bb603df", "624774ab70e8f89b23a18584", "548ee0ea4ab7379536f56354", "548ee1204ab7379536f56357", "548ee2ce4ab7379536f56358", "549ef207fe682f7549f1ea90", "55c3024a7030f8c855f992ed", "5ed5f6ad306f1a0007da8779"], "comments": 0, "downloads": 102, "finished": 418, "leechers": 0, "seeders": 26, "uploader_id": "5adb300b2e78648174ce0646", "team_id": "581b44bfee98e9ca20730e9a", "publish_time": "2022-04-22T10:41:48.973Z", "magnet": "magnet:?xt=urn:btih:359fcc714934f2d2bfc7b1c0efd5991eec78c74e", "infoHash": "359fcc714934f2d2bfc7b1c0efd5991eec78c74e", "file_id": "6262862d3d5c31000730fbc3", "teamsync": true, "content": [["[Airota&LoliHouse] Kunoichi Tsubaki no Mune no Uchi - 02 [WebRip 1080p HEVC-10bit AAC ASSx2].mkv", "623.24 MB"]], "size": "623.24 MB", "btskey": "", "sync": {"dmhy": "http://share.dmhy.org/topics/view/598249_LoliHouse_Kunoichi_Tsubaki_no_Mune_no_Uchi_-_02_WebRip_1080p_HEVC-10bit_AAC.html", "acgrip": "https://acg.rip/t/254205", "nyaa": "https://nyaa.si/view/1518105"}}, {"_id": "6262866a3d5c31000730fc28", "category_tag_id": "549ef207fe682f7549f1ea90", "title": "\u3010\u5343\u590f\u5b57\u5e55\u7d44\u3011\u3010\u5973\u5fcd\u8005\u5c0f\u693f\u7684\u5fc3\u4e8b_Kunoichi Tsubaki no Mune no Uchi\u3011[\u7b2c02\u8a71][1080p_AVC][\u7e41\u9ad4]", "introduction": "<p><img src=\"https://s2.loli.net/2022/04/15/i8SPpZfYR7VeTQN.jpg\" style=\"width:1000px;height:1411px\"></p>", "tag_ids": ["624774ab70e8f89b23a18584", "54bbe80a76870aad3bb603df", "548ee2ce4ab7379536f56358", "549ef207fe682f7549f1ea90", "55c3036c7030f8c855f992ee", "548ee1204ab7379536f56357"], "comments": 0, "downloads": 87, "finished": 341, "leechers": 0, "seeders": 6, "uploader_id": "5adb300b2e78648174ce0646", "team_id": "54bb896d76870aad3bb603cf", "publish_time": "2022-04-22T10:41:46.345Z", "magnet": "magnet:?xt=urn:btih:882c29e2a4d5f395a67ff6f8bcb658fa5388bcd1", "infoHash": "882c29e2a4d5f395a67ff6f8bcb658fa5388bcd1", "file_id": "6262863f3d5c31000730fbda", "teamsync": true, "content": [["[Airota][Kunoichi Tsubaki no Mune no Uchi][02][1080p AVC AAC][CHT].mp4", "494.41 MB"]], "size": "494.41 MB", "btskey": "", "sync": {"dmhy": "http://share.dmhy.org/topics/view/598248_Kunoichi_Tsubaki_no_Mune_no_Uchi_02_1080p_AVC.html", "acgrip": "https://acg.rip/t/254204"}}, {"_id": "6260cf0d3d5c3100072dfc49", "category_tag_id": "549ef207fe682f7549f1ea90", "title": "\u3010\u5343\u590f\u5b57\u5e55\u7ec4\u3011\u3010\u5973\u5fcd\u8005\u5c0f\u693f\u7684\u5fc3\u4e8b_Kunoichi Tsubaki no Mune no Uchi\u3011[\u7b2c02\u8bdd][1080p_AVC][\u7b80\u4f53]", "introduction": "<p><img src=\"https://s2.loli.net/2022/04/15/i8SPpZfYR7VeTQN.jpg\" style=\"width:1000px;height:1411px\"></p>", "tag_ids": ["54bbe80a76870aad3bb603df", "548ee0ea4ab7379536f56354", "548ee2ce4ab7379536f56358", "549ef207fe682f7549f1ea90", "55c3036c7030f8c855f992ee", "624774ab70e8f89b23a18584"], "comments": 0, "downloads": 110, "finished": 308, "leechers": 0, "seeders": 8, "uploader_id": "5adb300b2e78648174ce0646", "team_id": "54bb896d76870aad3bb603cf", "publish_time": "2022-04-21T03:27:09.320Z", "magnet": "magnet:?xt=urn:btih:d240b121d5240232e48419d2756565d7bcf73ce7", "infoHash": "d240b121d5240232e48419d2756565d7bcf73ce7", "file_id": "6260cf073d5c3100072dfc3b", "teamsync": true, "content": [["[Airota][Kunoichi Tsubaki no Mune no Uchi][02][1080p AVC AAC][CHS].mp4", "494.51 MB"]], "size": "494.51 MB", "btskey": "", "sync": {"dmhy": "http://share.dmhy.org/topics/view/598127_Kunoichi_Tsubaki_no_Mune_no_Uchi_02_1080p_AVC.html", "acgrip": "https://acg.rip/t/254126"}}, {"_id": "62609bae3d5c3100072d9dc0", "category_tag_id": "549ef207fe682f7549f1ea90", "title": "[\u5343\u590f\u5b57\u5e55\u7ec4&LoliHouse] \u5973\u5fcd\u8005\u5c0f\u693f\u7684\u5fc3\u4e8b / Kunoichi Tsubaki no Mune no Uchi - 01 [WebRip 1080p HEVC-10bit AAC][\u7b80\u7e41\u5185\u5c01\u5b57\u5e55]", "introduction": "<p><img src=\"https://s2.loli.net/2022/04/15/i8SPpZfYR7VeTQN.jpg\" style=\"width:1000px;height:1411px\"></p><p><strong>\u5973\u5fcd\u8005\u5c0f\u693f\u7684\u5fc3\u4e8b / Kunoichi Tsubaki no Mune no Uchi</strong></p><p><strong>\u5b57\u5e55\uff1a\u5343\u590f\u5b57\u5e55\u7ec4</strong></p><p><strong>\u811a\u672c\uff1a\u2588\u2588\u2588\u2588\u2588\u2588@LoliHouse</strong></p><p><strong>\u538b\u5236\uff1a\u2588\u2588\u2588\u2588\u2588\u2588@LoliHouse</strong></p><p><strong>\u672c\u7247\u4e0e<strong>\u5343\u590f\u5b57\u5e55\u7ec4</strong>\u5408\u4f5c\uff0c\u611f\u8c22\u5b57\u5e55\u7ec4\u7684\u8f9b\u52e4\u52b3\u52a8\u3002<br></strong></p><hr><p></p> <p><strong>\u4e3a\u4e86\u987a\u5229\u5730\u89c2\u770b\u6211\u4eec\u7684\u4f5c\u54c1\uff0c\u63a8\u8350\u5927\u5bb6\u4f7f\u7528\u4ee5\u4e0b\u64ad\u653e\u5668\uff1a</strong></p><p><strong>Windows\uff1a<a href=\"https://sourceforge.net/projects/mpcbe/\" target=\"_blank\">MPC-BE</a></strong></p><p><strong>macOS\uff1a<a href=\"https://lhc70000.github.io/iina/\" target=\"_blank\">IINA</a></strong></p><p><strong>iOS\uff1a<a href=\"https://itunes.apple.com/us/app/nplayer-lite/id1078835991?mt=8\" target=\"_blank\">nPlayer</a></strong></p><p><strong>Android\uff1a<a href=\"https://play.google.com/store/apps/details?id=com.mxtech.videoplayer.ad\" target=\"_blank\">MX Player<br></a></strong></p><hr><p><strong></strong></p><p><b><strong><b><strong><b><a href=\"https://share.dmhy.org/topics/view/533345_LoliHouse_LoliHouse_3rd_Anniversary_Gift_Part_1_Picture_Package_Wallpaper_112GB.html\" target=\"_blank\">\u70b9\u51fb\u67e5\u770bLoliHouse\u4e09\u5468\u5e74\u793c\u5305 (\u5176\u4e00)</a></b></strong></b></strong></b><br></p><p><b><strong><b><strong><b><strong><b><strong><b><a href=\"https://share.dmhy.org/topics/view/534469_LoliHouse_LoliHouse_3rd_Anniversary_Announcement.html\" target=\"_blank\">\u70b9\u51fb\u67e5\u770bLoliHouse\u4e09\u5468\u5e74\u7eaa\u5ff5\u516c\u544a</a></b></strong></b></strong></b><br></strong></b></strong></b></p><hr><p><b><strong><b></b></strong></b></p><p><strong><strong><b>\u4eba\u4eba\u4e3a\u6211\uff0c\u6211\u4e3a\u4eba\u4eba\uff0c\u4e3a\u4e86\u5404\u4f4d\u89c2\u4f17\u80fd\u5feb\u901f\u4e0b\u8f7d\uff0c\u8bf7\u4f7f\u7528<b> uTorrent / qBittorrent </b>\u7b49\u6b63\u89c4 BT \u8f6f\u4ef6\u4e0b\u8f7d\uff0c\u5e76\u4fdd\u6301\u5f00\u673a\u4e0a\u4f20\uff0c\u8c22\u8c22~</b></strong></strong></p>", "tag_ids": ["548ee2ce4ab7379536f56358", "581be821ee98e9ca20730eae", "54bbe80a76870aad3bb603df", "624774ab70e8f89b23a18584", "5ed5f6ad306f1a0007da8779", "55c3024a7030f8c855f992ed", "548ee0ea4ab7379536f56354", "548ee1204ab7379536f56357", "549ef207fe682f7549f1ea90"], "comments": 0, "downloads": 106, "finished": 437, "leechers": 0, "seeders": 21, "uploader_id": "5adb300b2e78648174ce0646", "team_id": "581b44bfee98e9ca20730e9a", "publish_time": "2022-04-20T23:47:58.529Z", "magnet": "magnet:?xt=urn:btih:616ac721b98dd1d6311dfb00aaca1300a0a82684", "infoHash": "616ac721b98dd1d6311dfb00aaca1300a0a82684", "file_id": "62609aeb3d5c3100072d9c3e", "teamsync": true, "content": [["[Airota&LoliHouse] Kunoichi Tsubaki no Mune no Uchi - 01 [WebRip 1080p HEVC-10bit AAC ASSx2].mkv", "569.81 MB"]], "size": "569.81 MB", "btskey": "", "sync": {"dmhy": "http://share.dmhy.org/topics/view/598110_LoliHouse_Kunoichi_Tsubaki_no_Mune_no_Uchi_-_01_WebRip_1080p_HEVC-10bit_AAC.html", "acgrip": "https://acg.rip/t/254111", "nyaa": "https://nyaa.si/view/1517591"}}, {"_id": "625af7acb368e1000746a4d9", "category_tag_id": "549ef207fe682f7549f1ea90", "title": "[Lilith-Raws x WitEx.io] \u5973\u5fcd\u8005\u693f\u7684\u5fc3\u4e8b / Kunoichi Tsubaki no Mune no Uchi - 02 [Baha][WEB-DL][1080p][AVC AAC][CHT][MP4]", "introduction": "<p>Telegram Update Notification Channel : <a href=\"https://t.me/lilithraws\">https://t.me/lilithraws</a><br>Open Data Platform : <a href=\"https://open.lilithraws.cf\">https://open.lilithraws.cf</a> (Support Streaming and Direct Download)<br>Twitter : <a href=\"https://twitter.com/lilithraws\">https://twitter.com/lilithraws</a></p><p>We're recommending <a href=\"https://github.com/c0re100/qBittorrent-Enhanced-Edition/releases\">qBittorrent Enhanced Edition</a> for downloading our seeds.<br><a href=\"https://bit.ly/lilithcrypto\"><img src=\"https://p.sda1.dev/5/be21c667794f31f409f5367a9d12e6bc\" alt=\"Lilith Crypto Banner\"></a><br>You can buy cryptos on WitEx -&gt; <a href=\"https://bit.ly/lilithwitex\">https://witex.io</a></p><p>Paypal Donation -&gt; <a href=\"https://donorbox.org/lilithraws\">https://donorbox.org/lilithraws</a><br>Support Us on Patreon -&gt; <a href=\"https://www.patreon.com/lilithraws\">https://www.patreon.com/lilithraws</a></p>", "tag_ids": ["548ee2ce4ab7379536f56358", "55c3036c7030f8c855f992ee", "548ee1204ab7379536f56357", "5d8b3245306f1a0007bd7aca", "548edffb4ab7379536f56352", "624774ab70e8f89b23a18584", "549ef207fe682f7549f1ea90"], "comments": 0, "downloads": 275, "finished": 2982, "leechers": 0, "seeders": 32, "uploader_id": "5d333d66306f1a0007b6c0bf", "team_id": "5d8b24be306f1a0007bd7998", "publish_time": "2022-04-16T17:06:52.289Z", "magnet": "magnet:?xt=urn:btih:f74ff2d836b4253dc70177d9a1079557c791a6b3", "infoHash": "f74ff2d836b4253dc70177d9a1079557c791a6b3", "file_id": "625af7aab368e1000746a4d4", "teamsync": true, "content": [["[Lilith-Raws] Kunoichi Tsubaki no Mune no Uchi - 02 [Baha][WEB-DL][1080p][AVC AAC][CHT][MP4].mp4", "510.9 MB"]], "size": "510.9 MB", "btskey": "", "sync": {"dmhy": "http://share.dmhy.org/topics/view/597665_Lilith-Raws_x_WitEx_io_Kunoichi_Tsubaki_no_Mune_no_Uchi_-_02_Baha_WEB-DL_1080p_AVC_AAC_CHT_MP4.html", "acgrip": "https://acg.rip/t/253848", "acgnx": "https://share.acgnx.se/show-f74ff2d836b4253dc70177d9a1079557c791a6b3.html"}}, {"_id": "625af08fb368e100074697a6", "category_tag_id": "549ef207fe682f7549f1ea90", "title": "[ANi] In the Heart of Kunoichi Tsubaki -  \u5973\u5fcd\u8005\u693f\u7684\u5fc3\u4e8b - 02 [1080P][Baha][WEB-DL][AAC AVC][CHT][MP4]", "introduction": "<p>Torrent Info By: ANi API (Auto Generated)</p> <p>Subtitle:</p> <p>&emsp;HardSub</p> <p>Mediainfo:</p> <p>&emsp;Resolution: 1080P</p> <p>&emsp;Video Format: AVC</p> <p>&emsp;Audio Format: AAC</p> <br><p>Note:</p> <p>&emsp;Magnet link not contain any http source info. If you want to download the file asap, please use the torrent file rather than the magnet link.</p> <p>&emsp;Xunlei, torrent media player and offline downloader has been banned by default.</p> <p>&emsp;This torrent using the HTTP Sources for the first content distributor and the source file stored on IPFS</p> <p>&emsp;This automatic torrent publisher currently in beta test. If have any thought about this publisher. Feel free to contact me.</p> <p>&emsp;Telegram Chat: <a title=\"https://t.me/+SH8EUievFGLKQew_\" href=\"https://t.me/+SH8EUievFGLKQew_\" target=\"_blank\">https://t.me/+SH8EUievFGLKQew_</a></p> <p>2022/4/16 16:36:29 UTC+0000 (Coordinated Universal Time)</p>", "tag_ids": ["548ee2ce4ab7379536f56358", "6039092432f14c00074809b9", "55c3036c7030f8c855f992ee", "548ee1204ab7379536f56357", "548edffb4ab7379536f56352", "624774ab70e8f89b23a18584", "549ef207fe682f7549f1ea90"], "comments": 0, "downloads": 106, "finished": 440, "leechers": 0, "seeders": 11, "uploader_id": "5e43f999306f1a0007cd093f", "team_id": "60313a6e32f14c000745a5e2", "publish_time": "2022-04-16T16:36:31.288Z", "magnet": "magnet:?xt=urn:btih:abb2e8cd36ae01e27d625be32a345fcf1d268748", "infoHash": "abb2e8cd36ae01e27d625be32a345fcf1d268748", "file_id": "625af08fb368e100074697a5", "teamsync": true, "content": [["[ANi] \u5973\u5fcd\u8005\u693f\u7684\u5fc3\u4e8b - 02 [1080P][Baha][WEB-DL][AAC AVC][CHT].mp4", "511.22 MB"]], "size": "511.22 MB", "btskey": "", "sync": {"dmhy": "http://share.dmhy.org/topics/view/597659_ANi_In_the_Heart_of_Kunoichi_Tsubaki_-_-_02_1080P_Baha_WEB-DL_AAC_AVC_CHT_MP4.html", "acgrip": "https://acg.rip/t/253842", "nyaa": "https://nyaa.si/view/1515799", "acgnx": "https://share.acgnx.se/show-abb2e8cd36ae01e27d625be32a345fcf1d268748.html"}}, {"_id": "625aefafb368e100074695d8", "category_tag_id": "549ef207fe682f7549f1ea90", "title": "[NC-Raws] \u5973\u5fcd\u8005\u693f\u7684\u5fc3\u4e8b / Kunoichi Tsubaki no Mune no Uchi - 02 (Baha 1920x1080 AVC AAC MP4)", "introduction": "<p style=\"text-align:center\"><img src=\"https://s2.loli.net/2022/04/17/WjNHLq4OStmagJs.jpg\" alt=\"https://s2.loli.net/2022/04/17/WjNHLq4OStmagJs.jpg\"></p><p style=\"text-align:center\">Watch on Telegram Channel: <a href=\"https://t.me/NC_Raws_Channel\" target=\"view_window\">https://t.me/NC_Raws_Channel</a></p><p style=\"text-align:center\">Auto-generated by NC-Raws.</p><p style=\"text-align:center\">Subtitle Language: \u4e2d\u6587\uff08\u7e41\u9ad4\uff09</p><p style=\"text-align:center\">Note: Xunlei has been banned by default.</p><p style=\"text-align:center\">Feel free to donate<br>BTC =&gt; 18aMQdjsAni1gbGk1Qvi12oFZTbdwT6E3p<br>ETH =&gt; 0xE766aC6e44d5Ab05534611583B38C7F1c897501a<br>USDT-TRC20 =&gt; TC7P5msV5PyAsnMeCcCEgkCZ7Mpgf4vspW<br><br>PayPal Donation =&gt; <a href=\"https://ko-fi.com/NC_Raws_Channel\" target=\"view_window\">NC-Raws@Ko-fi</a></p>", "tag_ids": ["548ee2ce4ab7379536f56358", "55c3036c7030f8c855f992ee", "548edffb4ab7379536f56352", "600c009432f14c00073a9f49", "624774ab70e8f89b23a18584", "549ef207fe682f7549f1ea90"], "comments": 0, "downloads": 128, "finished": 1036, "leechers": 0, "seeders": 6, "uploader_id": "60098e9132f14c000739f8f4", "team_id": "60098fb532f14c000739f911", "publish_time": "2022-04-16T16:32:47.608Z", "magnet": "magnet:?xt=urn:btih:16a9d4578d1a47dcebc2725c5ff6610067ad7916", "infoHash": "16a9d4578d1a47dcebc2725c5ff6610067ad7916", "file_id": "625aefafb368e100074695d7", "teamsync": true, "content": [["[NC-Raws] \u5973\u5fcd\u8005\u693f\u7684\u5fc3\u4e8b - 02 (Baha 1920x1080 AVC AAC MP4).mp4", "511.06 MB"]], "size": "511.06 MB", "btskey": "", "sync": {"dmhy": "http://share.dmhy.org/topics/view/597657_NC-Raws_Kunoichi_Tsubaki_no_Mune_no_Uchi_-_02_Baha_1920x1080_AVC_AAC_MP4.html", "acgrip": "https://acg.rip/t/253840", "acgnx": "https://share.acgnx.se/show-16a9d4578d1a47dcebc2725c5ff6610067ad7916.html"}}, {"_id": "625aef5bb368e10007469525", "category_tag_id": "549ef207fe682f7549f1ea90", "title": "[NC-Raws] \u5973\u5fcd\u8005\u693f\u7684\u5fc3\u4e8b / Kunoichi Tsubaki no Mune no Uchi - 02 (B-Global 1920x1080 HEVC AAC MKV)", "introduction": "<p style=\"text-align:center\"><img src=\"https://s2.loli.net/2022/04/17/GzWqxDCuairNXoZ.jpg\" alt=\"https://s2.loli.net/2022/04/17/GzWqxDCuairNXoZ.jpg\"></p><p style=\"text-align:center\">Watch on Telegram Channel: <a href=\"https://t.me/NC_Raws_Channel\" target=\"view_window\">https://t.me/NC_Raws_Channel</a></p><p style=\"text-align:center\">Auto-generated by NC-Raws.</p><p style=\"text-align:center\">Subtitle Language: ['English', '\u0e20\u0e32\u0e29\u0e32\u0e44\u0e17\u0e22', 'Ti\u1ebfng Vi\u1ec7t', 'Bahasa Indonesia']</p><p style=\"text-align:center\">Note: Xunlei has been banned by default.</p><p style=\"text-align:center\">Feel free to donate<br>BTC =&gt; 18aMQdjsAni1gbGk1Qvi12oFZTbdwT6E3p<br>ETH =&gt; 0xE766aC6e44d5Ab05534611583B38C7F1c897501a<br>USDT-TRC20 =&gt; TC7P5msV5PyAsnMeCcCEgkCZ7Mpgf4vspW<br><br>PayPal Donation =&gt; <a href=\"https://ko-fi.com/NC_Raws_Channel\" target=\"view_window\">NC-Raws@Ko-fi</a></p>", "tag_ids": ["548ee2ce4ab7379536f56358", "55c3024a7030f8c855f992ed", "548ee00b4ab7379536f56353", "600c009432f14c00073a9f49", "624774ab70e8f89b23a18584", "549ef207fe682f7549f1ea90"], "comments": 0, "downloads": 79, "finished": 118, "leechers": 0, "seeders": 4, "uploader_id": "60098e9132f14c000739f8f4", "team_id": "60098fb532f14c000739f911", "publish_time": "2022-04-16T16:31:23.720Z", "magnet": "magnet:?xt=urn:btih:161d05f76d3b278a9779b205c31d4dc8ad261210", "infoHash": "161d05f76d3b278a9779b205c31d4dc8ad261210", "file_id": "625aef5bb368e10007469524", "teamsync": true, "content": [["[NC-Raws] \u5973\u5fcd\u8005\u693f\u7684\u5fc3\u4e8b - 02 (B-Global 1920x1080 HEVC AAC MKV).mkv", "645.67 MB"]], "size": "645.67 MB", "btskey": "", "sync": {"dmhy": "http://share.dmhy.org/topics/view/597656_NC-Raws_Kunoichi_Tsubaki_no_Mune_no_Uchi_-_02_B-Global_1920x1080_HEVC_AAC_MKV.html", "acgrip": "https://acg.rip/t/253839", "acgnx": "https://share.acgnx.se/show-161d05f76d3b278a9779b205c31d4dc8ad261210.html"}}, {"_id": "62593d5a5aa87000078e7abb", "category_tag_id": "549ef207fe682f7549f1ea90", "title": "\u3010\u5343\u590f\u5b57\u5e55\u7d44\u3011\u3010\u5973\u5fcd\u8005\u5c0f\u693f\u7684\u5fc3\u4e8b_Kunoichi Tsubaki no Mune no Uchi\u3011[\u7b2c01\u8a71][1080p_AVC][\u7e41\u9ad4]", "introduction": "<p><img src=\"https://s2.loli.net/2022/04/15/i8SPpZfYR7VeTQN.jpg\" style=\"width:1000px;height:1411px\"></p>", "tag_ids": ["624774ab70e8f89b23a18584", "54bbe80a76870aad3bb603df", "548ee0ea4ab7379536f56354", "548ee2ce4ab7379536f56358", "549ef207fe682f7549f1ea90", "55c3036c7030f8c855f992ee", "548ee1204ab7379536f56357"], "comments": 0, "downloads": 99, "finished": 444, "leechers": 0, "seeders": 5, "uploader_id": "5adb300b2e78648174ce0646", "team_id": "54bb896d76870aad3bb603cf", "publish_time": "2022-04-15T09:39:38.199Z", "magnet": "magnet:?xt=urn:btih:77fa6a3e2a9aa078de6b35c717e46eeca2b9693e", "infoHash": "77fa6a3e2a9aa078de6b35c717e46eeca2b9693e", "file_id": "62593d3e5aa87000078e7a90", "teamsync": true, "content": [["[Airota][Kunoichi Tsubaki no Mune no Uchi][01][1080p AVC AAC][CHT].mp4", "608.95 MB"]], "size": "608.95 MB", "btskey": "", "sync": {"dmhy": "http://share.dmhy.org/topics/view/597505_Kunoichi_Tsubaki_no_Mune_no_Uchi_01_1080p_AVC.html", "acgrip": "https://acg.rip/t/253727"}}, {"_id": "62591ecd5aa87000078e4f20", "category_tag_id": "549ef207fe682f7549f1ea90", "title": "\u3010\u5343\u590f\u5b57\u5e55\u7ec4\u3011\u3010\u5973\u5fcd\u8005\u5c0f\u693f\u7684\u5fc3\u4e8b_Kunoichi Tsubaki no Mune no Uchi\u3011[\u7b2c01\u8bdd][1080p_AVC][\u7b80\u4f53]", "introduction": "<p><img src=\"https://s2.loli.net/2022/04/15/i8SPpZfYR7VeTQN.jpg\" style=\"width:1000px;height:1411px\"></p>", "tag_ids": ["548ee2ce4ab7379536f56358", "55c3036c7030f8c855f992ee", "624774ab70e8f89b23a18584", "54bbe80a76870aad3bb603df", "548ee0ea4ab7379536f56354", "549ef207fe682f7549f1ea90"], "comments": 0, "downloads": 114, "finished": 315, "leechers": 0, "seeders": 13, "uploader_id": "5adb300b2e78648174ce0646", "team_id": "54bb896d76870aad3bb603cf", "publish_time": "2022-04-15T07:29:17.577Z", "magnet": "magnet:?xt=urn:btih:f679caadf2eec938219c2e61606f267e0da1f78c", "infoHash": "f679caadf2eec938219c2e61606f267e0da1f78c", "file_id": "62591ecd5aa87000078e4f1f", "teamsync": true, "content": [["[Airota][Kunoichi Tsubaki no Mune no Uchi][01][1080p AVC AAC][CHS].mp4", "609.24 MB"]], "size": "609.24 MB", "btskey": "", "sync": {"dmhy": "http://share.dmhy.org/topics/view/597495_Kunoichi_Tsubaki_no_Mune_no_Uchi_01_1080p_AVC.html", "acgrip": "https://acg.rip/t/253722"}}, {"_id": "6251b5415aa8700007835126", "category_tag_id": "549ef207fe682f7549f1ea90", "title": "[Lilith-Raws x WitEx.io] \u5973\u5fcd\u8005\u693f\u7684\u5fc3\u4e8b / Kunoichi Tsubaki no Mune no Uchi - 01 [Baha][WEB-DL][1080p][AVC AAC][CHT][MP4]", "introduction": "<p>Telegram Update Notification Channel : <a href=\"https://t.me/lilithraws\">https://t.me/lilithraws</a><br>Open Data Platform : <a href=\"https://open.lilithraws.cf\">https://open.lilithraws.cf</a> (Support Streaming and Direct Download)<br>Twitter : <a href=\"https://twitter.com/lilithraws\">https://twitter.com/lilithraws</a></p><p>We're recommending <a href=\"https://github.com/c0re100/qBittorrent-Enhanced-Edition/releases\">qBittorrent Enhanced Edition</a> for downloading our seeds.<br><a href=\"https://bit.ly/lilithcrypto\"><img src=\"https://p.sda1.dev/5/be21c667794f31f409f5367a9d12e6bc\" alt=\"Lilith Crypto Banner\"></a><br>You can buy cryptos on WitEx -&gt; <a href=\"https://bit.ly/lilithwitex\">https://witex.io</a></p><p>Paypal Donation -&gt; <a href=\"https://donorbox.org/lilithraws\">https://donorbox.org/lilithraws</a><br>Support Us on Patreon -&gt; <a href=\"https://www.patreon.com/lilithraws\">https://www.patreon.com/lilithraws</a></p>", "tag_ids": ["548ee2ce4ab7379536f56358", "55c3036c7030f8c855f992ee", "548ee1204ab7379536f56357", "5d8b3245306f1a0007bd7aca", "548edffb4ab7379536f56352", "624774ab70e8f89b23a18584", "549ef207fe682f7549f1ea90"], "comments": 0, "downloads": 320, "finished": 4140, "leechers": 0, "seeders": 41, "uploader_id": "5d333d66306f1a0007b6c0bf", "team_id": "5d8b24be306f1a0007bd7998", "publish_time": "2022-04-09T16:33:05.223Z", "magnet": "magnet:?xt=urn:btih:ac3f93851e9d89b0628896b2d3be2a61c61b62aa", "infoHash": "ac3f93851e9d89b0628896b2d3be2a61c61b62aa", "file_id": "6251b5395aa8700007835118", "teamsync": true, "content": [["[Lilith-Raws] Kunoichi Tsubaki no Mune no Uchi - 01 [Baha][WEB-DL][1080p][AVC AAC][CHT][MP4].mp4", "543.53 MB"]], "size": "543.53 MB", "btskey": "", "sync": {"dmhy": "http://share.dmhy.org/topics/view/597006_Lilith-Raws_Kunoichi_Tsubaki_no_Mune_no_Uchi_-_01_Baha_WEB-DL_1080p_AVC_AAC_CHT_MP4.html", "acgrip": "https://acg.rip/t/253409", "acgnx": "https://share.acgnx.se/show-ac3f93851e9d89b0628896b2d3be2a61c61b62aa.html"}}, {"_id": "6251b53d5aa870000783511e", "category_tag_id": "549ef207fe682f7549f1ea90", "title": "[ANi] In the Heart of Kunoichi Tsubaki - \u5973\u5fcd\u8005\u693f\u7684\u5fc3\u4e8b[01][1080P][Baha][WEB-DL][AAC AVC][MP4]", "introduction": "<p>Torrent Info By: ANi API (Auto Generated)</p> <p>Subtitle:</p> <p>&emsp;HardSub</p> <p>Mediainfo:</p> <p>&emsp;Resolution: 1080P</p> <p>&emsp;Video Format: AVC</p> <p>&emsp;Audio Format: AAC</p> <br><p>Note:</p> <p>&emsp;Magnet link not contain any http source info. If you want to download the file asap, please use the torrent file rather than the magnet link.</p> <p>&emsp;Xunlei, torrent media player and offline downloader has been banned by default.</p> <p>&emsp;This torrent using the HTTP Sources for the first content distributor and the source file stored on IPFS</p> <p>&emsp;This automatic torrent publisher currently in beta test. If have any thought about this publisher. Feel free to contact me.</p> <p>&emsp;Telegram Chat: <a title=\"https://t.me/+SH8EUievFGLKQew_\" href=\"https://t.me/+SH8EUievFGLKQew_\" target=\"_blank\">https://t.me/+SH8EUievFGLKQew_</a></p> <p>2022/4/9 16:33:00 UTC+0000 (Coordinated Universal Time)</p>", "tag_ids": ["548ee2ce4ab7379536f56358", "6039092432f14c00074809b9", "55c3036c7030f8c855f992ee", "548edffb4ab7379536f56352", "624774ab70e8f89b23a18584", "549ef207fe682f7549f1ea90"], "comments": 0, "downloads": 130, "finished": 573, "leechers": 0, "seeders": 9, "uploader_id": "5e43f999306f1a0007cd093f", "team_id": "60313a6e32f14c000745a5e2", "publish_time": "2022-04-09T16:33:01.141Z", "magnet": "magnet:?xt=urn:btih:95beca800ceb77f70d2799bb371949800aefd7b4", "infoHash": "95beca800ceb77f70d2799bb371949800aefd7b4", "file_id": "6251b53d5aa870000783511d", "teamsync": true, "content": [["[ANi]\u5973\u5fcd\u8005\u693f\u7684\u5fc3\u4e8b[01][1080P][Baha][WEB-DL].mp4", "543.84 MB"]], "size": "543.84 MB", "btskey": "", "sync": {"dmhy": "http://share.dmhy.org/topics/view/597005_ANi_In_the_Heart_of_Kunoichi_Tsubaki_-_01_1080P_Baha_WEB-DL_AAC_AVC_MP4.html", "acgrip": "https://acg.rip/t/253408", "nyaa": "https://nyaa.si/view/1512594", "acgnx": "https://share.acgnx.se/show-95beca800ceb77f70d2799bb371949800aefd7b4.html"}}, {"_id": "6251b4f75aa87000078350b1", "category_tag_id": "549ef207fe682f7549f1ea90", "title": "[NC-Raws] \u5973\u5fcd\u8005\u693f\u7684\u5fc3\u4e8b / Kunoichi Tsubaki no Mune no Uchi - 01 (Baha 1920x1080 AVC AAC MP4)", "introduction": "<p style=\"text-align:center\"><img src=\"https://s2.loli.net/2022/04/10/rKo8JUwLVWDPGEe.jpg\" alt=\"https://s2.loli.net/2022/04/10/rKo8JUwLVWDPGEe.jpg\"></p><p style=\"text-align:center\">Watch on Telegram Channel: <a href=\"https://t.me/NC_Raws_Channel\" target=\"view_window\">https://t.me/NC_Raws_Channel</a></p><p style=\"text-align:center\">Auto-generated by NC-Raws.</p><p style=\"text-align:center\">Subtitle Language: \u4e2d\u6587\uff08\u7e41\u9ad4\uff09</p><p style=\"text-align:center\">Note: Xunlei has been banned by default.</p><p style=\"text-align:center\">Feel free to donate<br>BTC =&gt; 18aMQdjsAni1gbGk1Qvi12oFZTbdwT6E3p<br>ETH =&gt; 0xE766aC6e44d5Ab05534611583B38C7F1c897501a<br>USDT-TRC20 =&gt; TC7P5msV5PyAsnMeCcCEgkCZ7Mpgf4vspW<br><br>PayPal Donation =&gt; <a href=\"https://ko-fi.com/NC_Raws_Channel\" target=\"view_window\">NC-Raws@Ko-fi</a></p>", "tag_ids": ["548ee2ce4ab7379536f56358", "55c3036c7030f8c855f992ee", "548edffb4ab7379536f56352", "600c009432f14c00073a9f49", "624774ab70e8f89b23a18584", "549ef207fe682f7549f1ea90"], "comments": 0, "downloads": 161, "finished": 1195, "leechers": 0, "seeders": 9, "uploader_id": "60098e9132f14c000739f8f4", "team_id": "60098fb532f14c000739f911", "publish_time": "2022-04-09T16:31:51.648Z", "magnet": "magnet:?xt=urn:btih:fd92629cea9c78df90327a21e0a913dd17df0347", "infoHash": "fd92629cea9c78df90327a21e0a913dd17df0347", "file_id": "6251b4f75aa87000078350b0", "teamsync": true, "content": [["[NC-Raws] \u5973\u5fcd\u8005\u693f\u7684\u5fc3\u4e8b - 01 (Baha 1920x1080 AVC AAC MP4).mp4", "543.69 MB"]], "size": "543.69 MB", "btskey": "", "sync": {"dmhy": "http://share.dmhy.org/topics/view/597004_NC-Raws_Kunoichi_Tsubaki_no_Mune_no_Uchi_-_01_Baha_1920x1080_AVC_AAC_MP4.html", "acgrip": "https://acg.rip/t/253407", "acgnx": "https://share.acgnx.se/show-fd92629cea9c78df90327a21e0a913dd17df0347.html"}}, {"_id": "6251b4df5aa870000783508c", "category_tag_id": "549ef207fe682f7549f1ea90", "title": "[NC-Raws] \u5973\u5fcd\u8005\u693f\u7684\u5fc3\u4e8b / Kunoichi Tsubaki no Mune no Uchi - 01 (B-Global 1920x1080 HEVC AAC MKV)", "introduction": "<p style=\"text-align:center\"><img src=\"https://s2.loli.net/2022/04/10/uGlpRt5SY1H4jCk.jpg\" alt=\"https://s2.loli.net/2022/04/10/uGlpRt5SY1H4jCk.jpg\"></p><p style=\"text-align:center\">Watch on Telegram Channel: <a href=\"https://t.me/NC_Raws_Channel\" target=\"view_window\">https://t.me/NC_Raws_Channel</a></p><p style=\"text-align:center\">Auto-generated by NC-Raws.</p><p style=\"text-align:center\">Subtitle Language: ['English', '\u0e20\u0e32\u0e29\u0e32\u0e44\u0e17\u0e22', 'Ti\u1ebfng Vi\u1ec7t', 'Bahasa Indonesia']</p><p style=\"text-align:center\">Note: Xunlei has been banned by default.</p><p style=\"text-align:center\">Feel free to donate<br>BTC =&gt; 18aMQdjsAni1gbGk1Qvi12oFZTbdwT6E3p<br>ETH =&gt; 0xE766aC6e44d5Ab05534611583B38C7F1c897501a<br>USDT-TRC20 =&gt; TC7P5msV5PyAsnMeCcCEgkCZ7Mpgf4vspW<br><br>PayPal Donation =&gt; <a href=\"https://ko-fi.com/NC_Raws_Channel\" target=\"view_window\">NC-Raws@Ko-fi</a></p>", "tag_ids": ["548ee2ce4ab7379536f56358", "55c3024a7030f8c855f992ed", "548ee00b4ab7379536f56353", "600c009432f14c00073a9f49", "624774ab70e8f89b23a18584", "549ef207fe682f7549f1ea90"], "comments": 0, "downloads": 90, "finished": 262, "leechers": 0, "seeders": 8, "uploader_id": "60098e9132f14c000739f8f4", "team_id": "60098fb532f14c000739f911", "publish_time": "2022-04-09T16:31:27.050Z", "magnet": "magnet:?xt=urn:btih:57f21053e058e2352e15ce5c23bb6cc85ac65b76", "infoHash": "57f21053e058e2352e15ce5c23bb6cc85ac65b76", "file_id": "6251b4df5aa870000783508b", "teamsync": true, "content": [["[NC-Raws] \u5973\u5fcd\u8005\u693f\u7684\u5fc3\u4e8b - 01 (B-Global 1920x1080 HEVC AAC MKV).mkv", "651.03 MB"]], "size": "651.03 MB", "btskey": "", "sync": {"dmhy": "http://share.dmhy.org/topics/view/597003_NC-Raws_Kunoichi_Tsubaki_no_Mune_no_Uchi_-_01_B-Global_1920x1080_HEVC_AAC_MKV.html", "acgrip": "https://acg.rip/t/253406", "acgnx": "https://share.acgnx.se/show-57f21053e058e2352e15ce5c23bb6cc85ac65b76.html"}}]